Workbook

Sheet COVER SHEET
A1: This workbook describes all the demand side input data for the Python model.
A2: In an effort to create this model with as much open-source data as possible, numerous simplifications and assumption had to be taken. These are tracked as far as possible, but a few sub-models that feed into this input workbook could not directly be included herein.
A5: Sheet name | B5: Discription
A6: Sankey | B6: Material flow Sankey across life cycle stage
A7: Final Exhibits | B7: Demand side summary figures as shown in Planet Positive Chemicals
A8: Job + CO2 Analysis | B8: Jobs creation & CO2 emissions of demand side measures
A9: Side calc. | B9: Useful side calculation
A10: Yearly Summary | B10: Yearly demand by chemical and pyrolysis oil availability across scenarios
A11: Yearly XX | B11: Yearly mass flow breakdown and demand evolution by chemical
A12: Scope 3 Summary | B12: Scope 3 emissions factors by chemical/year
A13: Scope 3 Yearly | B13: Scope 3 emissions factors by end of life treatment
A14: Per Capita Plastic | B14: Geographical per capita plastics demand analysis & comparison
A15: Yearly Demand XX | B15: Demand baseline assumptions per chemical
A16: Demand Breakdown | B16: Demand breakdown by sub chemicals & applications
... A23: Sankey XX | B23: Sankey of demand breakdown by chemical

Sheet Sankey
A1: Sankey - For Carbon only !!
A2: For 2020
B3: Box #1 Feedstock | F3: Box #2: Chemical Production | J3: Box #3: Product Manufacturing | N3: Box #4: Use Phase | R3: Box #5: End-of-use
B4: Mt in 2050 | C4: % | F4: Mt in 2050 | G4: % | J4: Mt in 2050 | K4: % | N4: Mt in 2050 | O4: % | R4: Mt in 2050 | S4: %
A5: Fossil | B5: =C5*$B$10 -> 486.18905 | C5: 0.995 | E5: Depolymerization | F5: =R6 -> 0 | G5: =F5/$F$28 -> 0 | I5: Mechanical recycling | J5: ='Job + CO2 Analysis'!D22 -> 30.3155 | K5: =J5/$F$41 -> 0.060382142 | M5: Resuse | N5: ='Final Exhibits'!H5 -> 0 | O5: =N5/$N$7 -> 0 | Q5: Mechanical recycling | R5: ='Job + CO2 Analysis'!D22 -> 30.3155 | S5: =R5/SUM($R$35) -> 0.042741914
A6: Biomass | B6: =C6*$B$10 -> 2.443161 | C6: 0.005 | E6: Chemical production | F6: =SUM('Final Exhibits'!B4:B10)-19 -> 488.63221 | G6: =F6/$F$7 -> 1 | I6: Product Manufacturing | J6: =F7 -> 488.63221 | K6: =J6/$J$7 -> 0.94158275 | M6: Use | N6: =J7 -> 518.94771 | O6: =N6/$N$7 -> 1 | Q6: Depolymerization | R6: ='Job + CO2 Analysis'!BN3 -> 0 | S6: =R6/SUM($R$35) -> 0
A7: Point Source | B7: =C7*$B$31 -> 0 | C7: 0 | E7: Total production: | F7: =SUM(F5:F6) -> 488.63221 | G7: =F7/$F$7 -> 1 | I7: Total manufacturing: | J7: =SUM(J5:J6) -> 518.94771 | K7: =J7/$J$7 -> 1 | M7: Total use: | N7: =SUM(N5:N6) -> 518.94771 | O7: =N7/$N$7 -> 1 | Q7: Waste feedstock | R7: =B9 -> 0 | S7: =R7/SUM($R$35) -> 0
A8: DAC | B8: =C8*$B$31 -> 0 | C8: 0 | Q8: Incineration without CCS | R8: ='Job + CO2 Analysis'!D25+0.27*N6*AA8/SUM(AA8:AA12) -> 91.891809 | S8: =R8/SUM($R$35) -> 0.12955853 | AA8: ='Scope 3 Yearly'!AH11/SUM('Scope 3 Yearly'!$AH$11:$AH$16) -> 0.32
A9: Waste | B9: =C9*$B$31 -> 0 | C9: 0 | Q9: Open burning | R9: ='Job + CO2 Analysis'!D28 -> 79.404851 | S9: =R9/SUM($R$35) -> 0.11195313 | AA9: ='Scope 3 Yearly'!AH14/SUM('Scope 3 Yearly'!$AH$11:$AH$16) -> 0.16
A10: Total | B10: =F6 -> 488.63221 | Q10: Incineration with CCS | R10: =0 -> 0 | S10: =R10/SUM($R$35) -> 0 | AA10: =0 -> 0
Q11: Landfill | R11: ='Job + CO2 Analysis'!D26 -> 108.81406 | S11: =R11/SUM($R$35) -> 0.15341726 | AA11: ='Scope 3 Yearly'!AH12/SUM('Scope 3 Yearly'!$AH$11:$AH$16) -> 0.42
A12: Note Point source /waste can come from within or other industries | Q12: Leakage | R12: ='Job + CO2 Analysis'!D27+'Job + CO2 Analysis'!D29+'Job + CO2 Analysis'!D30 -> 58.818408 | S12: =R12/SUM($R$35) -> 0.082928248 | AA12: =SUM('Scope 3 Yearly'!AH13,'Scope 3 Yearly'!AH15,'Scope 3 Yearly'!AH16)/SUM('Scope 3 Yearly'!$AH$11:$AH$16) -> 0.1
A13: No quanitfication has been made but it must be shown visually | Q13: Accumulate in the economy | R13: =N6-SUM(R5:R12) -> 149.70308 | S13: =R13/SUM($R$35) -> 0.21106682 | AA13: =R13/N7 -> 0.28847431 | AB13: =1-AA13 -> 0.71152569
A14: Number in yellow estimated from the demand model (feedstock in t of C for Ar&Ol excluding hydrogen) | Q14: Total end-of-use | R14: =SUM(R5:R13) -> 518.94771
A18: Not shown
E19: Elimination | F19: 0 | G19: =F19/$F$41 -> 0 | I19: Elimination | J19: =F19 -> 0 | K19: =J19/$J$41 -> 0 | M19: Elimination | N19: =J19 -> 0 | O19: =N19/$N$41 -> 0
E20: Substitution | F20: 0 | G20: =F20/$F$41 -> 0 | I20: Substitution | J20: =F20 -> 0 | K20: =J20/$J$41 -> 0 | M20: Substitution | N20: =J20 -> 0 | O20: =N20/$N$41 -> 0
E21: Total utility: | F21: =SUM(F7:F20) -> 488.63221 | G21: =F21/$F$21 -> 1 | I21: Total utility: | J21: =SUM(J7,J19,J20) -> 518.94771 | K21: =J21/$J$21 -> 1 | M21: Total utility: | N21: =SUM(N7,N19,N20) -> 518.94771 | O21: =N21/$N$21 -> 1
A23: For Most Economic / Low circularity - 2050
B24: Box #1 Feedstock | F24: Box #2: Chemical Production | J24: Box #3: Product Manufacturing | N24: Box #4: Use Phase | R24: Box #5: End-of-use
B25: Mt in 2050 | C25: % | F25: Mt in 2050 | G25: % | J25: Mt in 2050 | K25: % | N25: Mt in 2050 | O25: % | R25: Mt in 2050 | S25: %
A26: Fossil | B26: =C26*$B$31 -> 351.13139 | C26: 0.74100509 | E26: Depolymerization | F26: =R27 -> 9.7546726 | G26: =F26/$F$28 -> 0.020170413 | I26: Mechanical recycling | J26: =R26 -> 225.65573 | K26: =J26/$J$28 -> 0.31815269 | M26: Resuse | N26: ='Final Exhibits'!H25 -> 0 | O26: =N26/$N$28 -> 0 | Q26: Mechanical recycling | R26: ='Job + CO2 Analysis'!BN22 -> 225.65573 | S26: =R26/SUM($R$35) -> 0.31815269
A27: Biomass | B27: =C27*$B$31 -> 72.952767 | C27: 0.15395482 | E27: Chemical production | F27: =SUM('Final Exhibits'!K16:K22)-'Final Exhibits'!E10-'Final Exhibits'!B10+'Yearly Summary'!D37 -> 473.85827 | G27: =F27/$F$28 -> 0.97982959 | I27: Product Manufacturing | J27: =F28 -> 483.61294 | K27: =J27/$J$28 -> 0.68184731 | M27: Use | N27: =J28 -> 709.26868 | O27: =N27/$N$28 -> 1 | Q27: Depolymerization | R27: ='Job + CO2 Analysis'!BN23 -> 9.7546726 | S27: =R27/SUM($R$35) -> 0.013753142
A28: Point Source | B28: =C28*$B$31 -> 36.000029 | C28: 0.075972144 | E28: Total production: | F28: =SUM(F26:F27) -> 483.61294 | G28: =F28/$F$28 -> 1 | I28: Total manufacturing: | J28: =SUM(J26:J27) -> 709.26868 | K28: =J28/$J$28 -> 1 | M28: Total use: | N28: =SUM(N26:N27) -> 709.26868 | O28: =N28/$N$28 -> 1 | Q28: Waste feedstock | R28: =B30 -> 13.774085 | S28: =R28/SUM($R$35) -> 0.019420122
A29: DAC | B29: =C29*$B$31 -> 0 | C29: 0 | Q29: Incineration without CCS | R29: ='Scope 3 Yearly'!BN19 -> 0.89491309 | S29: =R29/SUM($R$35) -> 0.0012617406
A30: Waste | B30: =C30*$B$31 -> 13.774085 | C30: 0.029067942 | Q30: Open burning | R30: ='Scope 3 Yearly'!BN14 -> 45.220761 | S30: =R30/SUM($R$35) -> 0.063756884
A31: Total | B31: =F27 -> 473.85827 | Q31: Incineration with CCS | R31: ='Scope 3 Yearly'!BN20-R28*'Scope 3 Yearly'!BN20/('Scope 3 Yearly'!BN20+'Scope 3 Yearly'!BN12) -> 83.623842 | S31: =R31/SUM($R$35) -> 0.1179015
F32: =B28-R31 -> -47.623813 | Q32: Landfill | R32: ='Scope 3 Yearly'!BN12-R28*'Scope 3 Yearly'!BN12/('Scope 3 Yearly'!BN20+'Scope 3 Yearly'!BN12) -> 110.85318 | S32: =R32/SUM($R$35) -> 0.15629222
A33: Note Point source /waste can come from within or other industries | Q33: Leakage | R33: ='Scope 3 Yearly'!BN15+'Scope 3 Yearly'!BN13+'Scope 3 Yearly'!BN16 -> 28.262975 | S33: =R33/SUM($R$35) -> 0.039848052
A34: No quanitfication has been made but it must be shown visually | Q34: Accumulate in the economy | R34: =N27-SUM(R26:R33) -> 191.22852 | S34: =R34/SUM($R$35) -> 0.26961365 | U34: =R34/N28 -> 0.26961365
A35: Number in yellow estimated from the demand model (feedstock in t of C for Ar&Ol excluding hydrogen) | Q35: Total end-of-use | R35: =SUM(R26:R34) -> 709.26868
R36: =B31-SUM(R28:R33) -> 191.22852
A38: Not shown
E39: Elimination | F39: ='Final Exhibits'!G24-'Job + CO2 Analysis'!BN5 -> 66.071576 | G39: =F39/$F$41 -> 0.13160077 | I39: Elimination | J39: =F39 -> 66.071576 | K39: =J39/$J$41 -> 0.085216233 | M39: Elimination | N39: =J39 -> 66.071576 | O39: =N39/$N$41 -> 0.085216233
E40: Substitution | F40: ='Final Exhibits'!H25-'Job + CO2 Analysis'!BN6 -> 0 | G40: =F40/$F$41 -> 0 | I40: Substitution | J40: =F40 -> 0 | K40: =J40/$J$41 -> 0 | M40: Substitution | N40: =J40 -> 0 | O40: =N40/$N$41 -> 0
E41: Total utility: | F41: =SUM(F28:F40) -> 502.0607 | G41: =F41/$F$41 -> 1 | I41: Total utility: | J41: =SUM(J28,J39,J40) -> 775.34025 | K41: =J41/$J$41 -> 1 | M41: Total utility: | N41: =SUM(N28,N39,N40) -> 775.34025 | O41: =N41/$N$41 -> 1
A43: For No fossil after X / Low circularity - 2050
B44: Box #1 Feedstock | F44: Box #2: Chemical Production | J44: Box #3: Product Manufacturing | N44: Box #4: Use Phase | R44: Box #5: End-of-use
B45: Mt in 2050 | C45: % | F45: Mt in 2050 | G45: % | J45: Mt in 2050 | K45: % | N45: Mt in 2050 | O45: % | R45: Mt in 2050 | S45: %
A46: Fossil | B46: =C46*$B$51 -> 84.364424 | C46: 0.17803725 | E46: Depolymerization | F46: =R47 -> 9.7546726 | G46: =F46/$F$28 -> 0.020170413 | I46: Mechanical recycling | J46: =R46 -> 225.65573 | K46: =J46/$J$48 -> 0.31815269 | M46: Resuse | N46: =N26 -> 0 | O46: =N46/$N$28 -> 0 | Q46: Mechanical recycling | R46: =R26 -> 225.65573 | S46: =R46/SUM($R$35) -> 0.31815269
A47: Biomass | B47: =C47*$B$51 -> 205.09935 | C47: 0.43282847 | E47: Chemical production | F47: =F27 -> 473.85827 | G47: =F47/$F$28 -> 0.97982959 | I47: Product Manufacturing | J47: =F48 -> 483.61294 | K47: =J47/$J$48 -> 0.68184731 | M47: Use | N47: =J48 -> 709.26868 | O47: =N47/$N$28 -> 1 | Q47: Depolymerization | R47: =R27 -> 9.7546726 | S47: =R47/SUM($R$35) -> 0.013753142
A48: Point Source | B48: =C48*$B$51 -> 87.352315 | C48: 0.1843427 | E48: Total production: | F48: =SUM(F46:F47) -> 483.61294 | G48: =F48/$F$61 -> 0.96325591 | I48: Total manufacturing: | J48: =SUM(J46:J47) -> 709.26868 | K48: =J48/$J$48 -> 1 | M48: Total use: | N48: =SUM(N46:N47) -> 709.26868 | O48: =N48/$N$28 -> 1 | Q48: Waste feedstock | R48: =B50 -> 11.561753 | S48: =R48/SUM($R$35) -> 0.01630095
A49: DAC | B49: =C49*$B$51 -> 85.480427 | C49: 0.18039239 | Q49: Incineration without CCS | R49: =R29 -> 0.89491309 | S49: =R49/SUM($R$35) -> 0.0012617406
A50: Waste | B50: =C50*$B$51 -> 11.561753 | C50: 0.02439918 | Q50: Open burning | R50: =R30 -> 45.220761 | S50: =R50/SUM($R$35) -> 0.063756884
A51: Total | B51: =F47 -> 473.85827 | Q51: Incineration with CCS | R51: ='Scope 3 Yearly'!BN20-R48*'Scope 3 Yearly'!BN20/('Scope 3 Yearly'!BN20+'Scope 3 Yearly'!BN12) -> 84.57513 | S51: =R51/SUM($R$35) -> 0.11924273
Q52: Landfill | R52: ='Scope 3 Yearly'!BN12-R48*'Scope 3 Yearly'!BN12/('Scope 3 Yearly'!BN20+'Scope 3 Yearly'!BN12) -> 112.11422 | S52: =R52/SUM($R$35) -> 0.15807017
A53: Note Point source /waste can come from within or other industries | Q53: Leakage | R53: =R33 -> 28.262975 | S53: =R53/SUM($R$35) -> 0.039848052
A54: No quanitfication has been made but it must be shown visually | Q54: Accumulate in the economy | R54: =N47-SUM(R46:R53) -> 191.22852 | S54: =R54/SUM($R$35) -> 0.26961365 | U54: =R54/N48 -> 0.26961365
A55: Number in yellow estimated from the demand model (feedstock in t of C for Ar&Ol excluding hydrogen) | Q55: Total end-of-use | R55: =SUM(R46:R54) -> 709.26868
A58: Not shown
E59: Elimination | F59: =F39 -> 66.071576 | G59: =F59/$F$41 -> 0.13160077 | I59: Elimination | J59: =J39 -> 66.071576 | K59: =J59/$J$41 -> 0.085216233 | M59: Elimination | N59: =N39 -> 66.071576 | O59: =N59/$N$41 -> 0.085216233
E60: Substitution | F60: =F40 -> 0 | G60: =F60/$F$41 -> 0 | I60: Substitution | J60: =J40 -> 0 | K60: =J60/$J$41 -> 0 | M60: Substitution | N60: =N40 -> 0 | O60: =N60/$N$41 -> 0
E61: Total utility: | F61: =F41 -> 502.0607 | G61: =F61/$F$41 -> 1 | I61: Total utility: | J61: =J41 -> 775.34025 | K61: =J61/$J$41 -> 1 | M61: Total utility: | N61: =N41 -> 775.34025 | O61: =N61/$N$41 -> 1

Sheet Final Exhibits
A1: Exhibit 3.1 – without circularity, demand for all base chemicals will increase, particularly methanol and ammonia as they enable a net zero economy
B2: 2020 | C2: Label | D2: 2050 BAU | E2: Label | F2: 2050 decarbonized BAU
A4: Butadiene | B4: ='Yearly Summary'!D57 -> 14.947368 | C4: =D4-B4 -> 10.107591 | D4: ='Yearly Summary'!AH57-E4 -> 25.054959 | E4: ='Yearly Butadiene'!AH42 -> 0 | F4: =D4+E4 -> 25.054959 | L4: Ammonia | M4: Ethylene | N4: Propylene | O4: Methanol | P4: Benzene | Q4: Toluene | R4: Xylene | S4: Butadiene
A5: Xylene | B5: ='Yearly Summary'!D52 -> 50.261625 | C5: =D5-B5 -> 18.121485 | D5: ='Yearly Summary'!AH52-E5 -> 68.38311 | E5: ='Yearly BTX'!AH66+'Yearly BTX'!AH17*'Yearly BTX'!AH24/SUM('Yearly BTX'!AH24:AH26) -> 1.3109583 | F5: =D5+E5 -> 69.694069 | I5: Text | K5: 2020 | L5: =B11 -> 185 | M5: =B9 -> 162.69231 | N5: =B8 -> 111.92308 | O5: =B10 -> 101.96027 | P5: =B7 -> 51.832301 | Q5: =B6 -> 14.015261 | R5: =B5 -> 50.261625 | S5: =B4 -> 14.947368
A6: Toluene | B6: ='Yearly Summary'!D47 -> 14.015261 | C6: =D6-B6 -> 5.2596726 | D6: ='Yearly Summary'!AH47-E6 -> 19.274933 | E6: ='Yearly BTX'!AH65+'Yearly BTX'!AH17*'Yearly BTX'!AH25/SUM('Yearly BTX'!AH24:AH26) -> 0.15898954 | F6: =D6+E6 -> 19.433923 | K6: 2050 | L6: =D11 -> 227.54 | M6: =D9 -> 255 | N6: =D8 -> 160 | O6: =D10 -> 145.59946 | P6: =D7 -> 70.854945 | Q6: =D6 -> 19.274933 | R6: =D5 -> 68.38311 | S6: =D4 -> 25.054959
A7: Benzene | B7: ='Yearly Summary'!D42 -> 51.832301 | C7: =D7-B7 -> 19.022644 | D7: ='Yearly Summary'!AH42-E7 -> 70.854945 | E7: ='Yearly BTX'!AH64+'Yearly BTX'!AH17*'Yearly BTX'!AH26/SUM('Yearly BTX'!AH24:AH26) -> 1.017063 | F7: =D7+E7 -> 71.872008 | H7: Total chem 2020 | I7: =SUM(B4:B11) -> 692.63221
A8: Propylene | B8: ='Yearly Summary'!D32 -> 111.92308 | C8: =D8-B8 -> 48.076923 | D8: ='Yearly Summary'!AH32-E8 -> 160 | E8: ='Yearly HC Propylene'!AH41 -> 2.9240993 | F8: =D8+E8 -> 162.9241 | H8: Total chem 2050 | I8: =SUM(D4:D11) -> 971.70741 | K8: R&S&Recycling(mech&chem) | M8: =SUM('Yearly LC Ethylene'!AH81:AH82,'Yearly LC Ethylene'!AH146:AH147,'Yearly LC Ethylene'!AH155:AH156) -> 100.86221 | N8: =SUM('Yearly LC Propylene'!AH39:AH40,'Yearly LC Propylene'!AH66:AH67,'Yearly LC Propylene'!AH69:AH70) -> 49.550462 | S8: =SUM('Yearly Butadiene'!BN43:BN44,'Yearly Butadiene'!BN71:BN72,'Yearly Butadiene'!BN74:BN75) -> 1.9461646
A9: Ethylene | B9: ='Yearly Summary'!D27 -> 162.69231 | C9: =D9-B9 -> 92.307692 | D9: ='Yearly Summary'!AH27-E9 -> 255 | E9: ='Yearly HC Ethylene'!AH83 -> 25.104593 | F9: =D9+E9 -> 280.10459 | H9: CAGR | I9: =(I8/I7)^(1/30)-1 -> 0.011349105 | K9: check | M9: =M6-'Yearly Summary'!BN28-'Final Exhibits'!M8 -> -25.104593 | N9: =N6-'Yearly Summary'!BN33-'Final Exhibits'!N8 -> -2.9240993 | S9: =S6-'Yearly Summary'!BN58-'Final Exhibits'!S8 -> 0
A10: Methanol | B10: ='Yearly Summary'!D37+31 -> 101.96027 | C10: =D10-B10 -> 43.63919 | D10: ='Yearly Summary'!AH37 -> 145.59946 | E10: =290 -> 290 | F10: =D10+E10 -> 435.59946
A11: Ammonia | B11: ='Yearly Summary'!D14 -> 185 | C11: =D11-B11 -> 42.54 | D11: 227.54 | E11: 786 | F11: =D11+E11 -> 1013.54
A13: Exhibit 3.2c – without circularity, demand for all base chemicals will increase, particularly methanol and ammonia as they enable a net zero economy
B14: =B2 -> 2020 | C14: =C2 -> Label | D14: =D2 -> 2050 BAU | E14: =E2 -> Label | F14: =F2 -> 2050 decarbonized BAU | G14: Label | I14: Label | J14: Label | K14: 2050 NZ + Low circularity | L14: Label | N14: Label | O14: Label | P14: 2050 NZ + High circularity
A16: Butadiene | B16: =B4 -> 14.947368 | C16: =C4 -> 10.107591 | D16: =D4 -> 25.054959 | E16: =E4 -> 0 | F16: =F4 -> 25.054959 | K16: ='Yearly Summary'!BN58 -> 23.108795 | P16: ='Yearly Summary'!AH58 -> 23.108795 | S16: =E16/F16 -> 0
A17: Xylene | B17: =B5 -> 50.261625 | C17: =C5 -> 18.121485 | D17: =D5 -> 68.38311 | E17: =E5 -> 1.3109583 | F17: =F5 -> 69.694069 | K17: ='Yearly Summary'!BN53 -> 46.053261 | P17: ='Yearly Summary'!AH53 -> 45.299975 | S17: =E17/F17 -> 0.018810185
A18: Toluene | B18: =B6 -> 14.015261 | C18: =C6 -> 5.2596726 | D18: =D6 -> 19.274933 | E18: =E6 -> 0.15898954 | F18: =F6 -> 19.433923 | K18: ='Yearly Summary'!BN48 -> 12.841775 | P18: ='Yearly Summary'!AH48 -> 12.631724 | S18: =E18/F18 -> 0.0081810316
A19: Benzene | B19: =B7 -> 51.832301 | C19: =C7 -> 19.022644 | D19: =D7 -> 70.854945 | E19: =E7 -> 1.017063 | F19: =F7 -> 71.872008 | K19: ='Yearly Summary'!BN43 -> 47.492425 | P19: ='Yearly Summary'!AH43 -> 46.7156 | S19: =E19/F19 -> 0.014151031
A20: Propylene | B20: =B8 -> 111.92308 | C20: =C8 -> 48.076923 | D20: =D8 -> 160 | E20: =E8 -> 2.9240993 | F20: =F8 -> 162.9241 | K20: ='Yearly Summary'!BN33 -> 113.37364 | P20: ='Yearly Summary'!AH33 -> 111.56454 | S20: =E20/F20 -> 0.017947617
A21: Ethylene | B21: =B9 -> 162.69231 | C21: =C9 -> 92.307692 | D21: =D9 -> 255 | E21: =E9 -> 25.104593 | F21: =F9 -> 280.10459 | K21: ='Yearly Summary'!BN28 -> 179.24238 | P21: ='Yearly Summary'!AH28 -> 175.32748 | S21: =E21/F21 -> 0.089625781
A22: Methanol | B22: =B10 -> 101.96027 | C22: =C10 -> 43.63919 | D22: =D10 -> 145.59946 | E22: =E10 -> 290 | F22: =F10 -> 435.59946 | K22: ='Yearly Summary'!BN38+E10-'Yearly Methanol'!AH71 -> 372.74599 | P22: ='Yearly Summary'!AH38+E10-'Yearly Methanol'!AH71 -> 372.44079
A23: Ammonia | B23: =B11 -> 185 | C23: =C11 -> 42.54 | D23: =D11 -> 227.54 | E23: =E11 -> 786 | F23: =D23+E23 -> 1013.54 | K23: ='Yearly Summary'!BN15 -> 417.71705 | P23: ='Yearly Summary'!AH15 -> 417.71705 | S23: =E23/F23 -> 0.77549973
A24: Elimination | G24: =SUM('Job + CO2 Analysis'!BN5,'Job + CO2 Analysis'!BN7,'Job + CO2 Analysis'!BN8,'Job + CO2 Analysis'!BN13,'Job + CO2 Analysis'!BN14,'Job + CO2 Analysis'!BN16,'Job + CO2 Analysis'!BN19) -> 66.071576 | L24: =SUM('Job + CO2 Analysis'!AH5,'Job + CO2 Analysis'!AH7,'Job + CO2 Analysis'!AH8,'Job + CO2 Analysis'!AH13,'Job + CO2 Analysis'!AH14,'Job + CO2 Analysis'!AH16,'Job + CO2 Analysis'!AH19) -> 66.071576
A25: Reuse | H25: =SUM('Job + CO2 Analysis'!BN9,'Job + CO2 Analysis'!BN12,'Job + CO2 Analysis'!BN17) -> 0 | M25: =SUM('Job + CO2 Analysis'!AH9,'Job + CO2 Analysis'!AH12,'Job + CO2 Analysis'!AH17) -> 0
A26: Substitution | I26: =SUM('Job + CO2 Analysis'!BN6,'Job + CO2 Analysis'!BN10,'Job + CO2 Analysis'!BN11,'Job + CO2 Analysis'!BN15,'Job + CO2 Analysis'!BN18,'Job + CO2 Analysis'!BN20) -> 0 | N26: =SUM('Job + CO2 Analysis'!AH6,'Job + CO2 Analysis'!AH10,'Job + CO2 Analysis'!AH11,'Job + CO2 Analysis'!AH15,'Job + CO2 Analysis'!AH18,'Job + CO2 Analysis'!AH20) -> 0
A27: Recycling | J27: ='Job + CO2 Analysis'!BN22+'Job + CO2 Analysis'!BN23-'Job + CO2 Analysis'!AJ22-'Job + CO2 Analysis'!AJ23 -> 205.09483 | O27: ='Job + CO2 Analysis'!AH22+'Job + CO2 Analysis'!AH23-'Job + CO2 Analysis'!D22-'Job + CO2 Analysis'!D23 -> 212.83851
A28: Series | G28: =G24 -> 66.071576 | L28: =L24 -> 66.071576
A30: Check | B30: =SUM(B16:B23) -> 692.63221 | D30: =SUM(D16:D23) -> 971.70741 | F30: =SUM(F16:F23) -> 2078.2231 | J30: =F30-G24-I26-J27-H25 -> 1807.0567 | K30: =SUM(K16:K23) -> 1212.5753 | O30: =F30-L24-N26-O27-M25 -> 1799.313 | P30: =SUM(P16:P23) -> 1204.806
B31: =B30-B23 -> 507.63221 | D31: =D30-D23 -> 744.16741 | F31: ='Yearly Summary'!AH9+'Final Exhibits'!E22 -> 1589.6618
A32: Numbers in the text
A33: Plastic and fetilizer per capita | F33: Mt chemicals | G33: 2161.7746 | H33: HC | I33: LC
A34: Circular levers for all chemicals | H34: =(SUM('Job + CO2 Analysis'!AH5:AH20,'Job + CO2 Analysis'!AH22:AH23)-SUM('Job + CO2 Analysis'!D22:D23))/SUM('Job + CO2 Analysis'!AH4,'Job + CO2 Analysis'!AH21+E10) -> 0.11579596 | I34: =(SUM('Job + CO2 Analysis'!BN5:BN20,'Job + CO2 Analysis'!BN22:BN23)-SUM('Job + CO2 Analysis'!AJ22:AJ23))/SUM('Job + CO2 Analysis'!BN21,'Job + CO2 Analysis'!BN4,E10) -> 0.11258098 | K34: =SUM(L24:O27)/SUM(F16:F23) -> 0.13420604 | L34: =(SUM(G24:J27))/SUM(F16:F23) -> 0.13047993 | M34: Check
A35: Circular levers for carbon-based chemicals | H35: =(SUM('Job + CO2 Analysis'!AH7:AH20,'Job + CO2 Analysis'!AH22:AH23)-SUM('Job + CO2 Analysis'!D22:D23))/SUM(F16:F22) -> 0.26196536 | I35: =(SUM('Job + CO2 Analysis'!BN7:BN20,'Job + CO2 Analysis'!BN22:BN23)-SUM('Job + CO2 Analysis'!AJ22:AJ23))/SUM(F16:F22) -> 0.25469212 | N35: Excld. Recycling | P35: =(SUM('Job + CO2 Analysis'!AH7:AH20))/SUM(F16:F22) -> 0.062057504 | Q35: =(SUM('Job + CO2 Analysis'!BN7:BN20))/SUM(F16:F22) -> 0.062057504
A36: Elimination | G36: =G24/SUM(G24:J27) -> 0.24365694 | I36: =L24/SUM(L24:O27) -> 0.23689202
A37: Reuse | G37: =H25/SUM(G24:J27) -> 0 | I37: =M25/SUM(L24:O27) -> 0
A38: Substitution | G38: =I26/SUM(G24:J27) -> 0 | I38: =N26/SUM(L24:O27) -> 0
A39: Recycling | G39: =J27/SUM(G24:J27) -> 0.75634306 | I39: =O27/SUM(L24:O27) -> 0.76310798
A40: Ratio mechanical vs total production | G40: =('Job + CO2 Analysis'!BN22-'Job + CO2 Analysis'!AJ22)/SUM(H40) -> 0.34578636 | H40: =F16*SUM('Demand Breakdown - C4'!G18:G20)+SUM(F17:F19)*SUM('Demand Breakdown - BTX'!I20:I22)+D22*SUM('Demand Breakdown - Methanol'!C3:C11)+F20*SUM('Demand Breakdown - Propylene'!C25:C27)+F21*SUM('Demand Breakdown - Ethylene'!C34:C40)-SUM('Job + CO2 Analysis'!BN8:BN18) -> 564.91596 | I40: =('Job + CO2 Analysis'!AH22-'Job + CO2 Analysis'!D22)/SUM(J40) -> 0.34578636 | J40: =F16*SUM('Demand Breakdown - C4'!G18:G20)+SUM(F17:F19)*SUM('Demand Breakdown - BTX'!I20:I22)+D22*SUM('Demand Breakdown - Methanol'!C3:C11)+F20*SUM('Demand Breakdown - Propylene'!C25:C27)+F21*SUM('Demand Breakdown - Ethylene'!C34:C40)-SUM('Job + CO2 Analysis'!AH8:AH18) -> 564.91596
A41: Mechanical Recycling rates | G41: ='Job + CO2 Analysis'!BN22/SUM('Job + CO2 Analysis'!BN22:BN23,'Job + CO2 Analysis'!BN25:BN30) -> 0.43559506 | I41: ='Job + CO2 Analysis'!AH22/SUM('Job + CO2 Analysis'!AH22:AH23,'Job + CO2 Analysis'!AH25:AH30) -> 0.43529385
A42: Open loop out of total recycling | H42: ='Yearly BTX'!BN113+'Yearly Butadiene'!BN71+'Yearly Methanol'!BN114+'Yearly LC Ethylene'!AH146+'Yearly LC Propylene'!AH66 -> 86.222401 | I42: =H42/'Job + CO2 Analysis'!BN22 -> 0.3820971
A45: METHANOL DEMAND
B46: 2020 | C46: Increase in food demand | D46: 2050 BAU | E46: Additional demand | F46: 2050 Net Zero | G46: Reduced demand | H46: 2050 Net Zero + Circular
A48: Base | B48: =B10 -> 101.96027 | C48: =C10 -> 43.63919 | D48: =D10 -> 145.59946 | F48: =SUM(D48:E49) -> 435.59946 | H48: =SUM(F48:G49) -> 375.20259
A49: Series | E49: =E10 -> 290 | G49: =-SUM('Yearly Methanol'!BN69:BN70,'Yearly Methanol'!BN12,'Yearly Methanol'!BN114:BN115,'Yearly Methanol'!BN120:BN121) -> -60.396864
A50: Series
A52: Olefins DEMAND | K52: Eth | L52: Prop | M52: But | N52: Olefins
B53: 2020 | C53: Increase in food demand | D53: 2050 BAU | E53: Additional demand | F53: 2050 Net Zero | G53: Reduced demand | H53: 2050 Net Zero + Circular | J53: PE | K53: ='Demand Breakdown - Ethylene'!C34+'Demand Breakdown - Ethylene'!C35 -> 0.61 | N53: =SUMPRODUCT(K53:M53,K$61:M$61) -> 99.242308 | O53: =N53/N$61 -> 0.34273161
J54: PS | K54: ='Demand Breakdown - Ethylene'!C39 -> 0.0594 | N54: =SUMPRODUCT(K54:M54,K$61:M$61) -> 9.6639231 | O54: =N54/N$61 -> 0.033374193
A55: Base | B55: =B4+B8+B9 -> 289.56275 | C55: =C4+C8+C9 -> 150.49221 | D55: =D4+D8+D9 -> 440.05496 | F55: =SUM(D55:E56) -> 468.08365 | H55: =SUM(F55:G56) -> 315.72481 | I55: =-G56/F55 -> 0.32549489 | J55: PET | K55: ='Demand Breakdown - Ethylene'!C36+'Demand Breakdown - Ethylene'!C37 -> 0.06566 | N55: =SUMPRODUCT(K55:M55,K$61:M$61) -> 10.682377 | O55: =N55/N$61 -> 0.036891405
A56: Series | E56: =E4+E8+E9 -> 28.028692 | G56: =-SUM('Yearly Butadiene'!BN43:BN44,'Yearly Butadiene'!BN71:BN72,'Yearly Butadiene'!BN74:BN75,'Yearly LC Ethylene'!AH81:AH82,'Yearly LC Ethylene'!AH146:AH147,'Yearly LC Ethylene'!AH155:AH156,'Yearly LC Propylene'!AH39:AH40,'Yearly LC Propylene'!AH66:AH67,'Yearly LC Propylene'!AH69:AH70) -> -152.35884 | J56: PP | K56: 0 | L56: ='Demand Breakdown - Propylene'!C25+'Demand Breakdown - Propylene'!C26 -> 0.67 | N56: =SUMPRODUCT(K56:M56,K$61:M$61) -> 74.988462 | O56: =N56/N$61 -> 0.25897137
A57: Series | J57: PVC | K57: ='Demand Breakdown - Ethylene'!C38 -> 0.1152 | N57: =SUMPRODUCT(K57:M57,K$61:M$61) -> 18.742154 | O57: =N57/N$61 -> 0.064725707
G58: =-SUM('Yearly Butadiene'!AH43:AH44,'Yearly HC Ethylene'!AH81:AH82,'Yearly HC Propylene'!AH39:AH40) -> 0 | H58: =F55+G58 -> 468.08365 | I58: =-G58/F55 -> 0 | J58: Rubber | K58: 0 | M58: ='Demand Breakdown - C4'!G18 -> 0.712 | N58: =SUMPRODUCT(K58:M58,K$61:M$61) -> 10.642526 | O58: =N58/N$61 -> 0.036753782
C59: 2020 | D59: 2050 | J59: Other polymers | K59: ='Demand Breakdown - Ethylene'!C40 -> 0.031354 | L59: ='Demand Breakdown - Propylene'!C27 -> 0.102 | M59: ='Demand Breakdown - C4'!G20 -> 0.211 | N59: =SUMPRODUCT(K59:M59,K$61:M$61) -> 19.671103 | O59: =N59/N$61 -> 0.067933817
B60: Mech | C60: =SUM('Yearly Butadiene'!D71:D72,'Yearly Butadiene'!D74:D75,'Yearly HC Ethylene'!D146:D147,'Yearly HC Ethylene'!D155:D156,'Yearly HC Propylene'!D66:D67,'Yearly HC Propylene'!D69:D70) -> 0.00011431675 | D60: =SUM('Yearly Butadiene'!AH71:AH72,'Yearly Butadiene'!AH74:AH75,'Yearly HC Ethylene'!AH146:AH147,'Yearly HC Ethylene'!AH155:AH156,'Yearly HC Propylene'!AH66:AH67,'Yearly HC Propylene'!AH69:AH70) -> 158.08284 | J60: Others | K60: ='Demand Breakdown - Ethylene'!C41 -> 0.118386 | L60: ='Demand Breakdown - Propylene'!C28 -> 0.228 | M60: ='Demand Breakdown - C4'!G22 -> 0.077 | N60: =SUMPRODUCT(K60:M60,K$61:M$61) -> 45.9299 | O60: =N60/N$61 -> 0.15861812
C61: ='Ethylene Recycling LC'!C182+'Propylene Recycling LC'!C103+'Butadiene Recycling LC'!C165 -> 22.978579 | D61: ='Ethylene Recycling LC'!AG182+'Propylene Recycling LC'!AG103+'Butadiene Recycling LC'!AG165 -> 168.39443 | J61: Total | K61: =B9 -> 162.69231 | L61: =B8 -> 111.92308 | M61: =B4 -> 14.947368 | N61: =SUM(K61:M61) -> 289.56275 | O61: =SUM(O53:O60) -> 1
K62: =K61/$N$61 -> 0.56185509 | L62: =L61/$N$61 -> 0.38652443 | M62: =M61/$N$61 -> 0.05162048
A65: Aromatics DEMAND
B66: 2020 | C66: Increase in food demand | D66: 2050 BAU | E66: Additional demand | F66: 2050 Net Zero | G66: Reduced fertilizer demand | H66: 2050 Net Zero + Circular
A68: Base | B68: =SUM(B5:B7) -> 116.10919 | C68: =SUM(C5:C7) -> 42.403802 | D68: =SUM(D5:D7) -> 158.51299 | F68: =SUM(D68:E69) -> 161 | H68: =SUM(F68:G69) -> 161
A69: Series | E69: =SUM('Yearly BTX'!BN69) -> 2.4870108 | G69: =-SUM('Yearly BTX'!BN67:BN68) -> 0
A70: Series
A73: Ammonia & derivatives
B74: 2020 | C74: Increase | D74: 2050 BAU | E74: Additional demand | F74: 2050 Net Zero | G74: Reduced fertilizer demand | H74: 2050 Net Zero + Circular
A76: Base | B76: 185.16 | C76: 42.38 | D76: =SUM(B76:C76) -> 227.54 | F76: =SUM(D76:E78) -> 1013.54 | H76: =SUM(F76:G77) -> 995.54 | J76: 185.16 | K76: 42.38 | L76: 227.54 | N76: 1013.54 | P76: 995.54
A77: Series | E77: 625 | G77: -18 | M77: 625 | O77: -18
A78: Series | E78: 161 | M78: 161
A80: Ammonium nitrate | B80: 40.04704
A81: Urea | B81: 66.778439
A82: Other Fertilizers | B82: 33.360329
A83: Marine Transport | B83: 625
A84: Power Generation | B84: 161
A85: Others | B85: 69.354192

Sheet Job + CO2 Analysis
D1: HIGH CIRCULARITY | AJ1: LOW CIRCULARITY | BP1: BUSINESS-AS-USUAL | CV1: BUSINESS-AS-USUAL MOST ECONOMIC
D2: 2020 | E2: =D2+1 -> 2021 | F2: =E2+1 -> 2022 | G2: =F2+1 -> 2023 | H2: =G2+1 -> 2024 | I2: =H2+1 -> 2025 | J2: =I2+1 -> 2026 | K2: =J2+1 -> 2027 | L2: =K2+1 -> 2028 | ... AH2: =AG2+1 -> 2050 | AJ2: 2020 | AK2: =AJ2+1 -> 2021 | AL2: =AK2+1 -> 2022 | AM2: =AL2+1 -> 2023 | AN2: =AM2+1 -> 2024 | AO2: =AN2+1 -> 2025 | AP2: =AO2+1 -> 2026 | AQ2: =AP2+1 -> 2027 | AR2: =AQ2+1 -> 2028 | ... BN2: =BM2+1 -> 2050 | BP2: 2020 | BQ2: =BP2+1 -> 2021 | BR2: =BQ2+1 -> 2022 | BS2: =BR2+1 -> 2023 | BT2: =BS2+1 -> 2024 | BU2: =BT2+1 -> 2025 | BV2: =BU2+1 -> 2026 | BW2: =BV2+1 -> 2027 | BX2: =BW2+1 -> 2028 | ... CT2: =CS2+1 -> 2050 | CV2: 2020 | CW2: =CV2+1 -> 2021 | CX2: =CW2+1 -> 2022 | CY2: =CX2+1 -> 2023 | CZ2: =CY2+1 -> 2024 | DA2: =CZ2+1 -> 2025 | DB2: =DA2+1 -> 2026 | DC2: =DB2+1 -> 2027 | DD2: =DC2+1 -> 2028 | ... DZ2: =DY2+1 -> 2050
A3: Total
A4: Production BAU | C4: mTons | D4: ='Yearly Summary'!D9 -> 661.63221 | E4: ='Yearly Summary'!E9 -> 681.06308 | F4: ='Yearly Summary'!F9 -> 700.1174 | G4: ='Yearly Summary'!G9 -> 719.45436 | H4: ='Yearly Summary'!H9 -> 739.08157 | I4: ='Yearly Summary'!I9 -> 759.00701 | J4: ='Yearly Summary'!J9 -> 777.34663 | K4: ='Yearly Summary'!K9 -> 795.89948 | ... AH4: ='Yearly Summary'!AH9 -> 1299.6618 | AJ4: ='Yearly Summary'!AJ9 -> 661.63221 | AK4: ='Yearly Summary'!AK9 -> 681.06308 | AL4: ='Yearly Summary'!AL9 -> 700.1174 | AM4: ='Yearly Summary'!AM9 -> 719.45436 | AN4: ='Yearly Summary'!AN9 -> 739.08157 | AO4: ='Yearly Summary'!AO9 -> 759.00701 | AP4: ='Yearly Summary'!AP9 -> 777.34663 | AQ4: ='Yearly Summary'!AQ9 -> 795.89948 | ... BN4: ='Yearly Summary'!BN9 -> 1299.6618 | BP4: =AJ4 -> 661.63221 | BQ4: =AK4 -> 681.06308 | BR4: =AL4 -> 700.1174 | BS4: =AM4 -> 719.45436 | BT4: =AN4 -> 739.08157 | BU4: =AO4 -> 759.00701 | BV4: =AP4 -> 777.34663 | BW4: =AQ4 -> 795.89948 | ... CT4: =BN4 -> 1299.6618 | CV4: =BP4 -> 661.63221 | CW4: =BQ4 -> 681.06308 | CX4: =BR4 -> 700.1174 | CY4: =BS4 -> 719.45436 | CZ4: =BT4 -> 739.08157 | DA4: =BU4 -> 759.00701 | DB4: =BV4 -> 777.34663 | DC4: =BW4 -> 795.89948 | ... DZ4: =CT4 -> 1299.6618
A5: R | B5: Fertilizer reduction (food waste, new tech, diet shift) | C5: mTons | D5: 0 | E5: 1.3016511 | F5: 2.6347665 | G5: 3.9965539 | H5: 5.3873627 | I5: 6.8051382 | J5: 8.2211838 | K5: 9.6512897 | L5: 11.096188 | M5: 12.553309 | N5: 0 | O5: 15.536888 | P5: 17.068964 | Q5: 18.617304 | R5: 20.17825 | S5: 21.754441 | T5: 23.329794 | U5: 24.913579 | V5: 26.506989 | W5: 28.110611 | X5: 0 | Y5: 31.316179 | Z5: 32.923264 | AA5: 34.526231 | AB5: 36.131568 | AC5: 37.742179 | AD5: 39.39173 | AE5: 41.042895 | AF5: 42.696549 | AG5: 44.347974 | AH5: 0 | AJ5: 0 | AK5: 0.50934174 | AL5: 1.0309956 | AM5: 1.5638689 | AN5: 2.1080985 | AO5: 2.6628802 | AP5: 3.216985 | AQ5: 3.7765916 | AR5: 4.3419868 | AS5: 4.9121643 | AT5: 0 | AU5: 6.0796518 | AV5: 6.6791597 | AW5: 7.2850319 | AX5: 7.8958369 | AY5: 8.5126072 | AZ5: 9.1290498 | BA5: 9.7487916 | BB5: 10.3723 | BC5: 10.999804 | BD5: 0 | BE5: 12.254157 | BF5: 12.883016 | BG5: 13.510264 | BH5: 14.13844 | BI5: 14.768679 | BJ5: 15.414155 | BK5: 16.060263 | BL5: 16.707345 | BM5: 17.353555 | BN5: 0 | BP5: 0 | BQ5: 0 | BR5: 0 | BS5: 0 | BT5: 0 | BU5: 0 | BV5: 0 | BW5: 0 | BX5: 0 | BY5: 0 | BZ5: 0 | CA5: 0 | CB5: 0 | CC5: 0 | CD5: 0 | CE5: 0 | CF5: 0 | CG5: 0 | CH5: 0 | CI5: 0 | CJ5: 0 | CK5: 0 | CL5: 0 | CM5: 0 | CN5: 0 | CO5: 0 | CP5: 0 | CQ5: 0 | CR5: 0 | CS5: 0 | CT5: 0 | CV5: 0 | CW5: 0 | CX5: 0 | CY5: 0 | CZ5: 0 | DA5: 0 | DB5: 0 | DC5: 0 | DD5: 0 | DE5: 0 | DF5: 0 | DG5: 0 | DH5: 0 | DI5: 0 | DJ5: 0 | DK5: 0 | DL5: 0 | DM5: 0 | DN5: 0 | DO5: 0 | DP5: 0 | DQ5: 0 | DR5: 0 | DS5: 0 | DT5: 0 | DU5: 0 | DV5: 0 | DW5: 0 | DX5: 0 | DY5: 0 | DZ5: 0 | EC5: Total demand 2020 | ED5: % of 2020 demand | EE5: Total demand 2050 | EF5: Elimination | EG5: Reuse | EH5: Subsitution | EI5: Recycling | EJ5: Remaining demand | EK5: Elimination | EL5: Reuse | EM5: Subsitution | EN5: Recycling | EO5: Remaining demand
A6: RR | B6: Fertilizer subsitution (Switch to organic farming) | C6: mTons | D6: 0 | E6: 0 | F6: 0 | G6: 0 | H6: 0 | I6: 0 | J6: 0 | K6: 0 | L6: 0 | M6: 0 | N6: 0 | O6: 0 | P6: 0 | Q6: 0 | R6: 0 | S6: 0 | T6: 0 | U6: 0 | V6: 0 | W6: 0 | X6: 0 | Y6: 0 | Z6: 0 | AA6: 0 | AB6: 0 | AC6: 0 | AD6: 0 | AE6: 0 | AF6: 0 | AG6: 0 | AH6: 0 | AJ6: 0 | AK6: 0 | AL6: 0 | AM6: 0 | AN6: 0 | AO6: 0 | AP6: 0 | AQ6: 0 | AR6: 0 | AS6: 0 | AT6: 0 | AU6: 0 | AV6: 0 | AW6: 0 | AX6: 0 | AY6: 0 | AZ6: 0 | BA6: 0 | BB6: 0 | BC6: 0 | BD6: 0 | BE6: 0 | BF6: 0 | BG6: 0 | BH6: 0 | BI6: 0 | BJ6: 0 | BK6: 0 | BL6: 0 | BM6: 0 | BN6: 0 | BP6: 0 | BQ6: 0 | BR6: 0 | BS6: 0 | BT6: 0 | BU6: 0 | BV6: 0 | BW6: 0 | BX6: 0 | BY6: 0 | BZ6: 0 | CA6: 0 | CB6: 0 | CC6: 0 | CD6: 0 | CE6: 0 | CF6: 0 | CG6: 0 | CH6: 0 | CI6: 0 | CJ6: 0 | CK6: 0 | CL6: 0 | CM6: 0 | CN6: 0 | CO6: 0 | CP6: 0 | CQ6: 0 | CR6: 0 | CS6: 0 | CT6: 0 | CV6: 0 | CW6: 0 | CX6: 0 | CY6: 0 | CZ6: 0 | DA6: 0 | DB6: 0 | DC6: 0 | DD6: 0 | DE6: 0 | DF6: 0 | DG6: 0 | DH6: 0 | DI6: 0 | DJ6: 0 | DK6: 0 | DL6: 0 | DM6: 0 | DN6: 0 | DO6: 0 | DP6: 0 | DQ6: 0 | DR6: 0 | DS6: 0 | DT6: 0 | DU6: 0 | DV6: 0 | DW6: 0 | DX6: 0 | DY6: 0 | DZ6: 0 | EB6: Ferti | EC6: 131.90798 | ED6: =EC6/$EC$13 -> 0.19803019 | EE6: 158.18581 | EF6: =AH5 -> 0 | EG6: =AH6 -> 0 | EH6: 0 | EI6: 0 | EJ6: =EE6-SUM(EF6:EI6) -> 158.18581 | EK6: =EF6/$EE6 -> 0 | EL6: =EG6/$EE6 -> 0 | EM6: =EH6/$EE6 -> 0 | EN6: =EI6/$EE6 -> 0 | EO6: =EJ6/$EE6 -> 1 | EP6: =EF6/EF$13 -> 0
A7: R | B7: Fuel additive elimination | C7: mTons | D7: ='Yearly BTX'!D10+'Yearly Methanol'!D12 -> 0 | E7: ='Yearly BTX'!E10+'Yearly Methanol'!E12 -> 0.72809657 | F7: ='Yearly BTX'!F10+'Yearly Methanol'!F12 -> 1.4859786 | G7: ='Yearly BTX'!G10+'Yearly Methanol'!G12 -> 2.2746126 | H7: ='Yearly BTX'!H10+'Yearly Methanol'!H12 -> 3.0949943 | I7: ='Yearly BTX'!I10+'Yearly Methanol'!I12 -> 3.9481484 | J7: ='Yearly BTX'!J10+'Yearly Methanol'!J12 -> 4.8351305 | K7: ='Yearly BTX'!K10+'Yearly Methanol'!K12 -> 5.7570273 | ... AH7: ='Yearly BTX'!AH10+'Yearly Methanol'!AH12 -> 66.071576 | AJ7: ='Yearly BTX'!AJ10+'Yearly Methanol'!AJ12 -> 0 | AK7: ='Yearly BTX'!AK10+'Yearly Methanol'!AK12 -> 0.72809657 | AL7: ='Yearly BTX'!AL10+'Yearly Methanol'!AL12 -> 1.4859786 | AM7: ='Yearly BTX'!AM10+'Yearly Methanol'!AM12 -> 2.2746126 | AN7: ='Yearly BTX'!AN10+'Yearly Methanol'!AN12 -> 3.0949943 | AO7: ='Yearly BTX'!AO10+'Yearly Methanol'!AO12 -> 3.9481484 | AP7: ='Yearly BTX'!AP10+'Yearly Methanol'!AP12 -> 4.8351305 | AQ7: ='Yearly BTX'!AQ10+'Yearly Methanol'!AQ12 -> 5.7570273 | ... BN7: ='Yearly BTX'!BN10+'Yearly Methanol'!BN12 -> 66.071576 | BP7: 0 | BQ7: 0 | BR7: 0 | BS7: 0 | BT7: 0 | BU7: 0 | BV7: 0 | BW7: 0 | BX7: 0 | BY7: 0 | BZ7: 0 | CA7: 0 | CB7: 0 | CC7: 0 | CD7: 0 | CE7: 0 | CF7: 0 | CG7: 0 | CH7: 0 | CI7: 0 | CJ7: 0 | CK7: 0 | CL7: 0 | CM7: 0 | CN7: 0 | CO7: 0 | CP7: 0 | CQ7: 0 | CR7: 0 | CS7: 0 | CT7: 0 | CV7: 0 | CW7: 0 | CX7: 0 | CY7: 0 | CZ7: 0 | DA7: 0 | DB7: 0 | DC7: 0 | DD7: 0 | DE7: 0 | DF7: 0 | DG7: 0 | DH7: 0 | DI7: 0 | DJ7: 0 | DK7: 0 | DL7: 0 | DM7: 0 | DN7: 0 | DO7: 0 | DP7: 0 | DQ7: 0 | DR7: 0 | DS7: 0 | DT7: 0 | DU7: 0 | DV7: 0 | DW7: 0 | DX7: 0 | DY7: 0 | DZ7: 0 | EB7: Pack | EC7: =SUM('R&S - Packaging and hh goods'!I4:O4) -> 187.00627 | ED7: =EC7/$EC$13 -> 0.28074788 | EE7: =SUM('R&S - Packaging and hh goods'!I6:O6) -> 277.98913 | EF7: =AH8 -> 0 | EG7: =AH9 -> 0 | EH7: =AH10+AH11 -> 0 | EI7: =EI16 -> 60.980528 | EJ7: =EE7-SUM(EF7:EI7) -> 217.0086 | EK7: =EF7/$EE7 -> 0 | EL7: =EG7/$EE7 -> 0 | EM7: =EH7/$EE7 -> 0 | EN7: =EI7/$EE7 -> 0.21936299 | EO7: =EJ7/$EE7 -> 0.78063701 | EP7: =EF7/EF$13 -> 0
A8: R | B8: Packaging reduction | C8: mTons | D8: ='Yearly Butadiene'!D19+'Yearly BTX'!D28+'Yearly Methanol'!D30+'Yearly HC Ethylene'!D27+'Yearly HC Propylene'!D15 -> 0 | E8: ='Yearly Butadiene'!E19+'Yearly BTX'!E28+'Yearly Methanol'!E30+'Yearly HC Ethylene'!E27+'Yearly HC Propylene'!E15 -> 0 | F8: ='Yearly Butadiene'!F19+'Yearly BTX'!F28+'Yearly Methanol'!F30+'Yearly HC Ethylene'!F27+'Yearly HC Propylene'!F15 -> 0 | G8: ='Yearly Butadiene'!G19+'Yearly BTX'!G28+'Yearly Methanol'!G30+'Yearly HC Ethylene'!G27+'Yearly HC Propylene'!G15 -> 0 | H8: ='Yearly Butadiene'!H19+'Yearly BTX'!H28+'Yearly Methanol'!H30+'Yearly HC Ethylene'!H27+'Yearly HC Propylene'!H15 -> 0 | I8: ='Yearly Butadiene'!I19+'Yearly BTX'!I28+'Yearly Methanol'!I30+'Yearly HC Ethylene'!I27+'Yearly HC Propylene'!I15 -> 0 | J8: ='Yearly Butadiene'!J19+'Yearly BTX'!J28+'Yearly Methanol'!J30+'Yearly HC Ethylene'!J27+'Yearly HC Propylene'!J15 -> 0 | K8: ='Yearly Butadiene'!K19+'Yearly BTX'!K28+'Yearly Methanol'!K30+'Yearly HC Ethylene'!K27+'Yearly HC Propylene'!K15 -> 0 | ... AH8: ='Yearly Butadiene'!AH19+'Yearly BTX'!AH28+'Yearly Methanol'!AH30+'Yearly HC Ethylene'!AH27+'Yearly HC Propylene'!AH15 -> 0 | AJ8: ='Yearly Butadiene'!AJ19+'Yearly BTX'!AJ28+'Yearly Methanol'!AJ30+'Yearly LC Ethylene'!D27+'Yearly LC Propylene'!D15 -> 0 | AK8: ='Yearly Butadiene'!AK19+'Yearly BTX'!AK28+'Yearly Methanol'!AK30+'Yearly LC Ethylene'!E27+'Yearly LC Propylene'!E15 -> 0 | AL8: ='Yearly Butadiene'!AL19+'Yearly BTX'!AL28+'Yearly Methanol'!AL30+'Yearly LC Ethylene'!F27+'Yearly LC Propylene'!F15 -> 0 | AM8: ='Yearly Butadiene'!AM19+'Yearly BTX'!AM28+'Yearly Methanol'!AM30+'Yearly LC Ethylene'!G27+'Yearly LC Propylene'!G15 -> 0 | AN8: ='Yearly Butadiene'!AN19+'Yearly BTX'!AN28+'Yearly Methanol'!AN30+'Yearly LC Ethylene'!H27+'Yearly LC Propylene'!H15 -> 0 | AO8: ='Yearly Butadiene'!AO19+'Yearly BTX'!AO28+'Yearly Methanol'!AO30+'Yearly LC Ethylene'!I27+'Yearly LC Propylene'!I15 -> 0 | AP8: ='Yearly Butadiene'!AP19+'Yearly BTX'!AP28+'Yearly Methanol'!AP30+'Yearly LC Ethylene'!J27+'Yearly LC Propylene'!J15 -> 0 | AQ8: ='Yearly Butadiene'!AQ19+'Yearly BTX'!AQ28+'Yearly Methanol'!AQ30+'Yearly LC Ethylene'!K27+'Yearly LC Propylene'!K15 -> 0 | ... BN8: ='Yearly Butadiene'!BN19+'Yearly BTX'!BN28+'Yearly Methanol'!BN30+'Yearly LC Ethylene'!AH27+'Yearly LC Propylene'!AH15 -> 0 | BP8: 0 | BQ8: 0 | BR8: 0 | BS8: 0 | BT8: 0 | BU8: 0 | BV8: 0 | BW8: 0 | BX8: 0 | BY8: 0 | BZ8: 0 | CA8: 0 | CB8: 0 | CC8: 0 | CD8: 0 | CE8: 0 | CF8: 0 | CG8: 0 | CH8: 0 | CI8: 0 | CJ8: 0 | CK8: 0 | CL8: 0 | CM8: 0 | CN8: 0 | CO8: 0 | CP8: 0 | CQ8: 0 | CR8: 0 | CS8: 0 | CT8: 0 | CV8: 0 | CW8: 0 | CX8: 0 | CY8: 0 | CZ8: 0 | DA8: 0 | DB8: 0 | DC8: 0 | DD8: 0 | DE8: 0 | DF8: 0 | DG8: 0 | DH8: 0 | DI8: 0 | DJ8: 0 | DK8: 0 | DL8: 0 | DM8: 0 | DN8: 0 | DO8: 0 | DP8: 0 | DQ8: 0 | DR8: 0 | DS8: 0 | DT8: 0 | DU8: 0 | DV8: 0 | DW8: 0 | DX8: 0 | DY8: 0 | DZ8: 0 | EB8: Building | EC8: =SUM('R&S - Buildings'!I4:O4) -> 68.497699 | ED8: =EC8/$EC$13 -> 0.1028339 | EE8: =SUM('R&S - Buildings'!I6:O6) -> 109.15985 | EF8: =AH14 -> 0 | EG8: =0 -> 0 | EH8: =AH15 -> 0 | EI8: =EI17 -> 69.966906 | EJ8: =EE8-SUM(EF8:EI8) -> 39.192947 | EK8: =EF8/$EE8 -> 0 | EL8: =EG8/$EE8 -> 0 | EM8: =EH8/$EE8 -> 0 | EN8: =EI8/$EE8 -> 0.64095823 | EO8: =EJ8/$EE8 -> 0.35904177 | EP8: =EF8/EF$13 -> 0
A9: RR | B9: Packaging reuse | C9: mTons | D9: ='Yearly Butadiene'!D20+'Yearly BTX'!D29+'Yearly Methanol'!D31+'Yearly HC Ethylene'!D28+'Yearly HC Propylene'!D16 -> 0 | E9: ='Yearly Butadiene'!E20+'Yearly BTX'!E29+'Yearly Methanol'!E31+'Yearly HC Ethylene'!E28+'Yearly HC Propylene'!E16 -> 0 | F9: ='Yearly Butadiene'!F20+'Yearly BTX'!F29+'Yearly Methanol'!F31+'Yearly HC Ethylene'!F28+'Yearly HC Propylene'!F16 -> 0 | G9: ='Yearly Butadiene'!G20+'Yearly BTX'!G29+'Yearly Methanol'!G31+'Yearly HC Ethylene'!G28+'Yearly HC Propylene'!G16 -> 0 | H9: ='Yearly Butadiene'!H20+'Yearly BTX'!H29+'Yearly Methanol'!H31+'Yearly HC Ethylene'!H28+'Yearly HC Propylene'!H16 -> 0 | I9: ='Yearly Butadiene'!I20+'Yearly BTX'!I29+'Yearly Methanol'!I31+'Yearly HC Ethylene'!I28+'Yearly HC Propylene'!I16 -> 0 | J9: ='Yearly Butadiene'!J20+'Yearly BTX'!J29+'Yearly Methanol'!J31+'Yearly HC Ethylene'!J28+'Yearly HC Propylene'!J16 -> 0 | K9: ='Yearly Butadiene'!K20+'Yearly BTX'!K29+'Yearly Methanol'!K31+'Yearly HC Ethylene'!K28+'Yearly HC Propylene'!K16 -> 0 | ... AH9: ='Yearly Butadiene'!AH20+'Yearly BTX'!AH29+'Yearly Methanol'!AH31+'Yearly HC Ethylene'!AH28+'Yearly HC Propylene'!AH16 -> 0 | AJ9: ='Yearly Butadiene'!AJ20+'Yearly BTX'!AJ29+'Yearly Methanol'!AJ31+'Yearly LC Ethylene'!D28+'Yearly LC Propylene'!D16 -> 0 | AK9: ='Yearly Butadiene'!AK20+'Yearly BTX'!AK29+'Yearly Methanol'!AK31+'Yearly LC Ethylene'!E28+'Yearly LC Propylene'!E16 -> 0 | AL9: ='Yearly Butadiene'!AL20+'Yearly BTX'!AL29+'Yearly Methanol'!AL31+'Yearly LC Ethylene'!F28+'Yearly LC Propylene'!F16 -> 0 | AM9: ='Yearly Butadiene'!AM20+'Yearly BTX'!AM29+'Yearly Methanol'!AM31+'Yearly LC Ethylene'!G28+'Yearly LC Propylene'!G16 -> 0 | AN9: ='Yearly Butadiene'!AN20+'Yearly BTX'!AN29+'Yearly Methanol'!AN31+'Yearly LC Ethylene'!H28+'Yearly LC Propylene'!H16 -> 0 | AO9: ='Yearly Butadiene'!AO20+'Yearly BTX'!AO29+'Yearly Methanol'!AO31+'Yearly LC Ethylene'!I28+'Yearly LC Propylene'!I16 -> 0 | AP9: ='Yearly Butadiene'!AP20+'Yearly BTX'!AP29+'Yearly Methanol'!AP31+'Yearly LC Ethylene'!J28+'Yearly LC Propylene'!J16 -> 0 | AQ9: ='Yearly Butadiene'!AQ20+'Yearly BTX'!AQ29+'Yearly Methanol'!AQ31+'Yearly LC Ethylene'!K28+'Yearly LC Propylene'!K16 -> 0 | ... BN9: ='Yearly Butadiene'!BN20+'Yearly BTX'!BN29+'Yearly Methanol'!BN31+'Yearly LC Ethylene'!AH28+'Yearly LC Propylene'!AH16 -> 0 | BP9: 0 | BQ9: 0 | BR9: 0 | BS9: 0 | BT9: 0 | BU9: 0 | BV9: 0 | BW9: 0 | BX9: 0 | BY9: 0 | BZ9: 0 | CA9: 0 | CB9: 0 | CC9: 0 | CD9: 0 | CE9: 0 | CF9: 0 | CG9: 0 | CH9: 0 | CI9: 0 | CJ9: 0 | CK9: 0 | CL9: 0 | CM9: 0 | CN9: 0 | CO9: 0 | CP9: 0 | CQ9: 0 | CR9: 0 | CS9: 0 | CT9: 0 | CV9: 0 | CW9: 0 | CX9: 0 | CY9: 0 | CZ9: 0 | DA9: 0 | DB9: 0 | DC9: 0 | DD9: 0 | DE9: 0 | DF9: 0 | DG9: 0 | DH9: 0 | DI9: 0 | DJ9: 0 | DK9: 0 | DL9: 0 | DM9: 0 | DN9: 0 | DO9: 0 | DP9: 0 | DQ9: 0 | DR9: 0 | DS9: 0 | DT9: 0 | DU9: 0 | DV9: 0 | DW9: 0 | DX9: 0 | DY9: 0 | DZ9: 0 | EB9: Transport | EC9: =SUM('R&S - Transportation'!C4:K4) -> 106.90047 | ED9: =EC9/$EC$13 -> 0.16048703 | EE9: =SUM('R&S - Transportation'!C7:J7) -> 135.62387 | EF9: =AH13 -> 0 | EG9: =AH12 -> 0 | EH9: =0 -> 0 | EI9: =EI18 -> 16.617891 | EJ9: =EE9-SUM(EF9:EI9) -> 119.00598 | EK9: =EF9/$EE9 -> 0 | EL9: =EG9/$EE9 -> 0 | EM9: =EH9/$EE9 -> 0 | EN9: =EI9/$EE9 -> 0.12252925 | EO9: =EJ9/$EE9 -> 0.87747075 | EP9: =EF9/EF$13 -> 0
A10: S | B10: Packaging substitution Paper | C10: mTons | D10: ='Yearly Butadiene'!D22+'Yearly BTX'!D31+'Yearly Methanol'!D33+'Yearly HC Ethylene'!D30+'Yearly HC Propylene'!D18 -> 0 | E10: ='Yearly Butadiene'!E22+'Yearly BTX'!E31+'Yearly Methanol'!E33+'Yearly HC Ethylene'!E30+'Yearly HC Propylene'!E18 -> 0 | F10: ='Yearly Butadiene'!F22+'Yearly BTX'!F31+'Yearly Methanol'!F33+'Yearly HC Ethylene'!F30+'Yearly HC Propylene'!F18 -> 0 | G10: ='Yearly Butadiene'!G22+'Yearly BTX'!G31+'Yearly Methanol'!G33+'Yearly HC Ethylene'!G30+'Yearly HC Propylene'!G18 -> 0 | H10: ='Yearly Butadiene'!H22+'Yearly BTX'!H31+'Yearly Methanol'!H33+'Yearly HC Ethylene'!H30+'Yearly HC Propylene'!H18 -> 0 | I10: ='Yearly Butadiene'!I22+'Yearly BTX'!I31+'Yearly Methanol'!I33+'Yearly HC Ethylene'!I30+'Yearly HC Propylene'!I18 -> 0 | J10: ='Yearly Butadiene'!J22+'Yearly BTX'!J31+'Yearly Methanol'!J33+'Yearly HC Ethylene'!J30+'Yearly HC Propylene'!J18 -> 0 | K10: ='Yearly Butadiene'!K22+'Yearly BTX'!K31+'Yearly Methanol'!K33+'Yearly HC Ethylene'!K30+'Yearly HC Propylene'!K18 -> 0 | ... AH10: ='Yearly Butadiene'!AH22+'Yearly BTX'!AH31+'Yearly Methanol'!AH33+'Yearly HC Ethylene'!AH30+'Yearly HC Propylene'!AH18 -> 0 | AJ10: ='Yearly Butadiene'!AJ22+'Yearly BTX'!AJ31+'Yearly Methanol'!AJ33+'Yearly LC Ethylene'!D30+'Yearly LC Propylene'!D18 -> 0 | AK10: ='Yearly Butadiene'!AK22+'Yearly BTX'!AK31+'Yearly Methanol'!AK33+'Yearly LC Ethylene'!E30+'Yearly LC Propylene'!E18 -> 0 | AL10: ='Yearly Butadiene'!AL22+'Yearly BTX'!AL31+'Yearly Methanol'!AL33+'Yearly LC Ethylene'!F30+'Yearly LC Propylene'!F18 -> 0 | AM10: ='Yearly Butadiene'!AM22+'Yearly BTX'!AM31+'Yearly Methanol'!AM33+'Yearly LC Ethylene'!G30+'Yearly LC Propylene'!G18 -> 0 | AN10: ='Yearly Butadiene'!AN22+'Yearly BTX'!AN31+'Yearly Methanol'!AN33+'Yearly LC Ethylene'!H30+'Yearly LC Propylene'!H18 -> 0 | AO10: ='Yearly Butadiene'!AO22+'Yearly BTX'!AO31+'Yearly Methanol'!AO33+'Yearly LC Ethylene'!I30+'Yearly LC Propylene'!I18 -> 0 | AP10: ='Yearly Butadiene'!AP22+'Yearly BTX'!AP31+'Yearly Methanol'!AP33+'Yearly LC Ethylene'!J30+'Yearly LC Propylene'!J18 -> 0 | AQ10: ='Yearly Butadiene'!AQ22+'Yearly BTX'!AQ31+'Yearly Methanol'!AQ33+'Yearly LC Ethylene'!K30+'Yearly LC Propylene'!K18 -> 0 | ... BN10: ='Yearly Butadiene'!BN22+'Yearly BTX'!BN31+'Yearly Methanol'!BN33+'Yearly LC Ethylene'!AH30+'Yearly LC Propylene'!AH18 -> 0 | BP10: 0 | BQ10: 0 | BR10: 0 | BS10: 0 | BT10: 0 | BU10: 0 | BV10: 0 | BW10: 0 | BX10: 0 | BY10: 0 | BZ10: 0 | CA10: 0 | CB10: 0 | CC10: 0 | CD10: 0 | CE10: 0 | CF10: 0 | CG10: 0 | CH10: 0 | CI10: 0 | CJ10: 0 | CK10: 0 | CL10: 0 | CM10: 0 | CN10: 0 | CO10: 0 | CP10: 0 | CQ10: 0 | CR10: 0 | CS10: 0 | CT10: 0 | CV10: 0 | CW10: 0 | CX10: 0 | CY10: 0 | CZ10: 0 | DA10: 0 | DB10: 0 | DC10: 0 | DD10: 0 | DE10: 0 | DF10: 0 | DG10: 0 | DH10: 0 | DI10: 0 | DJ10: 0 | DK10: 0 | DL10: 0 | DM10: 0 | DN10: 0 | DO10: 0 | DP10: 0 | DQ10: 0 | DR10: 0 | DS10: 0 | DT10: 0 | DU10: 0 | DV10: 0 | DW10: 0 | DX10: 0 | DY10: 0 | DZ10: 0 | EB10: Fashion | EC10: ='Demand - Industry shares'!L16 -> 83.333906 | ED10: =EC10/$EC$13 -> 0.12510713 | EE10: =SUM('R&S - Apparel'!D6:J6) -> 24.934953 | EF10: =AH16 -> 0 | EG10: =AH17 -> 0 | EH10: =AH18 -> 0 | EI10: =EI19 -> 7.7131795 | EJ10: =EE10-SUM(EF10:EI10) -> 17.221773 | EK10: =EF10/$EE10 -> 0 | EL10: =EG10/$EE10 -> 0 | EM10: =EH10/$EE10 -> 0 | EN10: =EI10/$EE10 -> 0.30933203 | EO10: =EJ10/$EE10 -> 0.69066797 | EP10: =EF10/EF$13 -> 0
A11: S | B11: Packaging Substitution Compostables | C11: mTons | D11: ='Yearly Butadiene'!D23+'Yearly BTX'!D32+'Yearly Methanol'!D34+'Yearly HC Ethylene'!D31+'Yearly HC Propylene'!D19 -> 0 | E11: ='Yearly Butadiene'!E23+'Yearly BTX'!E32+'Yearly Methanol'!E34+'Yearly HC Ethylene'!E31+'Yearly HC Propylene'!E19 -> 0 | F11: ='Yearly Butadiene'!F23+'Yearly BTX'!F32+'Yearly Methanol'!F34+'Yearly HC Ethylene'!F31+'Yearly HC Propylene'!F19 -> 0 | G11: ='Yearly Butadiene'!G23+'Yearly BTX'!G32+'Yearly Methanol'!G34+'Yearly HC Ethylene'!G31+'Yearly HC Propylene'!G19 -> 0 | H11: ='Yearly Butadiene'!H23+'Yearly BTX'!H32+'Yearly Methanol'!H34+'Yearly HC Ethylene'!H31+'Yearly HC Propylene'!H19 -> 0 | I11: ='Yearly Butadiene'!I23+'Yearly BTX'!I32+'Yearly Methanol'!I34+'Yearly HC Ethylene'!I31+'Yearly HC Propylene'!I19 -> 0 | J11: ='Yearly Butadiene'!J23+'Yearly BTX'!J32+'Yearly Methanol'!J34+'Yearly HC Ethylene'!J31+'Yearly HC Propylene'!J19 -> 0 | K11: ='Yearly Butadiene'!K23+'Yearly BTX'!K32+'Yearly Methanol'!K34+'Yearly HC Ethylene'!K31+'Yearly HC Propylene'!K19 -> 0 | ... AH11: ='Yearly Butadiene'!AH23+'Yearly BTX'!AH32+'Yearly Methanol'!AH34+'Yearly HC Ethylene'!AH31+'Yearly HC Propylene'!AH19 -> 0 | AJ11: ='Yearly Butadiene'!AJ23+'Yearly BTX'!AJ32+'Yearly Methanol'!AJ34+'Yearly LC Ethylene'!D31+'Yearly LC Propylene'!D19 -> 0 | AK11: ='Yearly Butadiene'!AK23+'Yearly BTX'!AK32+'Yearly Methanol'!AK34+'Yearly LC Ethylene'!E31+'Yearly LC Propylene'!E19 -> 0 | AL11: ='Yearly Butadiene'!AL23+'Yearly BTX'!AL32+'Yearly Methanol'!AL34+'Yearly LC Ethylene'!F31+'Yearly LC Propylene'!F19 -> 0 | AM11: ='Yearly Butadiene'!AM23+'Yearly BTX'!AM32+'Yearly Methanol'!AM34+'Yearly LC Ethylene'!G31+'Yearly LC Propylene'!G19 -> 0 | AN11: ='Yearly Butadiene'!AN23+'Yearly BTX'!AN32+'Yearly Methanol'!AN34+'Yearly LC Ethylene'!H31+'Yearly LC Propylene'!H19 -> 0 | AO11: ='Yearly Butadiene'!AO23+'Yearly BTX'!AO32+'Yearly Methanol'!AO34+'Yearly LC Ethylene'!I31+'Yearly LC Propylene'!I19 -> 0 | AP11: ='Yearly Butadiene'!AP23+'Yearly BTX'!AP32+'Yearly Methanol'!AP34+'Yearly LC Ethylene'!J31+'Yearly LC Propylene'!J19 -> 0 | AQ11: ='Yearly Butadiene'!AQ23+'Yearly BTX'!AQ32+'Yearly Methanol'!AQ34+'Yearly LC Ethylene'!K31+'Yearly LC Propylene'!K19 -> 0 | ... BN11: ='Yearly Butadiene'!BN23+'Yearly BTX'!BN32+'Yearly Methanol'!BN34+'Yearly LC Ethylene'!AH31+'Yearly LC Propylene'!AH19 -> 0 | BP11: 0 | BQ11: 0 | BR11: 0 | BS11: 0 | BT11: 0 | BU11: 0 | BV11: 0 | BW11: 0 | BX11: 0 | BY11: 0 | BZ11: 0 | CA11: 0 | CB11: 0 | CC11: 0 | CD11: 0 | CE11: 0 | CF11: 0 | CG11: 0 | CH11: 0 | CI11: 0 | CJ11: 0 | CK11: 0 | CL11: 0 | CM11: 0 | CN11: 0 | CO11: 0 | CP11: 0 | CQ11: 0 | CR11: 0 | CS11: 0 | CT11: 0 | CV11: 0 | CW11: 0 | CX11: 0 | CY11: 0 | CZ11: 0 | DA11: 0 | DB11: 0 | DC11: 0 | DD11: 0 | DE11: 0 | DF11: 0 | DG11: 0 | DH11: 0 | DI11: 0 | DJ11: 0 | DK11: 0 | DL11: 0 | DM11: 0 | DN11: 0 | DO11: 0 | DP11: 0 | DQ11: 0 | DR11: 0 | DS11: 0 | DT11: 0 | DU11: 0 | DV11: 0 | DW11: 0 | DX11: 0 | DY11: 0 | DZ11: 0 | EB11: Additives | ED11: =EC11/$EC$13 -> 0 | EF11: =AH7 -> 66.071576 | EP11: =EF11/EF$13 -> 1
A12: RR | B12: MaaS | C12: mTons | D12: ='Yearly Butadiene'!D13+'Yearly BTX'!D19+'Yearly Methanol'!D21+'Yearly HC Ethylene'!D15+'Yearly HC Propylene'!D9 -> 0 | E12: ='Yearly Butadiene'!E13+'Yearly BTX'!E19+'Yearly Methanol'!E21+'Yearly HC Ethylene'!E15+'Yearly HC Propylene'!E9 -> 0 | F12: ='Yearly Butadiene'!F13+'Yearly BTX'!F19+'Yearly Methanol'!F21+'Yearly HC Ethylene'!F15+'Yearly HC Propylene'!F9 -> 0 | G12: ='Yearly Butadiene'!G13+'Yearly BTX'!G19+'Yearly Methanol'!G21+'Yearly HC Ethylene'!G15+'Yearly HC Propylene'!G9 -> 0 | H12: ='Yearly Butadiene'!H13+'Yearly BTX'!H19+'Yearly Methanol'!H21+'Yearly HC Ethylene'!H15+'Yearly HC Propylene'!H9 -> 0 | I12: ='Yearly Butadiene'!I13+'Yearly BTX'!I19+'Yearly Methanol'!I21+'Yearly HC Ethylene'!I15+'Yearly HC Propylene'!I9 -> 0 | J12: ='Yearly Butadiene'!J13+'Yearly BTX'!J19+'Yearly Methanol'!J21+'Yearly HC Ethylene'!J15+'Yearly HC Propylene'!J9 -> 0 | K12: ='Yearly Butadiene'!K13+'Yearly BTX'!K19+'Yearly Methanol'!K21+'Yearly HC Ethylene'!K15+'Yearly HC Propylene'!K9 -> 0 | ... AH12: ='Yearly Butadiene'!AH13+'Yearly BTX'!AH19+'Yearly Methanol'!AH21+'Yearly HC Ethylene'!AH15+'Yearly HC Propylene'!AH9 -> 0 | AJ12: ='Yearly Butadiene'!AJ13+'Yearly BTX'!AJ19+'Yearly Methanol'!AJ21+'Yearly LC Ethylene'!D15+'Yearly LC Propylene'!D9 -> 0 | AK12: ='Yearly Butadiene'!AK13+'Yearly BTX'!AK19+'Yearly Methanol'!AK21+'Yearly LC Ethylene'!E15+'Yearly LC Propylene'!E9 -> 0 | AL12: ='Yearly Butadiene'!AL13+'Yearly BTX'!AL19+'Yearly Methanol'!AL21+'Yearly LC Ethylene'!F15+'Yearly LC Propylene'!F9 -> 0 | AM12: ='Yearly Butadiene'!AM13+'Yearly BTX'!AM19+'Yearly Methanol'!AM21+'Yearly LC Ethylene'!G15+'Yearly LC Propylene'!G9 -> 0 | AN12: ='Yearly Butadiene'!AN13+'Yearly BTX'!AN19+'Yearly Methanol'!AN21+'Yearly LC Ethylene'!H15+'Yearly LC Propylene'!H9 -> 0 | AO12: ='Yearly Butadiene'!AO13+'Yearly BTX'!AO19+'Yearly Methanol'!AO21+'Yearly LC Ethylene'!I15+'Yearly LC Propylene'!I9 -> 0 | AP12: ='Yearly Butadiene'!AP13+'Yearly BTX'!AP19+'Yearly Methanol'!AP21+'Yearly LC Ethylene'!J15+'Yearly LC Propylene'!J9 -> 0 | AQ12: ='Yearly Butadiene'!AQ13+'Yearly BTX'!AQ19+'Yearly Methanol'!AQ21+'Yearly LC Ethylene'!K15+'Yearly LC Propylene'!K9 -> 0 | ... BN12: ='Yearly Butadiene'!BN13+'Yearly BTX'!BN19+'Yearly Methanol'!BN21+'Yearly LC Ethylene'!AH15+'Yearly LC Propylene'!AH9 -> 0 | BP12: 0 | BQ12: 0 | BR12: 0 | BS12: 0 | BT12: 0 | BU12: 0 | BV12: 0 | BW12: 0 | BX12: 0 | BY12: 0 | BZ12: 0 | CA12: 0 | CB12: 0 | CC12: 0 | CD12: 0 | CE12: 0 | CF12: 0 | CG12: 0 | CH12: 0 | CI12: 0 | CJ12: 0 | CK12: 0 | CL12: 0 | CM12: 0 | CN12: 0 | CO12: 0 | CP12: 0 | CQ12: 0 | CR12: 0 | CS12: 0 | CT12: 0 | CV12: 0 | CW12: 0 | CX12: 0 | CY12: 0 | CZ12: 0 | DA12: 0 | DB12: 0 | DC12: 0 | DD12: 0 | DE12: 0 | DF12: 0 | DG12: 0 | DH12: 0 | DI12: 0 | DJ12: 0 | DK12: 0 | DL12: 0 | DM12: 0 | DN12: 0 | DO12: 0 | DP12: 0 | DQ12: 0 | DR12: 0 | DS12: 0 | DT12: 0 | DU12: 0 | DV12: 0 | DW12: 0 | DX12: 0 | DY12: 0 | DZ12: 0 | EB12: Others | EC12: 88.454043 | ED12: =EC12/$EC$13 -> 0.13279387 | EF12: =AH19 -> 0 | EP12: =EF12/EF$13 -> 0
A13: R | B13: Vehicle life extension | C13: mTons | D13: ='Yearly Butadiene'!D14+'Yearly BTX'!D20+'Yearly Methanol'!D22+'Yearly HC Ethylene'!D16+'Yearly HC Propylene'!D10 -> 0 | E13: ='Yearly Butadiene'!E14+'Yearly BTX'!E20+'Yearly Methanol'!E22+'Yearly HC Ethylene'!E16+'Yearly HC Propylene'!E10 -> 0 | F13: ='Yearly Butadiene'!F14+'Yearly BTX'!F20+'Yearly Methanol'!F22+'Yearly HC Ethylene'!F16+'Yearly HC Propylene'!F10 -> 0 | G13: ='Yearly Butadiene'!G14+'Yearly BTX'!G20+'Yearly Methanol'!G22+'Yearly HC Ethylene'!G16+'Yearly HC Propylene'!G10 -> 0 | H13: ='Yearly Butadiene'!H14+'Yearly BTX'!H20+'Yearly Methanol'!H22+'Yearly HC Ethylene'!H16+'Yearly HC Propylene'!H10 -> 0 | I13: ='Yearly Butadiene'!I14+'Yearly BTX'!I20+'Yearly Methanol'!I22+'Yearly HC Ethylene'!I16+'Yearly HC Propylene'!I10 -> 0 | J13: ='Yearly Butadiene'!J14+'Yearly BTX'!J20+'Yearly Methanol'!J22+'Yearly HC Ethylene'!J16+'Yearly HC Propylene'!J10 -> 0 | K13: ='Yearly Butadiene'!K14+'Yearly BTX'!K20+'Yearly Methanol'!K22+'Yearly HC Ethylene'!K16+'Yearly HC Propylene'!K10 -> 0 | ... AH13: ='Yearly Butadiene'!AH14+'Yearly BTX'!AH20+'Yearly Methanol'!AH22+'Yearly HC Ethylene'!AH16+'Yearly HC Propylene'!AH10 -> 0 | AJ13: ='Yearly Butadiene'!AJ14+'Yearly BTX'!AJ20+'Yearly Methanol'!AJ22+'Yearly LC Ethylene'!D16+'Yearly LC Propylene'!D10 -> 0 | AK13: ='Yearly Butadiene'!AK14+'Yearly BTX'!AK20+'Yearly Methanol'!AK22+'Yearly LC Ethylene'!E16+'Yearly LC Propylene'!E10 -> 0 | AL13: ='Yearly Butadiene'!AL14+'Yearly BTX'!AL20+'Yearly Methanol'!AL22+'Yearly LC Ethylene'!F16+'Yearly LC Propylene'!F10 -> 0 | AM13: ='Yearly Butadiene'!AM14+'Yearly BTX'!AM20+'Yearly Methanol'!AM22+'Yearly LC Ethylene'!G16+'Yearly LC Propylene'!G10 -> 0 | AN13: ='Yearly Butadiene'!AN14+'Yearly BTX'!AN20+'Yearly Methanol'!AN22+'Yearly LC Ethylene'!H16+'Yearly LC Propylene'!H10 -> 0 | AO13: ='Yearly Butadiene'!AO14+'Yearly BTX'!AO20+'Yearly Methanol'!AO22+'Yearly LC Ethylene'!I16+'Yearly LC Propylene'!I10 -> 0 | AP13: ='Yearly Butadiene'!AP14+'Yearly BTX'!AP20+'Yearly Methanol'!AP22+'Yearly LC Ethylene'!J16+'Yearly LC Propylene'!J10 -> 0 | AQ13: ='Yearly Butadiene'!AQ14+'Yearly BTX'!AQ20+'Yearly Methanol'!AQ22+'Yearly LC Ethylene'!K16+'Yearly LC Propylene'!K10 -> 0 | ... BN13: ='Yearly Butadiene'!BN14+'Yearly BTX'!BN20+'Yearly Methanol'!BN22+'Yearly LC Ethylene'!AH16+'Yearly LC Propylene'!AH10 -> 0 | BP13: 0 | BQ13: 0 | BR13: 0 | BS13: 0 | BT13: 0 | BU13: 0 | BV13: 0 | BW13: 0 | BX13: 0 | BY13: 0 | BZ13: 0 | CA13: 0 | CB13: 0 | CC13: 0 | CD13: 0 | CE13: 0 | CF13: 0 | CG13: 0 | CH13: 0 | CI13: 0 | CJ13: 0 | CK13: 0 | CL13: 0 | CM13: 0 | CN13: 0 | CO13: 0 | CP13: 0 | CQ13: 0 | CR13: 0 | CS13: 0 | CT13: 0 | CV13: 0 | CW13: 0 | CX13: 0 | CY13: 0 | CZ13: 0 | DA13: 0 | DB13: 0 | DC13: 0 | DD13: 0 | DE13: 0 | DF13: 0 | DG13: 0 | DH13: 0 | DI13: 0 | DJ13: 0 | DK13: 0 | DL13: 0 | DM13: 0 | DN13: 0 | DO13: 0 | DP13: 0 | DQ13: 0 | DR13: 0 | DS13: 0 | DT13: 0 | DU13: 0 | DV13: 0 | DW13: 0 | DX13: 0 | DY13: 0 | DZ13: 0 | EC13: =SUM(EC6:EC12) -> 666.10037 | EF13: =SUM(EF6:EF12) -> 66.071576 | EP13: =EF13/EF$13 -> 1
A14: R | B14: Building reduction | C14: mTons | D14: ='Yearly Butadiene'!D27+'Yearly BTX'!D39+'Yearly Methanol'!D41+'Yearly HC Ethylene'!D41+'Yearly HC Propylene'!D23 -> 0 | E14: ='Yearly Butadiene'!E27+'Yearly BTX'!E39+'Yearly Methanol'!E41+'Yearly HC Ethylene'!E41+'Yearly HC Propylene'!E23 -> 0 | F14: ='Yearly Butadiene'!F27+'Yearly BTX'!F39+'Yearly Methanol'!F41+'Yearly HC Ethylene'!F41+'Yearly HC Propylene'!F23 -> 0 | G14: ='Yearly Butadiene'!G27+'Yearly BTX'!G39+'Yearly Methanol'!G41+'Yearly HC Ethylene'!G41+'Yearly HC Propylene'!G23 -> 0 | H14: ='Yearly Butadiene'!H27+'Yearly BTX'!H39+'Yearly Methanol'!H41+'Yearly HC Ethylene'!H41+'Yearly HC Propylene'!H23 -> 0 | I14: ='Yearly Butadiene'!I27+'Yearly BTX'!I39+'Yearly Methanol'!I41+'Yearly HC Ethylene'!I41+'Yearly HC Propylene'!I23 -> 0 | J14: ='Yearly Butadiene'!J27+'Yearly BTX'!J39+'Yearly Methanol'!J41+'Yearly HC Ethylene'!J41+'Yearly HC Propylene'!J23 -> 0 | K14: ='Yearly Butadiene'!K27+'Yearly BTX'!K39+'Yearly Methanol'!K41+'Yearly HC Ethylene'!K41+'Yearly HC Propylene'!K23 -> 0 | ... AH14: ='Yearly Butadiene'!AH27+'Yearly BTX'!AH39+'Yearly Methanol'!AH41+'Yearly HC Ethylene'!AH41+'Yearly HC Propylene'!AH23 -> 0 | AJ14: ='Yearly Butadiene'!AJ27+'Yearly BTX'!AJ39+'Yearly Methanol'!AJ41+'Yearly LC Ethylene'!D41+'Yearly LC Propylene'!D23 -> 0 | AK14: ='Yearly Butadiene'!AK27+'Yearly BTX'!AK39+'Yearly Methanol'!AK41+'Yearly LC Ethylene'!E41+'Yearly LC Propylene'!E23 -> 0 | AL14: ='Yearly Butadiene'!AL27+'Yearly BTX'!AL39+'Yearly Methanol'!AL41+'Yearly LC Ethylene'!F41+'Yearly LC Propylene'!F23 -> 0 | AM14: ='Yearly Butadiene'!AM27+'Yearly BTX'!AM39+'Yearly Methanol'!AM41+'Yearly LC Ethylene'!G41+'Yearly LC Propylene'!G23 -> 0 | AN14: ='Yearly Butadiene'!AN27+'Yearly BTX'!AN39+'Yearly Methanol'!AN41+'Yearly LC Ethylene'!H41+'Yearly LC Propylene'!H23 -> 0 | AO14: ='Yearly Butadiene'!AO27+'Yearly BTX'!AO39+'Yearly Methanol'!AO41+'Yearly LC Ethylene'!I41+'Yearly LC Propylene'!I23 -> 0 | AP14: ='Yearly Butadiene'!AP27+'Yearly BTX'!AP39+'Yearly Methanol'!AP41+'Yearly LC Ethylene'!J41+'Yearly LC Propylene'!J23 -> 0 | AQ14: ='Yearly Butadiene'!AQ27+'Yearly BTX'!AQ39+'Yearly Methanol'!AQ41+'Yearly LC Ethylene'!K41+'Yearly LC Propylene'!K23 -> 0 | ... BN14: ='Yearly Butadiene'!BN27+'Yearly BTX'!BN39+'Yearly Methanol'!BN41+'Yearly LC Ethylene'!AH41+'Yearly LC Propylene'!AH23 -> 0 | BP14: 0 | BQ14: 0 | BR14: 0 | BS14: 0 | BT14: 0 | BU14: 0 | BV14: 0 | BW14: 0 | BX14: 0 | BY14: 0 | BZ14: 0 | CA14: 0 | CB14: 0 | CC14: 0 | CD14: 0 | CE14: 0 | CF14: 0 | CG14: 0 | CH14: 0 | CI14: 0 | CJ14: 0 | CK14: 0 | CL14: 0 | CM14: 0 | CN14: 0 | CO14: 0 | CP14: 0 | CQ14: 0 | CR14: 0 | CS14: 0 | CT14: 0 | CV14: 0 | CW14: 0 | CX14: 0 | CY14: 0 | CZ14: 0 | DA14: 0 | DB14: 0 | DC14: 0 | DD14: 0 | DE14: 0 | DF14: 0 | DG14: 0 | DH14: 0 | DI14: 0 | DJ14: 0 | DK14: 0 | DL14: 0 | DM14: 0 | DN14: 0 | DO14: 0 | DP14: 0 | DQ14: 0 | DR14: 0 | DS14: 0 | DT14: 0 | DU14: 0 | DV14: 0 | DW14: 0 | DX14: 0 | DY14: 0 | DZ14: 0 | EC14: =SUM('Yearly Summary'!D9) -> 661.63221
A15: S | B15: Building substitution | C15: mTons | D15: ='Yearly Butadiene'!D28+'Yearly BTX'!D40+'Yearly Methanol'!D42+'Yearly HC Ethylene'!D42+'Yearly HC Propylene'!D24 -> 0 | E15: ='Yearly Butadiene'!E28+'Yearly BTX'!E40+'Yearly Methanol'!E42+'Yearly HC Ethylene'!E42+'Yearly HC Propylene'!E24 -> 0 | F15: ='Yearly Butadiene'!F28+'Yearly BTX'!F40+'Yearly Methanol'!F42+'Yearly HC Ethylene'!F42+'Yearly HC Propylene'!F24 -> 0 | G15: ='Yearly Butadiene'!G28+'Yearly BTX'!G40+'Yearly Methanol'!G42+'Yearly HC Ethylene'!G42+'Yearly HC Propylene'!G24 -> 0 | H15: ='Yearly Butadiene'!H28+'Yearly BTX'!H40+'Yearly Methanol'!H42+'Yearly HC Ethylene'!H42+'Yearly HC Propylene'!H24 -> 0 | I15: ='Yearly Butadiene'!I28+'Yearly BTX'!I40+'Yearly Methanol'!I42+'Yearly HC Ethylene'!I42+'Yearly HC Propylene'!I24 -> 0 | J15: ='Yearly Butadiene'!J28+'Yearly BTX'!J40+'Yearly Methanol'!J42+'Yearly HC Ethylene'!J42+'Yearly HC Propylene'!J24 -> 0 | K15: ='Yearly Butadiene'!K28+'Yearly BTX'!K40+'Yearly Methanol'!K42+'Yearly HC Ethylene'!K42+'Yearly HC Propylene'!K24 -> 0 | ... AH15: ='Yearly Butadiene'!AH28+'Yearly BTX'!AH40+'Yearly Methanol'!AH42+'Yearly HC Ethylene'!AH42+'Yearly HC Propylene'!AH24 -> 0 | AJ15: ='Yearly Butadiene'!AJ28+'Yearly BTX'!AJ40+'Yearly Methanol'!AJ42+'Yearly LC Ethylene'!D42+'Yearly LC Propylene'!D24 -> 0 | AK15: ='Yearly Butadiene'!AK28+'Yearly BTX'!AK40+'Yearly Methanol'!AK42+'Yearly LC Ethylene'!E42+'Yearly LC Propylene'!E24 -> 0 | AL15: ='Yearly Butadiene'!AL28+'Yearly BTX'!AL40+'Yearly Methanol'!AL42+'Yearly LC Ethylene'!F42+'Yearly LC Propylene'!F24 -> 0 | AM15: ='Yearly Butadiene'!AM28+'Yearly BTX'!AM40+'Yearly Methanol'!AM42+'Yearly LC Ethylene'!G42+'Yearly LC Propylene'!G24 -> 0 | AN15: ='Yearly Butadiene'!AN28+'Yearly BTX'!AN40+'Yearly Methanol'!AN42+'Yearly LC Ethylene'!H42+'Yearly LC Propylene'!H24 -> 0 | AO15: ='Yearly Butadiene'!AO28+'Yearly BTX'!AO40+'Yearly Methanol'!AO42+'Yearly LC Ethylene'!I42+'Yearly LC Propylene'!I24 -> 0 | AP15: ='Yearly Butadiene'!AP28+'Yearly BTX'!AP40+'Yearly Methanol'!AP42+'Yearly LC Ethylene'!J42+'Yearly LC Propylene'!J24 -> 0 | AQ15: ='Yearly Butadiene'!AQ28+'Yearly BTX'!AQ40+'Yearly Methanol'!AQ42+'Yearly LC Ethylene'!K42+'Yearly LC Propylene'!K24 -> 0 | ... BN15: ='Yearly Butadiene'!BN28+'Yearly BTX'!BN40+'Yearly Methanol'!BN42+'Yearly LC Ethylene'!AH42+'Yearly LC Propylene'!AH24 -> 0 | BP15: 0 | BQ15: 0 | BR15: 0 | BS15: 0 | BT15: 0 | BU15: 0 | BV15: 0 | BW15: 0 | BX15: 0 | BY15: 0 | BZ15: 0 | CA15: 0 | CB15: 0 | CC15: 0 | CD15: 0 | CE15: 0 | CF15: 0 | CG15: 0 | CH15: 0 | CI15: 0 | CJ15: 0 | CK15: 0 | CL15: 0 | CM15: 0 | CN15: 0 | CO15: 0 | CP15: 0 | CQ15: 0 | CR15: 0 | CS15: 0 | CT15: 0 | CV15: 0 | CW15: 0 | CX15: 0 | CY15: 0 | CZ15: 0 | DA15: 0 | DB15: 0 | DC15: 0 | DD15: 0 | DE15: 0 | DF15: 0 | DG15: 0 | DH15: 0 | DI15: 0 | DJ15: 0 | DK15: 0 | DL15: 0 | DM15: 0 | DN15: 0 | DO15: 0 | DP15: 0 | DQ15: 0 | DR15: 0 | DS15: 0 | DT15: 0 | DU15: 0 | DV15: 0 | DW15: 0 | DX15: 0 | DY15: 0 | DZ15: 0 | EB15: Ferti | EE15: =EE6 -> 158.18581 | EF15: =BN5 -> 0 | EG15: =BN6 -> 0 | EH15: =0 -> 0 | EI15: 0 | EJ15: =EE15-SUM(EF15:EI15) -> 158.18581 | EK15: =EF15/$EE15 -> 0 | EL15: =EG15/$EE15 -> 0 | EM15: =EH15/$EE15 -> 0 | EN15: =EI15/$EE15 -> 0 | EO15: =EJ15/$EE15 -> 1 | EP15: =EF15/EF$22 -> 0 | EQ15: 0.11379023 | ER15: 0 | ES15: 0 | ET15: 0 | EU15: 0.88620977
A16: R | B16: Apparel - waste reduction | C16: mTons | D16: ='Yearly Butadiene'!D31+'Yearly BTX'!D46+'Yearly Methanol'!D48+'Yearly HC Ethylene'!D51+'Yearly HC Propylene'!D27 -> 0 | E16: ='Yearly Butadiene'!E31+'Yearly BTX'!E46+'Yearly Methanol'!E48+'Yearly HC Ethylene'!E51+'Yearly HC Propylene'!E27 -> 0 | F16: ='Yearly Butadiene'!F31+'Yearly BTX'!F46+'Yearly Methanol'!F48+'Yearly HC Ethylene'!F51+'Yearly HC Propylene'!F27 -> 0 | G16: ='Yearly Butadiene'!G31+'Yearly BTX'!G46+'Yearly Methanol'!G48+'Yearly HC Ethylene'!G51+'Yearly HC Propylene'!G27 -> 0 | H16: ='Yearly Butadiene'!H31+'Yearly BTX'!H46+'Yearly Methanol'!H48+'Yearly HC Ethylene'!H51+'Yearly HC Propylene'!H27 -> 0 | I16: ='Yearly Butadiene'!I31+'Yearly BTX'!I46+'Yearly Methanol'!I48+'Yearly HC Ethylene'!I51+'Yearly HC Propylene'!I27 -> 0 | J16: ='Yearly Butadiene'!J31+'Yearly BTX'!J46+'Yearly Methanol'!J48+'Yearly HC Ethylene'!J51+'Yearly HC Propylene'!J27 -> 0 | K16: ='Yearly Butadiene'!K31+'Yearly BTX'!K46+'Yearly Methanol'!K48+'Yearly HC Ethylene'!K51+'Yearly HC Propylene'!K27 -> 0 | ... AH16: ='Yearly Butadiene'!AH31+'Yearly BTX'!AH46+'Yearly Methanol'!AH48+'Yearly HC Ethylene'!AH51+'Yearly HC Propylene'!AH27 -> 0 | AJ16: ='Yearly Butadiene'!AJ31+'Yearly BTX'!AJ46+'Yearly Methanol'!AJ48+'Yearly LC Ethylene'!D51+'Yearly LC Propylene'!D27 -> 0 | AK16: ='Yearly Butadiene'!AK31+'Yearly BTX'!AK46+'Yearly Methanol'!AK48+'Yearly LC Ethylene'!E51+'Yearly LC Propylene'!E27 -> 0 | AL16: ='Yearly Butadiene'!AL31+'Yearly BTX'!AL46+'Yearly Methanol'!AL48+'Yearly LC Ethylene'!F51+'Yearly LC Propylene'!F27 -> 0 | AM16: ='Yearly Butadiene'!AM31+'Yearly BTX'!AM46+'Yearly Methanol'!AM48+'Yearly LC Ethylene'!G51+'Yearly LC Propylene'!G27 -> 0 | AN16: ='Yearly Butadiene'!AN31+'Yearly BTX'!AN46+'Yearly Methanol'!AN48+'Yearly LC Ethylene'!H51+'Yearly LC Propylene'!H27 -> 0 | AO16: ='Yearly Butadiene'!AO31+'Yearly BTX'!AO46+'Yearly Methanol'!AO48+'Yearly LC Ethylene'!I51+'Yearly LC Propylene'!I27 -> 0 | AP16: ='Yearly Butadiene'!AP31+'Yearly BTX'!AP46+'Yearly Methanol'!AP48+'Yearly LC Ethylene'!J51+'Yearly LC Propylene'!J27 -> 0 | AQ16: ='Yearly Butadiene'!AQ31+'Yearly BTX'!AQ46+'Yearly Methanol'!AQ48+'Yearly LC Ethylene'!K51+'Yearly LC Propylene'!K27 -> 0 | ... BN16: ='Yearly Butadiene'!BN31+'Yearly BTX'!BN46+'Yearly Methanol'!BN48+'Yearly LC Ethylene'!AH51+'Yearly LC Propylene'!AH27 -> 0 | BP16: 0 | BQ16: 0 | BR16: 0 | BS16: 0 | BT16: 0 | BU16: 0 | BV16: 0 | BW16: 0 | BX16: 0 | BY16: 0 | BZ16: 0 | CA16: 0 | CB16: 0 | CC16: 0 | CD16: 0 | CE16: 0 | CF16: 0 | CG16: 0 | CH16: 0 | CI16: 0 | CJ16: 0 | CK16: 0 | CL16: 0 | CM16: 0 | CN16: 0 | CO16: 0 | CP16: 0 | CQ16: 0 | CR16: 0 | CS16: 0 | CT16: 0 | CV16: 0 | CW16: 0 | CX16: 0 | CY16: 0 | CZ16: 0 | DA16: 0 | DB16: 0 | DC16: 0 | DD16: 0 | DE16: 0 | DF16: 0 | DG16: 0 | DH16: 0 | DI16: 0 | DJ16: 0 | DK16: 0 | DL16: 0 | DM16: 0 | DN16: 0 | DO16: 0 | DP16: 0 | DQ16: 0 | DR16: 0 | DS16: 0 | DT16: 0 | DU16: 0 | DV16: 0 | DW16: 0 | DX16: 0 | DY16: 0 | DZ16: 0 | EB16: Pack | EE16: =EE7 -> 277.98913 | EF16: =BN8 -> 0 | EG16: =BN9 -> 0 | EH16: =BN10+BN11 -> 0 | EI16: =SUM('Yearly BTX'!BN76:BN77,'Yearly Butadiene'!BN49:BN50,'Yearly Methanol'!BN78:BN79,'Yearly LC Ethylene'!AH93:AH94,'Yearly HC Propylene'!AH44:AH45) -> 60.980528 | EJ16: =EE16-SUM(EF16:EI16) -> 217.0086 | EK16: =EF16/$EE16 -> 0 | EL16: =EG16/$EE16 -> 0 | EM16: =EH16/$EE16 -> 0 | EN16: =EI16/$EE16 -> 0.21936299 | EO16: =EJ16/$EE16 -> 0.78063701 | EP16: =EF16/EF$22 -> 0 | EQ16: 0.069246918 | ER16: 0.18527826 | ES16: 0.13661662 | ET16: 0.086200532 | EU16: 0.52265767
A17: RR | B17: Apparel - NBM | C17: mTons | D17: ='Yearly Butadiene'!D32+'Yearly BTX'!D47+'Yearly Methanol'!D49+'Yearly HC Ethylene'!D52+'Yearly HC Propylene'!D28 -> 0 | E17: ='Yearly Butadiene'!E32+'Yearly BTX'!E47+'Yearly Methanol'!E49+'Yearly HC Ethylene'!E52+'Yearly HC Propylene'!E28 -> 0 | F17: ='Yearly Butadiene'!F32+'Yearly BTX'!F47+'Yearly Methanol'!F49+'Yearly HC Ethylene'!F52+'Yearly HC Propylene'!F28 -> 0 | G17: ='Yearly Butadiene'!G32+'Yearly BTX'!G47+'Yearly Methanol'!G49+'Yearly HC Ethylene'!G52+'Yearly HC Propylene'!G28 -> 0 | H17: ='Yearly Butadiene'!H32+'Yearly BTX'!H47+'Yearly Methanol'!H49+'Yearly HC Ethylene'!H52+'Yearly HC Propylene'!H28 -> 0 | I17: ='Yearly Butadiene'!I32+'Yearly BTX'!I47+'Yearly Methanol'!I49+'Yearly HC Ethylene'!I52+'Yearly HC Propylene'!I28 -> 0 | J17: ='Yearly Butadiene'!J32+'Yearly BTX'!J47+'Yearly Methanol'!J49+'Yearly HC Ethylene'!J52+'Yearly HC Propylene'!J28 -> 0 | K17: ='Yearly Butadiene'!K32+'Yearly BTX'!K47+'Yearly Methanol'!K49+'Yearly HC Ethylene'!K52+'Yearly HC Propylene'!K28 -> 0 | ... AH17: ='Yearly Butadiene'!AH32+'Yearly BTX'!AH47+'Yearly Methanol'!AH49+'Yearly HC Ethylene'!AH52+'Yearly HC Propylene'!AH28 -> 0 | AJ17: ='Yearly Butadiene'!AJ32+'Yearly BTX'!AJ47+'Yearly Methanol'!AJ49+'Yearly LC Ethylene'!D52+'Yearly LC Propylene'!D28 -> 0 | AK17: ='Yearly Butadiene'!AK32+'Yearly BTX'!AK47+'Yearly Methanol'!AK49+'Yearly LC Ethylene'!E52+'Yearly LC Propylene'!E28 -> 0 | AL17: ='Yearly Butadiene'!AL32+'Yearly BTX'!AL47+'Yearly Methanol'!AL49+'Yearly LC Ethylene'!F52+'Yearly LC Propylene'!F28 -> 0 | AM17: ='Yearly Butadiene'!AM32+'Yearly BTX'!AM47+'Yearly Methanol'!AM49+'Yearly LC Ethylene'!G52+'Yearly LC Propylene'!G28 -> 0 | AN17: ='Yearly Butadiene'!AN32+'Yearly BTX'!AN47+'Yearly Methanol'!AN49+'Yearly LC Ethylene'!H52+'Yearly LC Propylene'!H28 -> 0 | AO17: ='Yearly Butadiene'!AO32+'Yearly BTX'!AO47+'Yearly Methanol'!AO49+'Yearly LC Ethylene'!I52+'Yearly LC Propylene'!I28 -> 0 | AP17: ='Yearly Butadiene'!AP32+'Yearly BTX'!AP47+'Yearly Methanol'!AP49+'Yearly LC Ethylene'!J52+'Yearly LC Propylene'!J28 -> 0 | AQ17: ='Yearly Butadiene'!AQ32+'Yearly BTX'!AQ47+'Yearly Methanol'!AQ49+'Yearly LC Ethylene'!K52+'Yearly LC Propylene'!K28 -> 0 | ... BN17: ='Yearly Butadiene'!BN32+'Yearly BTX'!BN47+'Yearly Methanol'!BN49+'Yearly LC Ethylene'!AH52+'Yearly LC Propylene'!AH28 -> 0 | BP17: 0 | BQ17: 0 | BR17: 0 | BS17: 0 | BT17: 0 | BU17: 0 | BV17: 0 | BW17: 0 | BX17: 0 | BY17: 0 | BZ17: 0 | CA17: 0 | CB17: 0 | CC17: 0 | CD17: 0 | CE17: 0 | CF17: 0 | CG17: 0 | CH17: 0 | CI17: 0 | CJ17: 0 | CK17: 0 | CL17: 0 | CM17: 0 | CN17: 0 | CO17: 0 | CP17: 0 | CQ17: 0 | CR17: 0 | CS17: 0 | CT17: 0 | CV17: 0 | CW17: 0 | CX17: 0 | CY17: 0 | CZ17: 0 | DA17: 0 | DB17: 0 | DC17: 0 | DD17: 0 | DE17: 0 | DF17: 0 | DG17: 0 | DH17: 0 | DI17: 0 | DJ17: 0 | DK17: 0 | DL17: 0 | DM17: 0 | DN17: 0 | DO17: 0 | DP17: 0 | DQ17: 0 | DR17: 0 | DS17: 0 | DT17: 0 | DU17: 0 | DV17: 0 | DW17: 0 | DX17: 0 | DY17: 0 | DZ17: 0 | EB17: Building | EE17: =EE8 -> 109.15985 | EF17: =BN14 -> 0 | EG17: 0 | EH17: =BN15 -> 0 | EI17: =SUM('Yearly BTX'!AH96:AH99,'Yearly Butadiene'!AH60:AH63,'Yearly Methanol'!AH98:AH101,'Yearly HC Ethylene'!AH123:AH126,'Yearly HC Propylene'!AH55:AH58) -> 69.966906 | EJ17: =EE17-SUM(EF17:EI17) -> 39.192947 | EK17: =EF17/$EE17 -> 0 | EL17: =EG17/$EE17 -> 0 | EM17: =EH17/$EE17 -> 0 | EN17: =EI17/$EE17 -> 0.64095823 | EO17: =EJ17/$EE17 -> 0.35904177 | EP17: =EF17/EF$22 -> 0 | EQ17: 0.21563035 | ER17: 0 | ES17: 0.072452751 | ET17: 0.28400607 | EU17: 0.42791082
A18: S | B18: Apparel - substitution | C18: mTons | D18: ='Yearly Butadiene'!D34+'Yearly BTX'!D49+'Yearly Methanol'!D51+'Yearly HC Ethylene'!D54+'Yearly HC Propylene'!D30 -> 0 | E18: ='Yearly Butadiene'!E34+'Yearly BTX'!E49+'Yearly Methanol'!E51+'Yearly HC Ethylene'!E54+'Yearly HC Propylene'!E30 -> 0 | F18: ='Yearly Butadiene'!F34+'Yearly BTX'!F49+'Yearly Methanol'!F51+'Yearly HC Ethylene'!F54+'Yearly HC Propylene'!F30 -> 0 | G18: ='Yearly Butadiene'!G34+'Yearly BTX'!G49+'Yearly Methanol'!G51+'Yearly HC Ethylene'!G54+'Yearly HC Propylene'!G30 -> 0 | H18: ='Yearly Butadiene'!H34+'Yearly BTX'!H49+'Yearly Methanol'!H51+'Yearly HC Ethylene'!H54+'Yearly HC Propylene'!H30 -> 0 | I18: ='Yearly Butadiene'!I34+'Yearly BTX'!I49+'Yearly Methanol'!I51+'Yearly HC Ethylene'!I54+'Yearly HC Propylene'!I30 -> 0 | J18: ='Yearly Butadiene'!J34+'Yearly BTX'!J49+'Yearly Methanol'!J51+'Yearly HC Ethylene'!J54+'Yearly HC Propylene'!J30 -> 0 | K18: ='Yearly Butadiene'!K34+'Yearly BTX'!K49+'Yearly Methanol'!K51+'Yearly HC Ethylene'!K54+'Yearly HC Propylene'!K30 -> 0 | ... AH18: ='Yearly Butadiene'!AH34+'Yearly BTX'!AH49+'Yearly Methanol'!AH51+'Yearly HC Ethylene'!AH54+'Yearly HC Propylene'!AH30 -> 0 | AJ18: ='Yearly Butadiene'!AJ34+'Yearly BTX'!AJ49+'Yearly Methanol'!AJ51+'Yearly LC Ethylene'!D54+'Yearly LC Propylene'!D30 -> 0 | AK18: ='Yearly Butadiene'!AK34+'Yearly BTX'!AK49+'Yearly Methanol'!AK51+'Yearly LC Ethylene'!E54+'Yearly LC Propylene'!E30 -> 0 | AL18: ='Yearly Butadiene'!AL34+'Yearly BTX'!AL49+'Yearly Methanol'!AL51+'Yearly LC Ethylene'!F54+'Yearly LC Propylene'!F30 -> 0 | AM18: ='Yearly Butadiene'!AM34+'Yearly BTX'!AM49+'Yearly Methanol'!AM51+'Yearly LC Ethylene'!G54+'Yearly LC Propylene'!G30 -> 0 | AN18: ='Yearly Butadiene'!AN34+'Yearly BTX'!AN49+'Yearly Methanol'!AN51+'Yearly LC Ethylene'!H54+'Yearly LC Propylene'!H30 -> 0 | AO18: ='Yearly Butadiene'!AO34+'Yearly BTX'!AO49+'Yearly Methanol'!AO51+'Yearly LC Ethylene'!I54+'Yearly LC Propylene'!I30 -> 0 | AP18: ='Yearly Butadiene'!AP34+'Yearly BTX'!AP49+'Yearly Methanol'!AP51+'Yearly LC Ethylene'!J54+'Yearly LC Propylene'!J30 -> 0 | AQ18: ='Yearly Butadiene'!AQ34+'Yearly BTX'!AQ49+'Yearly Methanol'!AQ51+'Yearly LC Ethylene'!K54+'Yearly LC Propylene'!K30 -> 0 | ... BN18: ='Yearly Butadiene'!BN34+'Yearly BTX'!BN49+'Yearly Methanol'!BN51+'Yearly LC Ethylene'!AH54+'Yearly LC Propylene'!AH30 -> 0 | BP18: 0 | BQ18: 0 | BR18: 0 | BS18: 0 | BT18: 0 | BU18: 0 | BV18: 0 | BW18: 0 | BX18: 0 | BY18: 0 | BZ18: 0 | CA18: 0 | CB18: 0 | CC18: 0 | CD18: 0 | CE18: 0 | CF18: 0 | CG18: 0 | CH18: 0 | CI18: 0 | CJ18: 0 | CK18: 0 | CL18: 0 | CM18: 0 | CN18: 0 | CO18: 0 | CP18: 0 | CQ18: 0 | CR18: 0 | CS18: 0 | CT18: 0 | CV18: 0 | CW18: 0 | CX18: 0 | CY18: 0 | CZ18: 0 | DA18: 0 | DB18: 0 | DC18: 0 | DD18: 0 | DE18: 0 | DF18: 0 | DG18: 0 | DH18: 0 | DI18: 0 | DJ18: 0 | DK18: 0 | DL18: 0 | DM18: 0 | DN18: 0 | DO18: 0 | DP18: 0 | DQ18: 0 | DR18: 0 | DS18: 0 | DT18: 0 | DU18: 0 | DV18: 0 | DW18: 0 | DX18: 0 | DY18: 0 | DZ18: 0 | EB18: Transport | EE18: =EE9 -> 135.62387 | EF18: =BN13 -> 0 | EG18: =BN12 -> 0 | EH18: 0 | EI18: =SUM('Yearly BTX'!AH83,'Yearly Butadiene'!AH53,'Yearly Methanol'!AH85,'Yearly HC Ethylene'!AH103,'Yearly HC Ethylene'!AH104,'Yearly HC Propylene'!AH48) -> 16.617891 | EJ18: =EE18-SUM(EF18:EI18) -> 119.00598 | EK18: =EF18/$EE18 -> 0 | EL18: =EG18/$EE18 -> 0 | EM18: =EH18/$EE18 -> 0 | EN18: =EI18/$EE18 -> 0.12252925 | EO18: =EJ18/$EE18 -> 0.87747075 | EP18: =EF18/EF$22 -> 0 | EQ18: 0.056323776 | ER18: 0.098069696 | ES18: 0 | ET18: 0.074600265 | EU18: 0.77100626
A19: R | B19: Others Reduction | C19: mTons | D19: ='Yearly Butadiene'!D37+'Yearly BTX'!D55+'Yearly Methanol'!D57+'Yearly HC Ethylene'!D63+'Yearly HC Propylene'!D33 -> 0 | E19: ='Yearly Butadiene'!E37+'Yearly BTX'!E55+'Yearly Methanol'!E57+'Yearly HC Ethylene'!E63+'Yearly HC Propylene'!E33 -> 0 | F19: ='Yearly Butadiene'!F37+'Yearly BTX'!F55+'Yearly Methanol'!F57+'Yearly HC Ethylene'!F63+'Yearly HC Propylene'!F33 -> 0 | G19: ='Yearly Butadiene'!G37+'Yearly BTX'!G55+'Yearly Methanol'!G57+'Yearly HC Ethylene'!G63+'Yearly HC Propylene'!G33 -> 0 | H19: ='Yearly Butadiene'!H37+'Yearly BTX'!H55+'Yearly Methanol'!H57+'Yearly HC Ethylene'!H63+'Yearly HC Propylene'!H33 -> 0 | I19: ='Yearly Butadiene'!I37+'Yearly BTX'!I55+'Yearly Methanol'!I57+'Yearly HC Ethylene'!I63+'Yearly HC Propylene'!I33 -> 0 | J19: ='Yearly Butadiene'!J37+'Yearly BTX'!J55+'Yearly Methanol'!J57+'Yearly HC Ethylene'!J63+'Yearly HC Propylene'!J33 -> 0 | K19: ='Yearly Butadiene'!K37+'Yearly BTX'!K55+'Yearly Methanol'!K57+'Yearly HC Ethylene'!K63+'Yearly HC Propylene'!K33 -> 0 | ... AH19: ='Yearly Butadiene'!AH37+'Yearly BTX'!AH55+'Yearly Methanol'!AH57+'Yearly HC Ethylene'!AH63+'Yearly HC Propylene'!AH33 -> 0 | AJ19: ='Yearly Butadiene'!AJ37+'Yearly BTX'!AJ55+'Yearly Methanol'!AJ57+'Yearly LC Ethylene'!D63+'Yearly LC Propylene'!D33 -> 0 | AK19: ='Yearly Butadiene'!AK37+'Yearly BTX'!AK55+'Yearly Methanol'!AK57+'Yearly LC Ethylene'!E63+'Yearly LC Propylene'!E33 -> 0 | AL19: ='Yearly Butadiene'!AL37+'Yearly BTX'!AL55+'Yearly Methanol'!AL57+'Yearly LC Ethylene'!F63+'Yearly LC Propylene'!F33 -> 0 | AM19: ='Yearly Butadiene'!AM37+'Yearly BTX'!AM55+'Yearly Methanol'!AM57+'Yearly LC Ethylene'!G63+'Yearly LC Propylene'!G33 -> 0 | AN19: ='Yearly Butadiene'!AN37+'Yearly BTX'!AN55+'Yearly Methanol'!AN57+'Yearly LC Ethylene'!H63+'Yearly LC Propylene'!H33 -> 0 | AO19: ='Yearly Butadiene'!AO37+'Yearly BTX'!AO55+'Yearly Methanol'!AO57+'Yearly LC Ethylene'!I63+'Yearly LC Propylene'!I33 -> 0 | AP19: ='Yearly Butadiene'!AP37+'Yearly BTX'!AP55+'Yearly Methanol'!AP57+'Yearly LC Ethylene'!J63+'Yearly LC Propylene'!J33 -> 0 | AQ19: ='Yearly Butadiene'!AQ37+'Yearly BTX'!AQ55+'Yearly Methanol'!AQ57+'Yearly LC Ethylene'!K63+'Yearly LC Propylene'!K33 -> 0 | ... BN19: ='Yearly Butadiene'!BN37+'Yearly BTX'!BN55+'Yearly Methanol'!BN57+'Yearly LC Ethylene'!AH63+'Yearly LC Propylene'!AH33 -> 0 | BP19: 0 | BQ19: 0 | BR19: 0 | BS19: 0 | BT19: 0 | BU19: 0 | BV19: 0 | BW19: 0 | BX19: 0 | BY19: 0 | BZ19: 0 | CA19: 0 | CB19: 0 | CC19: 0 | CD19: 0 | CE19: 0 | CF19: 0 | CG19: 0 | CH19: 0 | CI19: 0 | CJ19: 0 | CK19: 0 | CL19: 0 | CM19: 0 | CN19: 0 | CO19: 0 | CP19: 0 | CQ19: 0 | CR19: 0 | CS19: 0 | CT19: 0 | CV19: 0 | CW19: 0 | CX19: 0 | CY19: 0 | CZ19: 0 | DA19: 0 | DB19: 0 | DC19: 0 | DD19: 0 | DE19: 0 | DF19: 0 | DG19: 0 | DH19: 0 | DI19: 0 | DJ19: 0 | DK19: 0 | DL19: 0 | DM19: 0 | DN19: 0 | DO19: 0 | DP19: 0 | DQ19: 0 | DR19: 0 | DS19: 0 | DT19: 0 | DU19: 0 | DV19: 0 | DW19: 0 | DX19: 0 | DY19: 0 | DZ19: 0 | EB19: Fashion | EE19: =EE10 -> 24.934953 | EF19: =BN16 -> 0 | EG19: =BN17 -> 0 | EH19: =BN18 -> 0 | EI19: =SUM('Yearly BTX'!AH89:AH90,'Yearly Butadiene'!AH56:AH57,'Yearly Methanol'!AH91:AH92,'Yearly HC Ethylene'!AH113:AH114,'Yearly HC Propylene'!AH51:AH52) -> 7.7131795 | EJ19: =EE19-SUM(EF19:EI19) -> 17.221773 | EK19: =EF19/$EE19 -> 0 | EL19: =EG19/$EE19 -> 0 | EM19: =EH19/$EE19 -> 0 | EN19: =EI19/$EE19 -> 0.30933203 | EO19: =EJ19/$EE19 -> 0.69066797 | EP19: =EF19/EF$22 -> 0 | EQ19: 0.12392007 | ER19: 0.1685313 | ES19: 0.099136057 | ET19: 0.064354291 | EU19: 0.54405829
A20: S | B20: Others Substitution | C20: mTons | D20: ='Yearly Butadiene'!D38+'Yearly BTX'!D56+'Yearly Methanol'!D58+'Yearly HC Ethylene'!D64+'Yearly HC Propylene'!D34 -> 0 | E20: ='Yearly Butadiene'!E38+'Yearly BTX'!E56+'Yearly Methanol'!E58+'Yearly HC Ethylene'!E64+'Yearly HC Propylene'!E34 -> 0 | F20: ='Yearly Butadiene'!F38+'Yearly BTX'!F56+'Yearly Methanol'!F58+'Yearly HC Ethylene'!F64+'Yearly HC Propylene'!F34 -> 0 | G20: ='Yearly Butadiene'!G38+'Yearly BTX'!G56+'Yearly Methanol'!G58+'Yearly HC Ethylene'!G64+'Yearly HC Propylene'!G34 -> 0 | H20: ='Yearly Butadiene'!H38+'Yearly BTX'!H56+'Yearly Methanol'!H58+'Yearly HC Ethylene'!H64+'Yearly HC Propylene'!H34 -> 0 | I20: ='Yearly Butadiene'!I38+'Yearly BTX'!I56+'Yearly Methanol'!I58+'Yearly HC Ethylene'!I64+'Yearly HC Propylene'!I34 -> 0 | J20: ='Yearly Butadiene'!J38+'Yearly BTX'!J56+'Yearly Methanol'!J58+'Yearly HC Ethylene'!J64+'Yearly HC Propylene'!J34 -> 0 | K20: ='Yearly Butadiene'!K38+'Yearly BTX'!K56+'Yearly Methanol'!K58+'Yearly HC Ethylene'!K64+'Yearly HC Propylene'!K34 -> 0 | ... AH20: ='Yearly Butadiene'!AH38+'Yearly BTX'!AH56+'Yearly Methanol'!AH58+'Yearly HC Ethylene'!AH64+'Yearly HC Propylene'!AH34 -> 0 | AJ20: ='Yearly Butadiene'!AJ38+'Yearly BTX'!AJ56+'Yearly Methanol'!AJ58+'Yearly LC Ethylene'!D64+'Yearly LC Propylene'!D34 -> 0 | AK20: ='Yearly Butadiene'!AK38+'Yearly BTX'!AK56+'Yearly Methanol'!AK58+'Yearly LC Ethylene'!E64+'Yearly LC Propylene'!E34 -> 0 | AL20: ='Yearly Butadiene'!AL38+'Yearly BTX'!AL56+'Yearly Methanol'!AL58+'Yearly LC Ethylene'!F64+'Yearly LC Propylene'!F34 -> 0 | AM20: ='Yearly Butadiene'!AM38+'Yearly BTX'!AM56+'Yearly Methanol'!AM58+'Yearly LC Ethylene'!G64+'Yearly LC Propylene'!G34 -> 0 | AN20: ='Yearly Butadiene'!AN38+'Yearly BTX'!AN56+'Yearly Methanol'!AN58+'Yearly LC Ethylene'!H64+'Yearly LC Propylene'!H34 -> 0 | AO20: ='Yearly Butadiene'!AO38+'Yearly BTX'!AO56+'Yearly Methanol'!AO58+'Yearly LC Ethylene'!I64+'Yearly LC Propylene'!I34 -> 0 | AP20: ='Yearly Butadiene'!AP38+'Yearly BTX'!AP56+'Yearly Methanol'!AP58+'Yearly LC Ethylene'!J64+'Yearly LC Propylene'!J34 -> 0 | AQ20: ='Yearly Butadiene'!AQ38+'Yearly BTX'!AQ56+'Yearly Methanol'!AQ58+'Yearly LC Ethylene'!K64+'Yearly LC Propylene'!K34 -> 0 | ... BN20: ='Yearly Butadiene'!BN38+'Yearly BTX'!BN56+'Yearly Methanol'!BN58+'Yearly LC Ethylene'!AH64+'Yearly LC Propylene'!AH34 -> 0 | BP20: 0 | BQ20: 0 | BR20: 0 | BS20: 0 | BT20: 0 | BU20: 0 | BV20: 0 | BW20: 0 | BX20: 0 | BY20: 0 | BZ20: 0 | CA20: 0 | CB20: 0 | CC20: 0 | CD20: 0 | CE20: 0 | CF20: 0 | CG20: 0 | CH20: 0 | CI20: 0 | CJ20: 0 | CK20: 0 | CL20: 0 | CM20: 0 | CN20: 0 | CO20: 0 | CP20: 0 | CQ20: 0 | CR20: 0 | CS20: 0 | CT20: 0 | CV20: 0 | CW20: 0 | CX20: 0 | CY20: 0 | CZ20: 0 | DA20: 0 | DB20: 0 | DC20: 0 | DD20: 0 | DE20: 0 | DF20: 0 | DG20: 0 | DH20: 0 | DI20: 0 | DJ20: 0 | DK20: 0 | DL20: 0 | DM20: 0 | DN20: 0 | DO20: 0 | DP20: 0 | DQ20: 0 | DR20: 0 | DS20: 0 | DT20: 0 | DU20: 0 | DV20: 0 | DW20: 0 | DX20: 0 | DY20: 0 | DZ20: 0 | EB20: Additives | EF20: =BN7 -> 66.071576 | EP20: =EF20/EF$22 -> 1
B21: Increase Demand | C21: mTons | D21: 0 | E21: 6.3621974 | F21: 11.994548 | G21: 18.642835 | H21: 24.308807 | I21: 29.99443 | J21: 36.533741 | K21: 44.04135 | L21: 50.520061 | M21: 58.973038 | N21: 68.403844 | O21: 100.68486 | P21: 134.17429 | Q21: 166.87736 | R21: 200.79994 | S21: 232.94866 | T21: 300.66839 | U21: 365.10019 | V21: 427.25355 | W21: 485.13919 | X21: 541.76917 | Y21: 594.51432 | Z21: 645.73909 | AA21: 695.46075 | AB21: 741.69884 | AC21: 786.47544 | AD21: 792.60639 | AE21: 798.98752 | AF21: 804.65072 | AG21: 811.63205 | AH21: 818.9723 | AJ21: 0 | AK21: 6.3356412 | AL21: 11.940533 | AM21: 18.560435 | AN21: 24.197072 | AO21: 29.852387 | AP21: 36.360392 | AQ21: 43.83567 | AR21: 50.281003 | AS21: 58.699526 | AT21: 68.094775 | AU21: 100.3391 | AV21: 133.79069 | AW21: 166.45472 | AX21: 200.33706 | AY21: 232.44429 | AZ21: 300.12124 | BA21: 364.50896 | BB21: 426.61691 | BC21: 484.45575 | BD21: 541.03753 | BE21: 593.84466 | BF21: 645.13371 | BG21: 694.92204 | BH21: 741.22924 | BI21: 786.07746 | BJ21: 792.28259 | BK21: 798.74054 | BL21: 804.48326 | BM21: 811.5469 | BN21: 818.9723 | BP21: 0 | BQ21: 0 | BR21: 0 | BS21: 0 | BT21: 0 | BU21: 0 | BV21: 0 | BW21: 0 | BX21: 0 | BY21: 0 | BZ21: 0 | CA21: 0 | CB21: 0 | CC21: 0 | CD21: 0 | CE21: 0 | CF21: 0 | CG21: 0 | CH21: 0 | CI21: 0 | CJ21: 0 | CK21: 0 | CL21: 0 | CM21: 0 | CN21: 0 | CO21: 0 | CP21: 0 | CQ21: 0 | CR21: 0 | CS21: 0 | CT21: 0 | CV21: 0 | CW21: 0 | CX21: 0 | CY21: 0 | CZ21: 0 | DA21: 0 | DB21: 0 | DC21: 0 | DD21: 0 | DE21: 0 | DF21: 0 | DG21: 0 | DH21: 0 | DI21: 0 | DJ21: 0 | DK21: 0 | DL21: 0 | DM21: 0 | DN21: 0 | DO21: 0 | DP21: 0 | DQ21: 0 | DR21: 0 | DS21: 0 | DT21: 0 | DU21: 0 | DV21: 0 | DW21: 0 | DX21: 0 | DY21: 0 | DZ21: 0 | EB21: Others | EF21: =BN19 -> 0 | EP21: =EF21/EF$22 -> 0 | EQ21: 0.11379023 | ER21: 0.069246918 | ES21: 0.21563035 | ET21: 0.056323776 | EU21: 0.12392007
A22: M | B22: Mecahnical Recycling | C22: mTons | D22: ='Scope 3 Yearly'!D9 -> 30.3155 | E22: ='Scope 3 Yearly'!E9 -> 32.567335 | F22: ='Scope 3 Yearly'!F9 -> 35.305858 | G22: ='Scope 3 Yearly'!G9 -> 38.091801 | H22: ='Scope 3 Yearly'!H9 -> 40.909184 | I22: ='Scope 3 Yearly'!I9 -> 43.740982 | J22: ='Scope 3 Yearly'!J9 -> 46.669763 | K22: ='Scope 3 Yearly'!K9 -> 49.695667 | ... AH22: ='Scope 3 Yearly'!AH9 -> 225.65573 | AJ22: ='Scope 3 Yearly'!AJ9 -> 30.3155 | AK22: ='Scope 3 Yearly'!AK9 -> 32.567335 | AL22: ='Scope 3 Yearly'!AL9 -> 35.305858 | AM22: ='Scope 3 Yearly'!AM9 -> 38.091801 | AN22: ='Scope 3 Yearly'!AN9 -> 40.909184 | AO22: ='Scope 3 Yearly'!AO9 -> 43.740982 | AP22: ='Scope 3 Yearly'!AP9 -> 46.669763 | AQ22: ='Scope 3 Yearly'!AQ9 -> 49.695667 | ... BN22: ='Scope 3 Yearly'!BN9 -> 225.65573 | BP22: ='Scope 3 Yearly'!BP9 -> 30.3155 | BQ22: ='Scope 3 Yearly'!BQ9 -> 30.821769 | BR22: ='Scope 3 Yearly'!BR9 -> 31.336493 | BS22: ='Scope 3 Yearly'!BS9 -> 31.859812 | BT22: ='Scope 3 Yearly'!BT9 -> 32.391871 | BU22: ='Scope 3 Yearly'!BU9 -> 32.932815 | BV22: ='Scope 3 Yearly'!BV9 -> 33.482793 | BW22: ='Scope 3 Yearly'!BW9 -> 34.041956 | ... CT22: ='Scope 3 Yearly'!CT9 -> 49.825246 | CV22: ='Scope 3 Yearly'!CV9 -> 30.3155 | CW22: ='Scope 3 Yearly'!CW9 -> 32.567335 | CX22: ='Scope 3 Yearly'!CX9 -> 35.305858 | CY22: ='Scope 3 Yearly'!CY9 -> 38.091801 | CZ22: ='Scope 3 Yearly'!CZ9 -> 40.909184 | DA22: ='Scope 3 Yearly'!DA9 -> 43.740982 | DB22: ='Scope 3 Yearly'!DB9 -> 46.669763 | DC22: ='Scope 3 Yearly'!DC9 -> 49.695667 | ... DZ22: ='Scope 3 Yearly'!DZ9 -> 225.65573 | EF22: =SUM(EF15:EF21) -> 66.071576 | EP22: =EF22/EF$22 -> 1 | EQ22: 0 | ER22: 0.18527826 | ES22: 0 | ET22: 0.098069696 | EU22: 0.1685313
A23: M | B23: Chemical Recycling | C23: mTons | D23: ='Scope 3 Yearly'!D10 -> 0.0001435477 | E23: ='Scope 3 Yearly'!E10 -> 0.00031583905 | F23: ='Scope 3 Yearly'!F10 -> 0.00066777723 | G23: ='Scope 3 Yearly'!G10 -> 0.0014024693 | H23: ='Scope 3 Yearly'!H10 -> 0.0029231962 | I23: ='Scope 3 Yearly'!I10 -> 0.0060389711 | J23: ='Scope 3 Yearly'!J10 -> 0.012369595 | K23: ='Scope 3 Yearly'!K10 -> 0.02505819 | ... AH23: ='Scope 3 Yearly'!AH10 -> 17.498424 | AJ23: ='Scope 3 Yearly'!AJ10 -> 7.9316887e-05 | AK23: ='Scope 3 Yearly'!AK10 -> 0.0001754267 | AL23: ='Scope 3 Yearly'!AL10 -> 0.00037081619 | AM23: ='Scope 3 Yearly'!AM10 -> 0.00077865286 | AN23: ='Scope 3 Yearly'!AN10 -> 0.0016227665 | AO23: ='Scope 3 Yearly'!AO10 -> 0.0033522063 | AP23: ='Scope 3 Yearly'!AP10 -> 0.0068661531 | AQ23: ='Scope 3 Yearly'!AQ10 -> 0.013909671 | ... BN23: ='Scope 3 Yearly'!BN10 -> 9.7546726 | BP23: ='Scope 3 Yearly'!BP10 -> 0 | BQ23: ='Scope 3 Yearly'!BQ10 -> 0 | BR23: ='Scope 3 Yearly'!BR10 -> 0 | BS23: ='Scope 3 Yearly'!BS10 -> 0 | BT23: ='Scope 3 Yearly'!BT10 -> 0 | BU23: ='Scope 3 Yearly'!BU10 -> 0 | BV23: ='Scope 3 Yearly'!BV10 -> 0 | BW23: ='Scope 3 Yearly'!BW10 -> 0 | ... CT23: ='Scope 3 Yearly'!CT10 -> 0 | CV23: ='Scope 3 Yearly'!CV10 -> 7.9316887e-05 | CW23: ='Scope 3 Yearly'!CW10 -> 0.0001754267 | CX23: ='Scope 3 Yearly'!CX10 -> 0.00037081619 | CY23: ='Scope 3 Yearly'!CY10 -> 0.00077865286 | CZ23: ='Scope 3 Yearly'!CZ10 -> 0.0016227665 | DA23: ='Scope 3 Yearly'!DA10 -> 0.0033522063 | DB23: ='Scope 3 Yearly'!DB10 -> 0.0068661531 | DC23: ='Scope 3 Yearly'!DC10 -> 0.013909671 | ... DZ23: ='Scope 3 Yearly'!DZ10 -> 9.7546726 | EQ23: 0 | ER23: 0.13661662 | ES23: 0.072452751 | ET23: 0 | EU23: 0.099136057
B24: Waste management (collection + MRF) | C24: mTons | D24: =SUM(D22:D23)+'Scope 3 Yearly'!D11+'Scope 3 Yearly'!D12+'Scope 3 Yearly'!D13+0.5*'Scope 3 Yearly'!D14 -> 249.41421 | E24: =SUM(E22:E23)+'Scope 3 Yearly'!E11+'Scope 3 Yearly'!E12+'Scope 3 Yearly'!E13+0.5*'Scope 3 Yearly'!E14 -> 258.94777 | F24: =SUM(F22:F23)+'Scope 3 Yearly'!F11+'Scope 3 Yearly'!F12+'Scope 3 Yearly'!F13+0.5*'Scope 3 Yearly'!F14 -> 268.24524 | G24: =SUM(G22:G23)+'Scope 3 Yearly'!G11+'Scope 3 Yearly'!G12+'Scope 3 Yearly'!G13+0.5*'Scope 3 Yearly'!G14 -> 277.13623 | H24: =SUM(H22:H23)+'Scope 3 Yearly'!H11+'Scope 3 Yearly'!H12+'Scope 3 Yearly'!H13+0.5*'Scope 3 Yearly'!H14 -> 285.55982 | I24: =SUM(I22:I23)+'Scope 3 Yearly'!I11+'Scope 3 Yearly'!I12+'Scope 3 Yearly'!I13+0.5*'Scope 3 Yearly'!I14 -> 293.45713 | J24: =SUM(J22:J23)+'Scope 3 Yearly'!J11+'Scope 3 Yearly'!J12+'Scope 3 Yearly'!J13+0.5*'Scope 3 Yearly'!J14 -> 301.42094 | K24: =SUM(K22:K23)+'Scope 3 Yearly'!K11+'Scope 3 Yearly'!K12+'Scope 3 Yearly'!K13+0.5*'Scope 3 Yearly'!K14 -> 309.44556 | ... AH24: =SUM(AH22:AH23)+'Scope 3 Yearly'!AH11+'Scope 3 Yearly'!AH12+'Scope 3 Yearly'!AH13+0.5*'Scope 3 Yearly'!AH14 -> 471.60706 | AJ24: ='Scope 3 Yearly'!AJ11+'Scope 3 Yearly'!AJ12+'Scope 3 Yearly'!AJ13+0.5*'Scope 3 Yearly'!AJ14+SUM(AJ22:AJ23) -> 249.4142 | AK24: ='Scope 3 Yearly'!AK11+'Scope 3 Yearly'!AK12+'Scope 3 Yearly'!AK13+0.5*'Scope 3 Yearly'!AK14+SUM(AK22:AK23) -> 258.94773 | AL24: ='Scope 3 Yearly'!AL11+'Scope 3 Yearly'!AL12+'Scope 3 Yearly'!AL13+0.5*'Scope 3 Yearly'!AL14+SUM(AL22:AL23) -> 268.24517 | AM24: ='Scope 3 Yearly'!AM11+'Scope 3 Yearly'!AM12+'Scope 3 Yearly'!AM13+0.5*'Scope 3 Yearly'!AM14+SUM(AM22:AM23) -> 277.13607 | AN24: ='Scope 3 Yearly'!AN11+'Scope 3 Yearly'!AN12+'Scope 3 Yearly'!AN13+0.5*'Scope 3 Yearly'!AN14+SUM(AN22:AN23) -> 285.5595 | AO24: ='Scope 3 Yearly'!AO11+'Scope 3 Yearly'!AO12+'Scope 3 Yearly'!AO13+0.5*'Scope 3 Yearly'!AO14+SUM(AO22:AO23) -> 293.45648 | AP24: ='Scope 3 Yearly'!AP11+'Scope 3 Yearly'!AP12+'Scope 3 Yearly'!AP13+0.5*'Scope 3 Yearly'!AP14+SUM(AP22:AP23) -> 301.41963 | AQ24: ='Scope 3 Yearly'!AQ11+'Scope 3 Yearly'!AQ12+'Scope 3 Yearly'!AQ13+0.5*'Scope 3 Yearly'!AQ14+SUM(AQ22:AQ23) -> 309.44294 | ... BN24: ='Scope 3 Yearly'!BN11+'Scope 3 Yearly'!BN12+'Scope 3 Yearly'!BN13+0.5*'Scope 3 Yearly'!BN14+SUM(BN22:BN23) -> 469.9931 | BP24: ='Scope 3 Yearly'!BP11+'Scope 3 Yearly'!BP12+'Scope 3 Yearly'!BP13+0.5*'Scope 3 Yearly'!BP14+SUM(BP22:BP23) -> 249.41418 | BQ24: ='Scope 3 Yearly'!BQ11+'Scope 3 Yearly'!BQ12+'Scope 3 Yearly'!BQ13+0.5*'Scope 3 Yearly'!BQ14+SUM(BQ22:BQ23) -> 256.55897 | BR24: ='Scope 3 Yearly'!BR11+'Scope 3 Yearly'!BR12+'Scope 3 Yearly'!BR13+0.5*'Scope 3 Yearly'!BR14+SUM(BR22:BR23) -> 263.23261 | BS24: ='Scope 3 Yearly'!BS11+'Scope 3 Yearly'!BS12+'Scope 3 Yearly'!BS13+0.5*'Scope 3 Yearly'!BS14+SUM(BS22:BS23) -> 269.38894 | BT24: ='Scope 3 Yearly'!BT11+'Scope 3 Yearly'!BT12+'Scope 3 Yearly'!BT13+0.5*'Scope 3 Yearly'!BT14+SUM(BT22:BT23) -> 274.98489 | BU24: ='Scope 3 Yearly'!BU11+'Scope 3 Yearly'!BU12+'Scope 3 Yearly'!BU13+0.5*'Scope 3 Yearly'!BU14+SUM(BU22:BU23) -> 279.981 | BV24: ='Scope 3 Yearly'!BV11+'Scope 3 Yearly'!BV12+'Scope 3 Yearly'!BV13+0.5*'Scope 3 Yearly'!BV14+SUM(BV22:BV23) -> 284.93541 | BW24: ='Scope 3 Yearly'!BW11+'Scope 3 Yearly'!BW12+'Scope 3 Yearly'!BW13+0.5*'Scope 3 Yearly'!BW14+SUM(BW22:BW23) -> 289.84268 | ... CT24: ='Scope 3 Yearly'!CT11+'Scope 3 Yearly'!CT12+'Scope 3 Yearly'!CT13+0.5*'Scope 3 Yearly'!CT14+SUM(CT22:CT23) -> 347.81697 | CV24: ='Scope 3 Yearly'!CV11+'Scope 3 Yearly'!CV12+'Scope 3 Yearly'!CV13+0.5*'Scope 3 Yearly'!CV14+SUM(CV22:CV23) -> 249.4142 | CW24: ='Scope 3 Yearly'!CW11+'Scope 3 Yearly'!CW12+'Scope 3 Yearly'!CW13+0.5*'Scope 3 Yearly'!CW14+SUM(CW22:CW23) -> 258.94773 | CX24: ='Scope 3 Yearly'!CX11+'Scope 3 Yearly'!CX12+'Scope 3 Yearly'!CX13+0.5*'Scope 3 Yearly'!CX14+SUM(CX22:CX23) -> 268.24517 | CY24: ='Scope 3 Yearly'!CY11+'Scope 3 Yearly'!CY12+'Scope 3 Yearly'!CY13+0.5*'Scope 3 Yearly'!CY14+SUM(CY22:CY23) -> 277.13607 | CZ24: ='Scope 3 Yearly'!CZ11+'Scope 3 Yearly'!CZ12+'Scope 3 Yearly'!CZ13+0.5*'Scope 3 Yearly'!CZ14+SUM(CZ22:CZ23) -> 285.5595 | DA24: ='Scope 3 Yearly'!DA11+'Scope 3 Yearly'!DA12+'Scope 3 Yearly'!DA13+0.5*'Scope 3 Yearly'!DA14+SUM(DA22:DA23) -> 293.45648 | DB24: ='Scope 3 Yearly'!DB11+'Scope 3 Yearly'!DB12+'Scope 3 Yearly'!DB13+0.5*'Scope 3 Yearly'!DB14+SUM(DB22:DB23) -> 301.41963 | DC24: ='Scope 3 Yearly'!DC11+'Scope 3 Yearly'!DC12+'Scope 3 Yearly'!DC13+0.5*'Scope 3 Yearly'!DC14+SUM(DC22:DC23) -> 309.44294 | ... DZ24: ='Scope 3 Yearly'!DZ11+'Scope 3 Yearly'!DZ12+'Scope 3 Yearly'!DZ13+0.5*'Scope 3 Yearly'!DZ14+SUM(DZ22:DZ23) -> 469.04421 | EB24: Closed loop | EE24: ='Yearly BTX'!AH114+'Yearly Butadiene'!AH72+'Yearly Methanol'!AH115+'Yearly HC Ethylene'!AH147+'Yearly HC Propylene'!AH67 -> 107.84339 | EQ24: 0 | ER24: 0.086200532 | ES24: 0.28400607 | ET24: 0.074600265 | EU24: 0.064354291
B25: Incineration | C25: mTons | D25: ='Scope 3 Yearly'!D11 -> 47.054727 | E25: ='Scope 3 Yearly'!E11 -> 50.048825 | F25: ='Scope 3 Yearly'!F11 -> 52.959424 | G25: ='Scope 3 Yearly'!G11 -> 55.834867 | H25: ='Scope 3 Yearly'!H11 -> 58.655071 | I25: ='Scope 3 Yearly'!I11 -> 61.399631 | J25: ='Scope 3 Yearly'!J11 -> 64.186157 | K25: ='Scope 3 Yearly'!K11 -> 67.011158 | ... AH25: ='Scope 3 Yearly'!AH11 -> 88.078228 | AJ25: ='Scope 3 Yearly'!AJ11 -> 47.054737 | AK25: ='Scope 3 Yearly'!AK11 -> 50.048848 | AL25: ='Scope 3 Yearly'!AL11 -> 52.959475 | AM25: ='Scope 3 Yearly'!AM11 -> 55.834977 | AN25: ='Scope 3 Yearly'!AN11 -> 58.655307 | AO25: ='Scope 3 Yearly'!AO11 -> 61.400132 | AP25: ='Scope 3 Yearly'!AP11 -> 64.187213 | AQ25: ='Scope 3 Yearly'!AQ11 -> 67.013358 | ... BN25: ='Scope 3 Yearly'!BN11 -> 90.441521 | BP25: ='Scope 3 Yearly'!BP11 -> 47.05475 | BQ25: ='Scope 3 Yearly'!BQ11 -> 49.342906 | BR25: ='Scope 3 Yearly'!BR11 -> 51.583686 | BS25: ='Scope 3 Yearly'!BS11 -> 53.76187 | BT25: ='Scope 3 Yearly'!BT11 -> 55.862127 | BU25: ='Scope 3 Yearly'!BU11 -> 57.869183 | BV25: ='Scope 3 Yearly'!BV11 -> 59.909386 | BW25: ='Scope 3 Yearly'!BW11 -> 61.981436 | ... CT25: ='Scope 3 Yearly'!CT11 -> 103.68991 | CV25: ='Scope 3 Yearly'!CV11 -> 47.054737 | CW25: ='Scope 3 Yearly'!CW11 -> 50.048848 | CX25: ='Scope 3 Yearly'!CX11 -> 52.959475 | CY25: ='Scope 3 Yearly'!CY11 -> 55.834977 | CZ25: ='Scope 3 Yearly'!CZ11 -> 58.655307 | DA25: ='Scope 3 Yearly'!DA11 -> 61.400132 | DB25: ='Scope 3 Yearly'!DB11 -> 64.187213 | DC25: ='Scope 3 Yearly'!DC11 -> 67.013358 | ... DZ25: ='Scope 3 Yearly'!DZ11 -> 90.075684 | EB25: Open Loop | EE25: ='Yearly BTX'!AH113+'Yearly Butadiene'!AH71+'Yearly Methanol'!AH114+'Yearly HC Ethylene'!AH146+'Yearly HC Propylene'!AH66 -> 86.211232 | EQ25: 0.88620977 | ER25: 0.52265767 | ES25: 0.42791082 | ET25: 0.77100626 | EU25: 0.54405829
B26: Landfill | C26: mTons | D26: ='Scope 3 Yearly'!D12 -> 108.81406 | E26: ='Scope 3 Yearly'!E12 -> 112.50895 | F26: ='Scope 3 Yearly'!F12 -> 115.84874 | G26: ='Scope 3 Yearly'!G12 -> 118.96634 | H26: ='Scope 3 Yearly'!H12 -> 121.83866 | I26: ='Scope 3 Yearly'!I12 -> 124.44389 | J26: ='Scope 3 Yearly'!J12 -> 127.0351 | K26: ='Scope 3 Yearly'!K12 -> 129.60773 | ... AH26: ='Scope 3 Yearly'!AH12 -> 115.60267 | AJ26: ='Scope 3 Yearly'!AJ12 -> 108.81408 | AK26: ='Scope 3 Yearly'!AK12 -> 112.509 | AL26: ='Scope 3 Yearly'!AL12 -> 115.84885 | AM26: ='Scope 3 Yearly'!AM12 -> 118.96657 | AN26: ='Scope 3 Yearly'!AN12 -> 121.83915 | AO26: ='Scope 3 Yearly'!AO12 -> 124.44491 | AP26: ='Scope 3 Yearly'!AP12 -> 127.03719 | AQ26: ='Scope 3 Yearly'!AQ12 -> 129.61199 | ... BN26: ='Scope 3 Yearly'!BN12 -> 118.7045 | BP26: ='Scope 3 Yearly'!BP12 -> 108.81411 | BQ26: ='Scope 3 Yearly'!BQ12 -> 110.42784 | BR26: ='Scope 3 Yearly'!BR12 -> 111.69481 | BS26: ='Scope 3 Yearly'!BS12 -> 112.60233 | BT26: ='Scope 3 Yearly'!BT12 -> 113.14073 | BU26: ='Scope 3 Yearly'!BU12 -> 113.30356 | BV26: ='Scope 3 Yearly'!BV12 -> 113.35523 | BW26: ='Scope 3 Yearly'!BW12 -> 113.29316 | ... CT26: ='Scope 3 Yearly'!CT12 -> 70.527823 | CV26: ='Scope 3 Yearly'!CV12 -> 108.81408 | CW26: ='Scope 3 Yearly'!CW12 -> 112.509 | CX26: ='Scope 3 Yearly'!CX12 -> 115.84885 | CY26: ='Scope 3 Yearly'!CY12 -> 118.96657 | CZ26: ='Scope 3 Yearly'!CZ12 -> 121.83915 | DA26: ='Scope 3 Yearly'!DA12 -> 124.44491 | DB26: ='Scope 3 Yearly'!DB12 -> 127.03719 | DC26: ='Scope 3 Yearly'!DC12 -> 129.61199 | ... DZ26: ='Scope 3 Yearly'!DZ12 -> 118.22433
B27: ='Scope 3 Yearly'!A13 -> Dumpsite | C27: mTons | D27: ='Scope 3 Yearly'!D13 -> 23.527363 | E27: ='Scope 3 Yearly'!E13 -> 23.510839 | F27: ='Scope 3 Yearly'!F13 -> 23.376621 | G27: ='Scope 3 Yearly'!G13 -> 23.15878 | H27: ='Scope 3 Yearly'!H13 -> 22.858226 | I27: ='Scope 3 Yearly'!I13 -> 22.476651 | J27: ='Scope 3 Yearly'!J13 -> 22.063991 | K27: ='Scope 3 Yearly'!K13 -> 21.620154 | ... AH27: ='Scope 3 Yearly'!AH13 -> 2.7524446 | AJ27: ='Scope 3 Yearly'!AJ13 -> 23.527368 | AK27: ='Scope 3 Yearly'!AK13 -> 23.51085 | AL27: ='Scope 3 Yearly'!AL13 -> 23.376643 | AM27: ='Scope 3 Yearly'!AM13 -> 23.158826 | AN27: ='Scope 3 Yearly'!AN13 -> 22.858318 | AO27: ='Scope 3 Yearly'!AO13 -> 22.476834 | AP27: ='Scope 3 Yearly'!AP13 -> 22.064355 | AQ27: ='Scope 3 Yearly'!AQ13 -> 21.620864 | ... BN27: ='Scope 3 Yearly'!BN13 -> 2.8262975 | BP27: ='Scope 3 Yearly'!BP13 -> 23.527375 | BQ27: ='Scope 3 Yearly'!BQ13 -> 24.38729 | BR27: ='Scope 3 Yearly'!BR13 -> 25.205189 | BS27: ='Scope 3 Yearly'!BS13 -> 25.975199 | BT27: ='Scope 3 Yearly'!BT13 -> 26.69165 | BU27: ='Scope 3 Yearly'!BU13 -> 27.349134 | BV27: ='Scope 3 Yearly'!BV13 -> 28.00868 | BW27: ='Scope 3 Yearly'!BW13 -> 28.669671 | ... CT27: ='Scope 3 Yearly'!CT13 -> 38.766949 | CV27: ='Scope 3 Yearly'!CV13 -> 23.527368 | CW27: ='Scope 3 Yearly'!CW13 -> 23.51085 | CX27: ='Scope 3 Yearly'!CX13 -> 23.376643 | CY27: ='Scope 3 Yearly'!CY13 -> 23.158826 | CZ27: ='Scope 3 Yearly'!CZ13 -> 22.858318 | DA27: ='Scope 3 Yearly'!DA13 -> 22.476834 | DB27: ='Scope 3 Yearly'!DB13 -> 22.064355 | DC27: ='Scope 3 Yearly'!DC13 -> 21.620864 | ... DZ27: ='Scope 3 Yearly'!DZ13 -> 2.8148651
B28: ='Scope 3 Yearly'!A14 -> Open Burning | C28: mTons | D28: ='Scope 3 Yearly'!D14 -> 79.404851 | E28: ='Scope 3 Yearly'!E14 -> 80.623006 | F28: ='Scope 3 Yearly'!F14 -> 81.507864 | G28: ='Scope 3 Yearly'!G14 -> 82.166083 | H28: ='Scope 3 Yearly'!H14 -> 82.591515 | I28: ='Scope 3 Yearly'!I14 -> 82.77986 | J28: ='Scope 3 Yearly'!J14 -> 82.907119 | K28: ='Scope 3 Yearly'!K14 -> 82.971586 | ... AH28: ='Scope 3 Yearly'!AH14 -> 44.039114 | AJ28: ='Scope 3 Yearly'!AJ14 -> 79.404869 | AK28: ='Scope 3 Yearly'!AK14 -> 80.623044 | AL28: ='Scope 3 Yearly'!AL14 -> 81.507942 | AM28: ='Scope 3 Yearly'!AM14 -> 82.166244 | AN28: ='Scope 3 Yearly'!AN14 -> 82.591847 | AO28: ='Scope 3 Yearly'!AO14 -> 82.780536 | AP28: ='Scope 3 Yearly'!AP14 -> 82.908484 | AQ28: ='Scope 3 Yearly'!AQ14 -> 82.97431 | ... BN28: ='Scope 3 Yearly'!BN14 -> 45.220761 | BP28: ='Scope 3 Yearly'!BP14 -> 79.40489 | BQ28: ='Scope 3 Yearly'!BQ14 -> 83.158324 | BR28: ='Scope 3 Yearly'!BR14 -> 86.824856 | BS28: ='Scope 3 Yearly'!BS14 -> 90.379461 | BT28: ='Scope 3 Yearly'!BT14 -> 93.797026 | BU28: ='Scope 3 Yearly'!BU14 -> 97.052622 | BV28: ='Scope 3 Yearly'!BV14 -> 100.35865 | BW28: ='Scope 3 Yearly'!BW14 -> 103.71292 | ... CT28: ='Scope 3 Yearly'!CT14 -> 170.01409 | CV28: ='Scope 3 Yearly'!CV14 -> 79.404869 | CW28: ='Scope 3 Yearly'!CW14 -> 80.623044 | CX28: ='Scope 3 Yearly'!CX14 -> 81.507942 | CY28: ='Scope 3 Yearly'!CY14 -> 82.166244 | CZ28: ='Scope 3 Yearly'!CZ14 -> 82.591847 | DA28: ='Scope 3 Yearly'!DA14 -> 82.780536 | DB28: ='Scope 3 Yearly'!DB14 -> 82.908484 | DC28: ='Scope 3 Yearly'!DC14 -> 82.97431 | ... DZ28: ='Scope 3 Yearly'!DZ14 -> 45.037842
B29: ='Scope 3 Yearly'!A15 -> Leakage Environment | C29: mTons | D29: ='Scope 3 Yearly'!D15 -> 20.586443 | E29: ='Scope 3 Yearly'!E15 -> 21.089122 | F29: ='Scope 3 Yearly'!F15 -> 21.514766 | G29: ='Scope 3 Yearly'!G15 -> 21.889806 | H29: ='Scope 3 Yearly'!H15 -> 22.211295 | I29: ='Scope 3 Yearly'!I15 -> 22.476651 | J29: ='Scope 3 Yearly'!J15 -> 22.732597 | K29: ='Scope 3 Yearly'!K15 -> 22.978488 | ... AH29: ='Scope 3 Yearly'!AH15 -> 16.514668 | AJ29: ='Scope 3 Yearly'!AJ15 -> 20.586447 | AK29: ='Scope 3 Yearly'!AK15 -> 21.089132 | AL29: ='Scope 3 Yearly'!AL15 -> 21.514787 | AM29: ='Scope 3 Yearly'!AM15 -> 21.889849 | AN29: ='Scope 3 Yearly'!AN15 -> 22.211384 | AO29: ='Scope 3 Yearly'!AO15 -> 22.476834 | AP29: ='Scope 3 Yearly'!AP15 -> 22.732971 | AQ29: ='Scope 3 Yearly'!AQ15 -> 22.979243 | ... BN29: ='Scope 3 Yearly'!BN15 -> 16.957785 | BP29: ='Scope 3 Yearly'!BP15 -> 20.586453 | BQ29: ='Scope 3 Yearly'!BQ15 -> 21.697888 | BR29: ='Scope 3 Yearly'!BR15 -> 22.795715 | BS29: ='Scope 3 Yearly'!BS15 -> 23.872599 | BT29: ='Scope 3 Yearly'!BT15 -> 24.92106 | BU29: ='Scope 3 Yearly'!BU15 -> 25.933548 | BV29: ='Scope 3 Yearly'!BV15 -> 26.966174 | BW29: ='Scope 3 Yearly'!BW15 -> 28.018357 | ... CT29: ='Scope 3 Yearly'!CT15 -> 50.443741 | CV29: ='Scope 3 Yearly'!CV15 -> 20.586447 | CW29: ='Scope 3 Yearly'!CW15 -> 21.089132 | CX29: ='Scope 3 Yearly'!CX15 -> 21.514787 | CY29: ='Scope 3 Yearly'!CY15 -> 21.889849 | CZ29: ='Scope 3 Yearly'!CZ15 -> 22.211384 | DA29: ='Scope 3 Yearly'!DA15 -> 22.476834 | DB29: ='Scope 3 Yearly'!DB15 -> 22.732971 | DC29: ='Scope 3 Yearly'!DC15 -> 22.979243 | ... DZ29: ='Scope 3 Yearly'!DZ15 -> 16.889191
B30: ='Scope 3 Yearly'!A16 -> Leakage Ocean | C30: mTons | D30: ='Scope 3 Yearly'!D16 -> 14.704602 | E30: ='Scope 3 Yearly'!E16 -> 14.933924 | F30: ='Scope 3 Yearly'!F16 -> 15.101711 | G30: ='Scope 3 Yearly'!G16 -> 15.227691 | H30: ='Scope 3 Yearly'!H16 -> 15.310699 | I30: ='Scope 3 Yearly'!I16 -> 15.349908 | J30: ='Scope 3 Yearly'!J16 -> 15.377933 | K30: ='Scope 3 Yearly'!K16 -> 15.394455 | ... AH30: ='Scope 3 Yearly'!AH16 -> 8.2573339 | AJ30: ='Scope 3 Yearly'!AJ16 -> 14.704605 | AK30: ='Scope 3 Yearly'!AK16 -> 14.93393 | AL30: ='Scope 3 Yearly'!AL16 -> 15.101725 | AM30: ='Scope 3 Yearly'!AM16 -> 15.227721 | AN30: ='Scope 3 Yearly'!AN16 -> 15.31076 | AO30: ='Scope 3 Yearly'!AO16 -> 15.350033 | AP30: ='Scope 3 Yearly'!AP16 -> 15.378187 | AQ30: ='Scope 3 Yearly'!AQ16 -> 15.394961 | ... BN30: ='Scope 3 Yearly'!BN16 -> 8.4788926 | BP30: ='Scope 3 Yearly'!BP16 -> 14.704609 | BQ30: ='Scope 3 Yearly'!BQ16 -> 15.446298 | BR30: ='Scope 3 Yearly'!BR16 -> 16.174901 | BS30: ='Scope 3 Yearly'!BS16 -> 16.885497 | BT30: ='Scope 3 Yearly'!BT16 -> 17.57311 | BU30: ='Scope 3 Yearly'!BU16 -> 18.232756 | BV30: ='Scope 3 Yearly'!BV16 -> 18.904122 | BW30: ='Scope 3 Yearly'!BW16 -> 19.586797 | ... CT30: ='Scope 3 Yearly'!CT16 -> 33.62916 | CV30: ='Scope 3 Yearly'!CV16 -> 14.704605 | CW30: ='Scope 3 Yearly'!CW16 -> 14.93393 | CX30: ='Scope 3 Yearly'!CX16 -> 15.101725 | CY30: ='Scope 3 Yearly'!CY16 -> 15.227721 | CZ30: ='Scope 3 Yearly'!CZ16 -> 15.31076 | DA30: ='Scope 3 Yearly'!DA16 -> 15.350033 | DB30: ='Scope 3 Yearly'!DB16 -> 15.378187 | DC30: ='Scope 3 Yearly'!DC16 -> 15.394961 | ... DZ30: ='Scope 3 Yearly'!DZ16 -> 8.4445954
A31: Production Circular | C31: ='Yearly HC Ethylene'!C152 -> m Tons | D31: =D4-SUM(D5:D20)-D22+$D$22-D23 -> 661.63206 | E31: =E4-SUM(E5:E20)-E22+$D$22-E23 -> 676.78118 | F31: =F4-SUM(F5:F20)-F22+$D$22-F23 -> 691.00563 | G31: =G4-SUM(G5:G20)-G22+$D$22-G23 -> 705.40549 | H31: =H4-SUM(H5:H20)-H22+$D$22-H23 -> 720.00261 | I31: =I4-SUM(I5:I20)-I22+$D$22-I23 -> 734.8222 | J31: =J4-SUM(J5:J20)-J22+$D$22-J23 -> 747.92369 | K31: =K4-SUM(K5:K20)-K22+$D$22-K23 -> 761.08593 | ... AH31: =AH4-SUM(AH5:AH20)-AH22+$D$22-AH23 -> 1020.7516 | AJ31: =AJ4-SUM(AJ5:AJ20)-AJ22+$D$22-AJ23 -> 661.63213 | AK31: =AK4-SUM(AK5:AK20)-AK22+$D$22-AK23 -> 677.57363 | AL31: =AL4-SUM(AL5:AL20)-AL22+$D$22-AL23 -> 692.6097 | AM31: =AM4-SUM(AM5:AM20)-AM22+$D$22-AM23 -> 707.8388 | AN31: =AN4-SUM(AN5:AN20)-AN22+$D$22-AN23 -> 723.28317 | AO31: =AO4-SUM(AO5:AO20)-AO22+$D$22-AO23 -> 738.96714 | AP31: =AP4-SUM(AP5:AP20)-AP22+$D$22-AP23 -> 752.93339 | AQ31: =AQ4-SUM(AQ5:AQ20)-AQ22+$D$22-AQ23 -> 766.97178 | ... BN31: =BN4-SUM(BN5:BN20)-BN22+$D$22-BN23 -> 1028.4953 | BP31: =BP4-SUM(BP5:BP20)-BP22+$D$22-BP23 -> 661.63221 | BQ31: =BQ4-SUM(BQ5:BQ20)-BQ22+$D$22-BQ23 -> 680.55681 | BR31: =BR4-SUM(BR5:BR20)-BR22+$D$22-BR23 -> 699.09641 | BS31: =BS4-SUM(BS5:BS20)-BS22+$D$22-BS23 -> 717.91005 | BT31: =BT4-SUM(BT5:BT20)-BT22+$D$22-BT23 -> 737.0052 | BU31: =BU4-SUM(BU5:BU20)-BU22+$D$22-BU23 -> 756.38969 | BV31: =BV4-SUM(BV5:BV20)-BV22+$D$22-BV23 -> 774.17934 | BW31: =BW4-SUM(BW5:BW20)-BW22+$D$22-BW23 -> 792.17302 | ... CT31: =CT4-SUM(CT5:CT20)-CT22+$D$22-CT23 -> 1280.1521 | CV31: =CV4-SUM(CV5:CV20)-CV22+$D$22-CV23 -> 661.63213 | CW31: =CW4-SUM(CW5:CW20)-CW22+$D$22-CW23 -> 678.81107 | CX31: =CX4-SUM(CX5:CX20)-CX22+$D$22-CX23 -> 695.12667 | CY31: =CY4-SUM(CY5:CY20)-CY22+$D$22-CY23 -> 711.67728 | CZ31: =CZ4-SUM(CZ5:CZ20)-CZ22+$D$22-CZ23 -> 728.48627 | DA31: =DA4-SUM(DA5:DA20)-DA22+$D$22-DA23 -> 745.57817 | DB31: =DB4-SUM(DB5:DB20)-DB22+$D$22-DB23 -> 760.98551 | DC31: =DC4-SUM(DC5:DC20)-DC22+$D$22-DC23 -> 776.5054 | ... DZ31: =DZ4-SUM(DZ5:DZ20)-DZ22+$D$22-DZ23 -> 1094.5669
A32: Check | C32: ='Yearly HC Ethylene'!C153 -> m Tons | D32: ='Yearly Summary'!D10 -> 661.63206 | E32: ='Yearly Summary'!E10 -> 677.55451 | F32: ='Yearly Summary'!F10 -> 692.80339 | G32: ='Yearly Summary'!G10 -> 708.25901 | H32: ='Yearly Summary'!H10 -> 723.94355 | I32: ='Yearly Summary'!I10 -> 739.89326 | J32: ='Yearly Summary'!J10 -> 751.88015 | K32: ='Yearly Summary'!K10 -> 763.95053 | ... AH32: ='Yearly Summary'!AH10 -> 917.26255 | AJ32: ='Yearly Summary'!AJ10 -> 661.63213 | AK32: ='Yearly Summary'!AK10 -> 677.52674 | AL32: ='Yearly Summary'!AL10 -> 692.74703 | AM32: ='Yearly Summary'!AM10 -> 708.17339 | AN32: ='Yearly Summary'!AN10 -> 723.82815 | AO32: ='Yearly Summary'!AO10 -> 739.74791 | AP32: ='Yearly Summary'!AP10 -> 751.70537 | AQ32: ='Yearly Summary'!AQ10 -> 763.7482 | ... BN32: ='Yearly Summary'!BN10 -> 925.03192
AI33: =SUM(AH27:AH30) -> 71.563561 | AJ33: =(CU33-AI33)/CU33 -> 0.75563395 | BN33: =BN32+675+150 -> 1750.0319 | BO33: =SUM(BN27:BN30) -> 73.483736 | BP33: =(CU33-BO33)/CU33 -> 0.74907718 | CU33: =SUM(CT27:CT30) -> 292.85394 | EF33: ASSUMPTIONS
A34: Job creation | EF34: Job factor | EG34: job/1000 tons of plastic/year | EM34: Source
B35: =B7 -> Fuel additive elimination | C35: job | D35: =D7*$EF35*1000 -> 0 | E35: =E7*$EF35*1000 -> 0 | F35: =F7*$EF35*1000 -> 0 | G35: =G7*$EF35*1000 -> 0 | H35: =H7*$EF35*1000 -> 0 | I35: =I7*$EF35*1000 -> 0 | J35: =J7*$EF35*1000 -> 0 | K35: =K7*$EF35*1000 -> 0 | ... AH35: =AH7*$EF35*1000 -> 0 | AJ35: =AJ7*$EF35*1000 -> 0 | AK35: =AK7*$EF35*1000 -> 0 | AL35: =AL7*$EF35*1000 -> 0 | AM35: =AM7*$EF35*1000 -> 0 | AN35: =AN7*$EF35*1000 -> 0 | AO35: =AO7*$EF35*1000 -> 0 | AP35: =AP7*$EF35*1000 -> 0 | AQ35: =AQ7*$EF35*1000 -> 0 | ... BN35: =BN7*$EF35*1000 -> 0 | BP35: =BP7*$EF35*1000 -> 0 | BQ35: =BQ7*$EF35*1000 -> 0 | BR35: =BR7*$EF35*1000 -> 0 | BS35: =BS7*$EF35*1000 -> 0 | BT35: =BT7*$EF35*1000 -> 0 | BU35: =BU7*$EF35*1000 -> 0 | BV35: =BV7*$EF35*1000 -> 0 | BW35: =BW7*$EF35*1000 -> 0 | ... CT35: =CT7*$EF35*1000 -> 0 | CV35: =CV7*$EF35*1000 -> 0 | CW35: =CW7*$EF35*1000 -> 0 | CX35: =CX7*$EF35*1000 -> 0 | CY35: =CY7*$EF35*1000 -> 0 | CZ35: =CZ7*$EF35*1000 -> 0 | DA35: =DA7*$EF35*1000 -> 0 | DB35: =DB7*$EF35*1000 -> 0 | DC35: =DC7*$EF35*1000 -> 0 | ... DZ35: =DZ7*$EF35*1000 -> 0 | EF35: 0 | EM35: None
B36: =B8 -> Packaging reduction | C36: job | D36: =D8*$EF36*1000 -> 0 | E36: =E8*$EF36*1000 -> 0 | F36: =F8*$EF36*1000 -> 0 | G36: =G8*$EF36*1000 -> 0 | H36: =H8*$EF36*1000 -> 0 | I36: =I8*$EF36*1000 -> 0 | J36: =J8*$EF36*1000 -> 0 | K36: =K8*$EF36*1000 -> 0 | ... AH36: =AH8*$EF36*1000 -> 0 | AJ36: =AJ8*$EF36*1000 -> 0 | AK36: =AK8*$EF36*1000 -> 0 | AL36: =AL8*$EF36*1000 -> 0 | AM36: =AM8*$EF36*1000 -> 0 | AN36: =AN8*$EF36*1000 -> 0 | AO36: =AO8*$EF36*1000 -> 0 | AP36: =AP8*$EF36*1000 -> 0 | AQ36: =AQ8*$EF36*1000 -> 0 | ... BN36: =BN8*$EF36*1000 -> 0 | BP36: =BP8*$EF36*1000 -> 0 | BQ36: =BQ8*$EF36*1000 -> 0 | BR36: =BR8*$EF36*1000 -> 0 | BS36: =BS8*$EF36*1000 -> 0 | BT36: =BT8*$EF36*1000 -> 0 | BU36: =BU8*$EF36*1000 -> 0 | BV36: =BV8*$EF36*1000 -> 0 | BW36: =BW8*$EF36*1000 -> 0 | ... CT36: =CT8*$EF36*1000 -> 0 | CV36: =CV8*$EF36*1000 -> 0 | CW36: =CW8*$EF36*1000 -> 0 | CX36: =CX8*$EF36*1000 -> 0 | CY36: =CY8*$EF36*1000 -> 0 | CZ36: =CZ8*$EF36*1000 -> 0 | DA36: =DA8*$EF36*1000 -> 0 | DB36: =DB8*$EF36*1000 -> 0 | DC36: =DC8*$EF36*1000 -> 0 | ... DZ36: =DZ8*$EF36*1000 -> 0 | EF36: 0 | EM36: BPW
B37: =B9 -> Packaging reuse | C37: job | D37: =D9*$EF37*1000 -> 0 | E37: =E9*$EF37*1000 -> 0 | F37: =F9*$EF37*1000 -> 0 | G37: =G9*$EF37*1000 -> 0 | H37: =H9*$EF37*1000 -> 0 | I37: =I9*$EF37*1000 -> 0 | J37: =J9*$EF37*1000 -> 0 | K37: =K9*$EF37*1000 -> 0 | ... AH37: =AH9*$EF37*1000 -> 0 | AJ37: =AJ9*$EF37*1000 -> 0 | AK37: =AK9*$EF37*1000 -> 0 | AL37: =AL9*$EF37*1000 -> 0 | AM37: =AM9*$EF37*1000 -> 0 | AN37: =AN9*$EF37*1000 -> 0 | AO37: =AO9*$EF37*1000 -> 0 | AP37: =AP9*$EF37*1000 -> 0 | AQ37: =AQ9*$EF37*1000 -> 0 | ... BN37: =BN9*$EF37*1000 -> 0 | BP37: =BP9*$EF37*1000 -> 0 | BQ37: =BQ9*$EF37*1000 -> 0 | BR37: =BR9*$EF37*1000 -> 0 | BS37: =BS9*$EF37*1000 -> 0 | BT37: =BT9*$EF37*1000 -> 0 | BU37: =BU9*$EF37*1000 -> 0 | BV37: =BV9*$EF37*1000 -> 0 | BW37: =BW9*$EF37*1000 -> 0 | ... CT37: =CT9*$EF37*1000 -> 0 | CV37: =CV9*$EF37*1000 -> 0 | CW37: =CW9*$EF37*1000 -> 0 | CX37: =CX9*$EF37*1000 -> 0 | CY37: =CY9*$EF37*1000 -> 0 | CZ37: =CZ9*$EF37*1000 -> 0 | DA37: =DA9*$EF37*1000 -> 0 | DB37: =DB9*$EF37*1000 -> 0 | DC37: =DC9*$EF37*1000 -> 0 | ... DZ37: =DZ9*$EF37*1000 -> 0 | EF37: 9.5 | EM37: BPW
B38: =B10 -> Packaging substitution Paper | C38: job | D38: =D10*$EF38*1000 -> 0 | E38: =E10*$EF38*1000 -> 0 | F38: =F10*$EF38*1000 -> 0 | G38: =G10*$EF38*1000 -> 0 | H38: =H10*$EF38*1000 -> 0 | I38: =I10*$EF38*1000 -> 0 | J38: =J10*$EF38*1000 -> 0 | K38: =K10*$EF38*1000 -> 0 | ... AH38: =AH10*$EF38*1000 -> 0 | AJ38: =AJ10*$EF38*1000 -> 0 | AK38: =AK10*$EF38*1000 -> 0 | AL38: =AL10*$EF38*1000 -> 0 | AM38: =AM10*$EF38*1000 -> 0 | AN38: =AN10*$EF38*1000 -> 0 | AO38: =AO10*$EF38*1000 -> 0 | AP38: =AP10*$EF38*1000 -> 0 | AQ38: =AQ10*$EF38*1000 -> 0 | ... BN38: =BN10*$EF38*1000 -> 0 | BP38: =BP10*$EF38*1000 -> 0 | BQ38: =BQ10*$EF38*1000 -> 0 | BR38: =BR10*$EF38*1000 -> 0 | BS38: =BS10*$EF38*1000 -> 0 | BT38: =BT10*$EF38*1000 -> 0 | BU38: =BU10*$EF38*1000 -> 0 | BV38: =BV10*$EF38*1000 -> 0 | BW38: =BW10*$EF38*1000 -> 0 | ... CT38: =CT10*$EF38*1000 -> 0 | CV38: =CV10*$EF38*1000 -> 0 | CW38: =CW10*$EF38*1000 -> 0 | CX38: =CX10*$EF38*1000 -> 0 | CY38: =CY10*$EF38*1000 -> 0 | CZ38: =CZ10*$EF38*1000 -> 0 | DA38: =DA10*$EF38*1000 -> 0 | DB38: =DB10*$EF38*1000 -> 0 | DC38: =DC10*$EF38*1000 -> 0 | ... DZ38: =DZ10*$EF38*1000 -> 0 | EF38: 18.5 | EM38: BPW | EQ38: Job/1000 ton
B39: =B11 -> Packaging Substitution Compostables | C39: job | D39: =D11*$EF39*1000 -> 0 | E39: =E11*$EF39*1000 -> 0 | F39: =F11*$EF39*1000 -> 0 | G39: =G11*$EF39*1000 -> 0 | H39: =H11*$EF39*1000 -> 0 | I39: =I11*$EF39*1000 -> 0 | J39: =J11*$EF39*1000 -> 0 | K39: =K11*$EF39*1000 -> 0 | ... AH39: =AH11*$EF39*1000 -> 0 | AJ39: =AJ11*$EF39*1000 -> 0 | AK39: =AK11*$EF39*1000 -> 0 | AL39: =AL11*$EF39*1000 -> 0 | AM39: =AM11*$EF39*1000 -> 0 | AN39: =AN11*$EF39*1000 -> 0 | AO39: =AO11*$EF39*1000 -> 0 | AP39: =AP11*$EF39*1000 -> 0 | AQ39: =AQ11*$EF39*1000 -> 0 | ... BN39: =BN11*$EF39*1000 -> 0 | BP39: =BP11*$EF39*1000 -> 0 | BQ39: =BQ11*$EF39*1000 -> 0 | BR39: =BR11*$EF39*1000 -> 0 | BS39: =BS11*$EF39*1000 -> 0 | BT39: =BT11*$EF39*1000 -> 0 | BU39: =BU11*$EF39*1000 -> 0 | BV39: =BV11*$EF39*1000 -> 0 | BW39: =BW11*$EF39*1000 -> 0 | ... CT39: =CT11*$EF39*1000 -> 0 | CV39: =CV11*$EF39*1000 -> 0 | CW39: =CW11*$EF39*1000 -> 0 | CX39: =CX11*$EF39*1000 -> 0 | CY39: =CY11*$EF39*1000 -> 0 | CZ39: =CZ11*$EF39*1000 -> 0 | DA39: =DA11*$EF39*1000 -> 0 | DB39: =DB11*$EF39*1000 -> 0 | DC39: =DC11*$EF39*1000 -> 0 | ... DZ39: =DZ11*$EF39*1000 -> 0 | EF39: 18.9 | EM39: BPW | EP39: Chemical production (include upstream | EQ39: 8
B40: =B12 -> MaaS | C40: job | D40: =D12*$EF40*1000 -> 0 | E40: =E12*$EF40*1000 -> 0 | F40: =F12*$EF40*1000 -> 0 | G40: =G12*$EF40*1000 -> 0 | H40: =H12*$EF40*1000 -> 0 | I40: =I12*$EF40*1000 -> 0 | J40: =J12*$EF40*1000 -> 0 | K40: =K12*$EF40*1000 -> 0 | ... AH40: =AH12*$EF40*1000 -> 0 | AJ40: =AJ12*$EF40*1000 -> 0 | AK40: =AK12*$EF40*1000 -> 0 | AL40: =AL12*$EF40*1000 -> 0 | AM40: =AM12*$EF40*1000 -> 0 | AN40: =AN12*$EF40*1000 -> 0 | AO40: =AO12*$EF40*1000 -> 0 | AP40: =AP12*$EF40*1000 -> 0 | AQ40: =AQ12*$EF40*1000 -> 0 | ... BN40: =BN12*$EF40*1000 -> 0 | BP40: =BP12*$EF40*1000 -> 0 | BQ40: =BQ12*$EF40*1000 -> 0 | BR40: =BR12*$EF40*1000 -> 0 | BS40: =BS12*$EF40*1000 -> 0 | BT40: =BT12*$EF40*1000 -> 0 | BU40: =BU12*$EF40*1000 -> 0 | BV40: =BV12*$EF40*1000 -> 0 | BW40: =BW12*$EF40*1000 -> 0 | ... CT40: =CT12*$EF40*1000 -> 0 | CV40: =CV12*$EF40*1000 -> 0 | CW40: =CW12*$EF40*1000 -> 0 | CX40: =CX12*$EF40*1000 -> 0 | CY40: =CY12*$EF40*1000 -> 0 | CZ40: =CZ12*$EF40*1000 -> 0 | DA40: =DA12*$EF40*1000 -> 0 | DB40: =DB12*$EF40*1000 -> 0 | DC40: =DC12*$EF40*1000 -> 0 | ... DZ40: =DZ12*$EF40*1000 -> 0 | EF40: 10
B41: =B13 -> Vehicle life extension | C41: job | D41: =D13*$EF41*1000 -> 0 | E41: =E13*$EF41*1000 -> 0 | F41: =F13*$EF41*1000 -> 0 | G41: =G13*$EF41*1000 -> 0 | H41: =H13*$EF41*1000 -> 0 | I41: =I13*$EF41*1000 -> 0 | J41: =J13*$EF41*1000 -> 0 | K41: =K13*$EF41*1000 -> 0 | ... AH41: =AH13*$EF41*1000 -> 0 | AJ41: =AJ13*$EF41*1000 -> 0 | AK41: =AK13*$EF41*1000 -> 0 | AL41: =AL13*$EF41*1000 -> 0 | AM41: =AM13*$EF41*1000 -> 0 | AN41: =AN13*$EF41*1000 -> 0 | AO41: =AO13*$EF41*1000 -> 0 | AP41: =AP13*$EF41*1000 -> 0 | AQ41: =AQ13*$EF41*1000 -> 0 | ... BN41: =BN13*$EF41*1000 -> 0 | BP41: =BP13*$EF41*1000 -> 0 | BQ41: =BQ13*$EF41*1000 -> 0 | BR41: =BR13*$EF41*1000 -> 0 | BS41: =BS13*$EF41*1000 -> 0 | BT41: =BT13*$EF41*1000 -> 0 | BU41: =BU13*$EF41*1000 -> 0 | BV41: =BV13*$EF41*1000 -> 0 | BW41: =BW13*$EF41*1000 -> 0 | ... CT41: =CT13*$EF41*1000 -> 0 | CV41: =CV13*$EF41*1000 -> 0 | CW41: =CW13*$EF41*1000 -> 0 | CX41: =CX13*$EF41*1000 -> 0 | CY41: =CY13*$EF41*1000 -> 0 | CZ41: =CZ13*$EF41*1000 -> 0 | DA41: =DA13*$EF41*1000 -> 0 | DB41: =DB13*$EF41*1000 -> 0 | DC41: =DC13*$EF41*1000 -> 0 | ... DZ41: =DZ13*$EF41*1000 -> 0 | EF41: 10 | EQ41: Job/EJ
B42: =B14 -> Building reduction | C42: job | D42: =D14*$EF42*1000 -> 0 | E42: =E14*$EF42*1000 -> 0 | F42: =F14*$EF42*1000 -> 0 | G42: =G14*$EF42*1000 -> 0 | H42: =H14*$EF42*1000 -> 0 | I42: =I14*$EF42*1000 -> 0 | J42: =J14*$EF42*1000 -> 0 | K42: =K14*$EF42*1000 -> 0 | ... AH42: =AH14*$EF42*1000 -> 0 | AJ42: =AJ14*$EF42*1000 -> 0 | AK42: =AK14*$EF42*1000 -> 0 | AL42: =AL14*$EF42*1000 -> 0 | AM42: =AM14*$EF42*1000 -> 0 | AN42: =AN14*$EF42*1000 -> 0 | AO42: =AO14*$EF42*1000 -> 0 | AP42: =AP14*$EF42*1000 -> 0 | AQ42: =AQ14*$EF42*1000 -> 0 | ... BN42: =BN14*$EF42*1000 -> 0 | BP42: =BP14*$EF42*1000 -> 0 | BQ42: =BQ14*$EF42*1000 -> 0 | BR42: =BR14*$EF42*1000 -> 0 | BS42: =BS14*$EF42*1000 -> 0 | BT42: =BT14*$EF42*1000 -> 0 | BU42: =BU14*$EF42*1000 -> 0 | BV42: =BV14*$EF42*1000 -> 0 | BW42: =BW14*$EF42*1000 -> 0 | ... CT42: =CT14*$EF42*1000 -> 0 | CV42: =CV14*$EF42*1000 -> 0 | CW42: =CW14*$EF42*1000 -> 0 | CX42: =CX14*$EF42*1000 -> 0 | CY42: =CY14*$EF42*1000 -> 0 | CZ42: =CZ14*$EF42*1000 -> 0 | DA42: =DA14*$EF42*1000 -> 0 | DB42: =DB14*$EF42*1000 -> 0 | DC42: =DC14*$EF42*1000 -> 0 | ... DZ42: =DZ14*$EF42*1000 -> 0 | EF42: 0 | EM42: BPW | EP42: Biomass
B43: =B15 -> Building substitution | C43: job | D43: =D15*$EF43*1000 -> 0 | E43: =E15*$EF43*1000 -> 0 | F43: =F15*$EF43*1000 -> 0 | G43: =G15*$EF43*1000 -> 0 | H43: =H15*$EF43*1000 -> 0 | I43: =I15*$EF43*1000 -> 0 | J43: =J15*$EF43*1000 -> 0 | K43: =K15*$EF43*1000 -> 0 | ... AH43: =AH15*$EF43*1000 -> 0 | AJ43: =AJ15*$EF43*1000 -> 0 | AK43: =AK15*$EF43*1000 -> 0 | AL43: =AL15*$EF43*1000 -> 0 | AM43: =AM15*$EF43*1000 -> 0 | AN43: =AN15*$EF43*1000 -> 0 | AO43: =AO15*$EF43*1000 -> 0 | AP43: =AP15*$EF43*1000 -> 0 | AQ43: =AQ15*$EF43*1000 -> 0 | ... BN43: =BN15*$EF43*1000 -> 0 | BP43: =BP15*$EF43*1000 -> 0 | BQ43: =BQ15*$EF43*1000 -> 0 | BR43: =BR15*$EF43*1000 -> 0 | BS43: =BS15*$EF43*1000 -> 0 | BT43: =BT15*$EF43*1000 -> 0 | BU43: =BU15*$EF43*1000 -> 0 | BV43: =BV15*$EF43*1000 -> 0 | BW43: =BW15*$EF43*1000 -> 0 | ... CT43: =CT15*$EF43*1000 -> 0 | CV43: =CV15*$EF43*1000 -> 0 | CW43: =CW15*$EF43*1000 -> 0 | CX43: =CX15*$EF43*1000 -> 0 | CY43: =CY15*$EF43*1000 -> 0 | CZ43: =CZ15*$EF43*1000 -> 0 | DA43: =DA15*$EF43*1000 -> 0 | DB43: =DB15*$EF43*1000 -> 0 | DC43: =DC15*$EF43*1000 -> 0 | ... DZ43: =DZ15*$EF43*1000 -> 0 | EF43: 18.5 | EM43: BPW | EP43: H2
B44: =B16 -> Apparel - waste reduction | C44: job | D44: =D16*$EF44*1000 -> 0 | E44: =E16*$EF44*1000 -> 0 | F44: =F16*$EF44*1000 -> 0 | G44: =G16*$EF44*1000 -> 0 | H44: =H16*$EF44*1000 -> 0 | I44: =I16*$EF44*1000 -> 0 | J44: =J16*$EF44*1000 -> 0 | K44: =K16*$EF44*1000 -> 0 | ... AH44: =AH16*$EF44*1000 -> 0 | AJ44: =AJ16*$EF44*1000 -> 0 | AK44: =AK16*$EF44*1000 -> 0 | AL44: =AL16*$EF44*1000 -> 0 | AM44: =AM16*$EF44*1000 -> 0 | AN44: =AN16*$EF44*1000 -> 0 | AO44: =AO16*$EF44*1000 -> 0 | AP44: =AP16*$EF44*1000 -> 0 | AQ44: =AQ16*$EF44*1000 -> 0 | ... BN44: =BN16*$EF44*1000 -> 0 | BP44: =BP16*$EF44*1000 -> 0 | BQ44: =BQ16*$EF44*1000 -> 0 | BR44: =BR16*$EF44*1000 -> 0 | BS44: =BS16*$EF44*1000 -> 0 | BT44: =BT16*$EF44*1000 -> 0 | BU44: =BU16*$EF44*1000 -> 0 | BV44: =BV16*$EF44*1000 -> 0 | BW44: =BW16*$EF44*1000 -> 0 | ... CT44: =CT16*$EF44*1000 -> 0 | CV44: =CV16*$EF44*1000 -> 0 | CW44: =CW16*$EF44*1000 -> 0 | CX44: =CX16*$EF44*1000 -> 0 | CY44: =CY16*$EF44*1000 -> 0 | CZ44: =CZ16*$EF44*1000 -> 0 | DA44: =DA16*$EF44*1000 -> 0 | DB44: =DB16*$EF44*1000 -> 0 | DC44: =DC16*$EF44*1000 -> 0 | ... DZ44: =DZ16*$EF44*1000 -> 0 | EF44: 0 | EM44: BPW | EP44: Power
B45: =B17 -> Apparel - NBM | C45: job | D45: =D17*$EF45*1000 -> 0 | E45: =E17*$EF45*1000 -> 0 | F45: =F17*$EF45*1000 -> 0 | G45: =G17*$EF45*1000 -> 0 | H45: =H17*$EF45*1000 -> 0 | I45: =I17*$EF45*1000 -> 0 | J45: =J17*$EF45*1000 -> 0 | K45: =K17*$EF45*1000 -> 0 | ... AH45: =AH17*$EF45*1000 -> 0 | AJ45: =AJ17*$EF45*1000 -> 0 | AK45: =AK17*$EF45*1000 -> 0 | AL45: =AL17*$EF45*1000 -> 0 | AM45: =AM17*$EF45*1000 -> 0 | AN45: =AN17*$EF45*1000 -> 0 | AO45: =AO17*$EF45*1000 -> 0 | AP45: =AP17*$EF45*1000 -> 0 | AQ45: =AQ17*$EF45*1000 -> 0 | ... BN45: =BN17*$EF45*1000 -> 0 | BO45: =SUM(BN49:BN50) -> 738421.64 | BP45: =BP17*$EF45*1000 -> 0 | BQ45: =BQ17*$EF45*1000 -> 0 | BR45: =BR17*$EF45*1000 -> 0 | BS45: =BS17*$EF45*1000 -> 0 | BT45: =BT17*$EF45*1000 -> 0 | BU45: =BU17*$EF45*1000 -> 0 | BV45: =BV17*$EF45*1000 -> 0 | BW45: =BW17*$EF45*1000 -> 0 | ... CT45: =CT17*$EF45*1000 -> 0 | CU45: =SUM(CT49:CT50) -> 149475.74 | CV45: =CV17*$EF45*1000 -> 0 | CW45: =CW17*$EF45*1000 -> 0 | CX45: =CX17*$EF45*1000 -> 0 | CY45: =CY17*$EF45*1000 -> 0 | CZ45: =CZ17*$EF45*1000 -> 0 | DA45: =DA17*$EF45*1000 -> 0 | DB45: =DB17*$EF45*1000 -> 0 | DC45: =DC17*$EF45*1000 -> 0 | ... DZ45: =DZ17*$EF45*1000 -> 0 | EF45: =AVERAGE(5.6,13.3) -> 9.45 | EH45: =SUM(AJ49:AJ50) -> 90947.001 | EI45: =CU45 -> 149475.74 | EJ45: =BO45 -> 738421.64 | EK45: =EJ45 -> 738421.64 | EM45: BPW | EP45: Fossil
B46: =B18 -> Apparel - substitution | C46: job | D46: =D18*$EF46*1000 -> 0 | E46: =E18*$EF46*1000 -> 0 | F46: =F18*$EF46*1000 -> 0 | G46: =G18*$EF46*1000 -> 0 | H46: =H18*$EF46*1000 -> 0 | I46: =I18*$EF46*1000 -> 0 | J46: =J18*$EF46*1000 -> 0 | K46: =K18*$EF46*1000 -> 0 | ... AH46: =AH18*$EF46*1000 -> 0 | AJ46: =AJ18*$EF46*1000 -> 0 | AK46: =AK18*$EF46*1000 -> 0 | AL46: =AL18*$EF46*1000 -> 0 | AM46: =AM18*$EF46*1000 -> 0 | AN46: =AN18*$EF46*1000 -> 0 | AO46: =AO18*$EF46*1000 -> 0 | AP46: =AP18*$EF46*1000 -> 0 | AQ46: =AQ18*$EF46*1000 -> 0 | ... BN46: =BN18*$EF46*1000 -> 0 | BO46: =SUM(BN51:BN53) -> 2135883.6 | BP46: =BP18*$EF46*1000 -> 0 | BQ46: =BQ18*$EF46*1000 -> 0 | BR46: =BR18*$EF46*1000 -> 0 | BS46: =BS18*$EF46*1000 -> 0 | BT46: =BT18*$EF46*1000 -> 0 | BU46: =BU18*$EF46*1000 -> 0 | BV46: =BV18*$EF46*1000 -> 0 | BW46: =BW18*$EF46*1000 -> 0 | ... CT46: =CT18*$EF46*1000 -> 0 | CU46: =SUM(CT51:CT53) -> 1582598.2 | CV46: =CV18*$EF46*1000 -> 0 | CW46: =CW18*$EF46*1000 -> 0 | CX46: =CX18*$EF46*1000 -> 0 | CY46: =CY18*$EF46*1000 -> 0 | CZ46: =CZ18*$EF46*1000 -> 0 | DA46: =DA18*$EF46*1000 -> 0 | DB46: =DB18*$EF46*1000 -> 0 | DC46: =DC18*$EF46*1000 -> 0 | ... DZ46: =DZ18*$EF46*1000 -> 0 | EF46: 18.5 | EH46: =SUM(AJ51:AJ53) -> 1137950.8 | EI46: =CU46 -> 1582598.2 | EJ46: =BO46 -> 2135883.6 | EK46: =EJ46 -> 2135883.6 | EM46: BPW | EQ46: Job/1000 ton
B47: =B19 -> Others Reduction | C47: job | D47: =D19*$EF47*1000 -> 0 | E47: =E19*$EF47*1000 -> 0 | F47: =F19*$EF47*1000 -> 0 | G47: =G19*$EF47*1000 -> 0 | H47: =H19*$EF47*1000 -> 0 | I47: =I19*$EF47*1000 -> 0 | J47: =J19*$EF47*1000 -> 0 | K47: =K19*$EF47*1000 -> 0 | ... AH47: =AH19*$EF47*1000 -> 0 | AJ47: =AJ19*$EF47*1000 -> 0 | AK47: =AK19*$EF47*1000 -> 0 | AL47: =AL19*$EF47*1000 -> 0 | AM47: =AM19*$EF47*1000 -> 0 | AN47: =AN19*$EF47*1000 -> 0 | AO47: =AO19*$EF47*1000 -> 0 | AP47: =AP19*$EF47*1000 -> 0 | AQ47: =AQ19*$EF47*1000 -> 0 | ... BN47: =BN19*$EF47*1000 -> 0 | BO47: =SUM(BN37:BN48) -> 0 | BP47: =BP19*$EF47*1000 -> 0 | BQ47: =BQ19*$EF47*1000 -> 0 | BR47: =BR19*$EF47*1000 -> 0 | BS47: =BS19*$EF47*1000 -> 0 | BT47: =BT19*$EF47*1000 -> 0 | BU47: =BU19*$EF47*1000 -> 0 | BV47: =BV19*$EF47*1000 -> 0 | BW47: =BW19*$EF47*1000 -> 0 | ... CT47: =CT19*$EF47*1000 -> 0 | CU47: =SUM(CT37:CT48) -> 0 | CV47: =CV19*$EF47*1000 -> 0 | CW47: =CW19*$EF47*1000 -> 0 | CX47: =CX19*$EF47*1000 -> 0 | CY47: =CY19*$EF47*1000 -> 0 | CZ47: =CZ19*$EF47*1000 -> 0 | DA47: =DA19*$EF47*1000 -> 0 | DB47: =DB19*$EF47*1000 -> 0 | DC47: =DC19*$EF47*1000 -> 0 | ... DZ47: =DZ19*$EF47*1000 -> 0 | EF47: 0 | EH47: =SUM(AJ37:AJ48) -> 0 | EI47: =CU47 -> 0 | EJ47: =BO47 -> 0 | EK47: =EJ47 -> 0 | EM47: BPW | EP47: Biomass
B48: =B20 -> Others Substitution | C48: job | D48: =D20*$EF48*1000 -> 0 | E48: =E20*$EF48*1000 -> 0 | F48: =F20*$EF48*1000 -> 0 | G48: =G20*$EF48*1000 -> 0 | H48: =H20*$EF48*1000 -> 0 | I48: =I20*$EF48*1000 -> 0 | J48: =J20*$EF48*1000 -> 0 | K48: =K20*$EF48*1000 -> 0 | ... AH48: =AH20*$EF48*1000 -> 0 | AJ48: =AJ20*$EF48*1000 -> 0 | AK48: =AK20*$EF48*1000 -> 0 | AL48: =AL20*$EF48*1000 -> 0 | AM48: =AM20*$EF48*1000 -> 0 | AN48: =AN20*$EF48*1000 -> 0 | AO48: =AO20*$EF48*1000 -> 0 | AP48: =AP20*$EF48*1000 -> 0 | AQ48: =AQ20*$EF48*1000 -> 0 | ... BN48: =BN20*$EF48*1000 -> 0 | BP48: =BP20*$EF48*1000 -> 0 | BQ48: =BQ20*$EF48*1000 -> 0 | BR48: =BR20*$EF48*1000 -> 0 | BS48: =BS20*$EF48*1000 -> 0 | BT48: =BT20*$EF48*1000 -> 0 | BU48: =BU20*$EF48*1000 -> 0 | BV48: =BV20*$EF48*1000 -> 0 | BW48: =BW20*$EF48*1000 -> 0 | ... CT48: =CT20*$EF48*1000 -> 0 | CV48: =CV20*$EF48*1000 -> 0 | CW48: =CW20*$EF48*1000 -> 0 | CX48: =CX20*$EF48*1000 -> 0 | CY48: =CY20*$EF48*1000 -> 0 | CZ48: =CZ20*$EF48*1000 -> 0 | DA48: =DA20*$EF48*1000 -> 0 | DB48: =DB20*$EF48*1000 -> 0 | DC48: =DC20*$EF48*1000 -> 0 | ... DZ48: =DZ20*$EF48*1000 -> 0 | EF48: 18.5 | EM48: BPW | EP48: Fossil
B49: =B22 -> Mecahnical Recycling | C49: job | D49: =D22*$EF49*1000 -> 90946.501 | E49: =E22*$EF49*1000 -> 97702.005 | F49: =F22*$EF49*1000 -> 105917.57 | G49: =G22*$EF49*1000 -> 114275.4 | H49: =H22*$EF49*1000 -> 122727.55 | I49: =I22*$EF49*1000 -> 131222.95 | J49: =J22*$EF49*1000 -> 140009.29 | K49: =K22*$EF49*1000 -> 149087 | ... AH49: =AH22*$EF49*1000 -> 676967.2 | AJ49: =AJ22*$EF49*1000 -> 90946.501 | AK49: =AK22*$EF49*1000 -> 97702.005 | AL49: =AL22*$EF49*1000 -> 105917.57 | AM49: =AM22*$EF49*1000 -> 114275.4 | AN49: =AN22*$EF49*1000 -> 122727.55 | AO49: =AO22*$EF49*1000 -> 131222.95 | AP49: =AP22*$EF49*1000 -> 140009.29 | AQ49: =AQ22*$EF49*1000 -> 149087 | ... BN49: =BN22*$EF49*1000 -> 676967.2 | BP49: =BP22*$EF49*1000 -> 90946.501 | BQ49: =BQ22*$EF49*1000 -> 92465.308 | BR49: =BR22*$EF49*1000 -> 94009.479 | BS49: =BS22*$EF49*1000 -> 95579.437 | BT49: =BT22*$EF49*1000 -> 97175.614 | BU49: =BU22*$EF49*1000 -> 98798.446 | BV49: =BV22*$EF49*1000 -> 100448.38 | BW49: =BW22*$EF49*1000 -> 102125.87 | ... CT49: =CT22*$EF49*1000 -> 149475.74 | CV49: =CV22*$EF49*1000 -> 90946.501 | CW49: =CW22*$EF49*1000 -> 97702.005 | CX49: =CX22*$EF49*1000 -> 105917.57 | CY49: =CY22*$EF49*1000 -> 114275.4 | CZ49: =CZ22*$EF49*1000 -> 122727.55 | DA49: =DA22*$EF49*1000 -> 131222.95 | DB49: =DB22*$EF49*1000 -> 140009.29 | DC49: =DC22*$EF49*1000 -> 149087 | ... DZ49: =DZ22*$EF49*1000 -> 676967.2 | EF49: 3 | EH49: =SUM(EH45:EH46) -> 1228897.8 | EI49: =SUM(EI45:EI46) -> 1732073.9 | EJ49: =SUM(EJ45:EJ46) -> 2874305.2 | EK49: =SUM(EK45:EK46) -> 2874305.2 | EM49: BPW | EP49: H2
B50: =B23 -> Chemical Recycling | C50: job | D50: =D23*$EF50*1000 -> 0.90435053 | E50: =E23*$EF50*1000 -> 1.989786 | F50: =F23*$EF50*1000 -> 4.2069965 | G50: =G23*$EF50*1000 -> 8.8355565 | H50: =H23*$EF50*1000 -> 18.416136 | I50: =I23*$EF50*1000 -> 38.045518 | J50: =J23*$EF50*1000 -> 77.928449 | K50: =K23*$EF50*1000 -> 157.8666 | ... AH50: =AH23*$EF50*1000 -> 110240.07 | AJ50: =AJ23*$EF50*1000 -> 0.49969639 | AK50: =AK23*$EF50*1000 -> 1.1051882 | AL50: =AL23*$EF50*1000 -> 2.336142 | AM50: =AM23*$EF50*1000 -> 4.905513 | AN50: =AN23*$EF50*1000 -> 10.223429 | AO50: =AO23*$EF50*1000 -> 21.1189 | AP50: =AP23*$EF50*1000 -> 43.256765 | AQ50: =AQ23*$EF50*1000 -> 87.630925 | ... BN50: =BN23*$EF50*1000 -> 61454.437 | BP50: =BP23*$EF50*1000 -> 0 | BQ50: =BQ23*$EF50*1000 -> 0 | BR50: =BR23*$EF50*1000 -> 0 | BS50: =BS23*$EF50*1000 -> 0 | BT50: =BT23*$EF50*1000 -> 0 | BU50: =BU23*$EF50*1000 -> 0 | BV50: =BV23*$EF50*1000 -> 0 | BW50: =BW23*$EF50*1000 -> 0 | ... CT50: =CT23*$EF50*1000 -> 0 | CV50: =CV23*$EF50*1000 -> 0.49969639 | CW50: =CW23*$EF50*1000 -> 1.1051882 | CX50: =CX23*$EF50*1000 -> 2.336142 | CY50: =CY23*$EF50*1000 -> 4.905513 | CZ50: =CZ23*$EF50*1000 -> 10.223429 | DA50: =DA23*$EF50*1000 -> 21.1189 | DB50: =DB23*$EF50*1000 -> 43.256765 | DC50: =DC23*$EF50*1000 -> 87.630925 | ... DZ50: =DZ23*$EF50*1000 -> 61454.437 | EF50: 6.3 | EH50: =EH47 -> 0 | EI50: =EI47 -> 0 | EJ50: =EJ47 -> 0 | EK50: =EK47 -> 0 | EM50: BPWE | EP50: CO2
B51: =B24 -> Waste management (collection + MRF) | C51: job | D51: =D24*$EF51*1000 -> 1122364 | E51: =E24*$EF51*1000 -> 1165265 | F51: =F24*$EF51*1000 -> 1207103.6 | G51: =G24*$EF51*1000 -> 1247113 | H51: =H24*$EF51*1000 -> 1285019.2 | I51: =I24*$EF51*1000 -> 1320557.1 | J51: =J24*$EF51*1000 -> 1356394.2 | K51: =K24*$EF51*1000 -> 1392505 | ... AH51: =AH24*$EF51*1000 -> 2122231.8 | AJ51: =AJ24*$EF51*1000 -> 1122363.9 | AK51: =AK24*$EF51*1000 -> 1165264.8 | AL51: =AL24*$EF51*1000 -> 1207103.3 | AM51: =AM24*$EF51*1000 -> 1247112.3 | AN51: =AN24*$EF51*1000 -> 1285017.8 | AO51: =AO24*$EF51*1000 -> 1320554.2 | AP51: =AP24*$EF51*1000 -> 1356388.3 | AQ51: =AQ24*$EF51*1000 -> 1392493.2 | ... BN51: =BN24*$EF51*1000 -> 2114969 | BP51: =BP24*$EF51*1000 -> 1122363.8 | BQ51: =BQ24*$EF51*1000 -> 1154515.4 | BR51: =BR24*$EF51*1000 -> 1184546.7 | BS51: =BS24*$EF51*1000 -> 1212250.2 | BT51: =BT24*$EF51*1000 -> 1237432 | BU51: =BU24*$EF51*1000 -> 1259914.5 | BV51: =BV24*$EF51*1000 -> 1282209.4 | BW51: =BW24*$EF51*1000 -> 1304292.1 | ... CT51: =CT24*$EF51*1000 -> 1565176.4 | CV51: =CV24*$EF51*1000 -> 1122363.9 | CW51: =CW24*$EF51*1000 -> 1165264.8 | CX51: =CX24*$EF51*1000 -> 1207103.3 | CY51: =CY24*$EF51*1000 -> 1247112.3 | CZ51: =CZ24*$EF51*1000 -> 1285017.8 | DA51: =DA24*$EF51*1000 -> 1320554.2 | DB51: =DB24*$EF51*1000 -> 1356388.3 | DC51: =DC24*$EF51*1000 -> 1392493.2 | ... DZ51: =DZ24*$EF51*1000 -> 2110699 | EF51: 4.5 | EM51: BPWE | EP51: Waste
B52: =B25 -> Incineration | C52: job | D52: =D25*$EF52*1000 -> 4705.4727 | E52: =E25*$EF52*1000 -> 5004.8825 | F52: =F25*$EF52*1000 -> 5295.9424 | G52: =G25*$EF52*1000 -> 5583.4867 | H52: =H25*$EF52*1000 -> 5865.5071 | I52: =I25*$EF52*1000 -> 6139.9631 | J52: =J25*$EF52*1000 -> 6418.6157 | K52: =K25*$EF52*1000 -> 6701.1158 | ... AH52: =AH25*$EF52*1000 -> 8807.8228 | AJ52: =AJ25*$EF52*1000 -> 4705.4737 | AK52: =AK25*$EF52*1000 -> 5004.8848 | AL52: =AL25*$EF52*1000 -> 5295.9475 | AM52: =AM25*$EF52*1000 -> 5583.4977 | AN52: =AN25*$EF52*1000 -> 5865.5307 | AO52: =AO25*$EF52*1000 -> 6140.0132 | AP52: =AP25*$EF52*1000 -> 6418.7213 | AQ52: =AQ25*$EF52*1000 -> 6701.3358 | ... BN52: =BN25*$EF52*1000 -> 9044.1521 | BP52: =BP25*$EF52*1000 -> 4705.475 | BQ52: =BQ25*$EF52*1000 -> 4934.2906 | BR52: =BR25*$EF52*1000 -> 5158.3686 | BS52: =BS25*$EF52*1000 -> 5376.187 | BT52: =BT25*$EF52*1000 -> 5586.2127 | BU52: =BU25*$EF52*1000 -> 5786.9183 | BV52: =BV25*$EF52*1000 -> 5990.9386 | BW52: =BW25*$EF52*1000 -> 6198.1436 | ... CT52: =CT25*$EF52*1000 -> 10368.991 | CV52: =CV25*$EF52*1000 -> 4705.4737 | CW52: =CW25*$EF52*1000 -> 5004.8848 | CX52: =CX25*$EF52*1000 -> 5295.9475 | CY52: =CY25*$EF52*1000 -> 5583.4977 | CZ52: =CZ25*$EF52*1000 -> 5865.5307 | DA52: =DA25*$EF52*1000 -> 6140.0132 | DB52: =DB25*$EF52*1000 -> 6418.7213 | DC52: =DC25*$EF52*1000 -> 6701.3358 | ... DZ52: =DZ25*$EF52*1000 -> 9007.5684 | EF52: 0.1 | EM52: BPW
B53: =B26 -> Landfill | C53: job | D53: =D26*$EF53*1000 -> 10881.406 | E53: =E26*$EF53*1000 -> 11250.895 | F53: =F26*$EF53*1000 -> 11584.874 | G53: =G26*$EF53*1000 -> 11896.634 | H53: =H26*$EF53*1000 -> 12183.866 | I53: =I26*$EF53*1000 -> 12444.389 | J53: =J26*$EF53*1000 -> 12703.51 | K53: =K26*$EF53*1000 -> 12960.773 | ... AH53: =AH26*$EF53*1000 -> 11560.267 | AJ53: =AJ26*$EF53*1000 -> 10881.408 | AK53: =AK26*$EF53*1000 -> 11250.9 | AL53: =AL26*$EF53*1000 -> 11584.885 | AM53: =AM26*$EF53*1000 -> 11896.657 | AN53: =AN26*$EF53*1000 -> 12183.915 | AO53: =AO26*$EF53*1000 -> 12444.491 | AP53: =AP26*$EF53*1000 -> 12703.719 | AQ53: =AQ26*$EF53*1000 -> 12961.199 | ... BN53: =BN26*$EF53*1000 -> 11870.45 | BP53: =BP26*$EF53*1000 -> 10881.411 | BQ53: =BQ26*$EF53*1000 -> 11042.784 | BR53: =BR26*$EF53*1000 -> 11169.481 | BS53: =BS26*$EF53*1000 -> 11260.233 | BT53: =BT26*$EF53*1000 -> 11314.073 | BU53: =BU26*$EF53*1000 -> 11330.356 | BV53: =BV26*$EF53*1000 -> 11335.523 | BW53: =BW26*$EF53*1000 -> 11329.316 | ... CT53: =CT26*$EF53*1000 -> 7052.7823 | CV53: =CV26*$EF53*1000 -> 10881.408 | CW53: =CW26*$EF53*1000 -> 11250.9 | CX53: =CX26*$EF53*1000 -> 11584.885 | CY53: =CY26*$EF53*1000 -> 11896.657 | CZ53: =CZ26*$EF53*1000 -> 12183.915 | DA53: =DA26*$EF53*1000 -> 12444.491 | DB53: =DB26*$EF53*1000 -> 12703.719 | DC53: =DC26*$EF53*1000 -> 12961.199 | ... DZ53: =DZ26*$EF53*1000 -> 11822.433 | EF53: 0.1 | EM53: BPW
B54: =B27 -> Dumpsite | C54: job | D54: =D26*$EF54*1000 -> 0 | E54: =E26*$EF54*1000 -> 0 | F54: =F26*$EF54*1000 -> 0 | G54: =G26*$EF54*1000 -> 0 | H54: =H26*$EF54*1000 -> 0 | I54: =I26*$EF54*1000 -> 0 | J54: =J26*$EF54*1000 -> 0 | K54: =K26*$EF54*1000 -> 0 | ... AH54: =AH26*$EF54*1000 -> 0 | AJ54: =AJ26*$EF54*1000 -> 0 | AK54: =AK26*$EF54*1000 -> 0 | AL54: =AL26*$EF54*1000 -> 0 | AM54: =AM26*$EF54*1000 -> 0 | AN54: =AN26*$EF54*1000 -> 0 | AO54: =AO26*$EF54*1000 -> 0 | AP54: =AP26*$EF54*1000 -> 0 | AQ54: =AQ26*$EF54*1000 -> 0 | ... BN54: =BN26*$EF54*1000 -> 0 | BP54: =BP26*$EF54*1000 -> 0 | BQ54: =BQ26*$EF54*1000 -> 0 | BR54: =BR26*$EF54*1000 -> 0 | BS54: =BS26*$EF54*1000 -> 0 | BT54: =BT26*$EF54*1000 -> 0 | BU54: =BU26*$EF54*1000 -> 0 | BV54: =BV26*$EF54*1000 -> 0 | BW54: =BW26*$EF54*1000 -> 0 | ... CT54: =CT26*$EF54*1000 -> 0 | CV54: =CV26*$EF54*1000 -> 0 | CW54: =CW26*$EF54*1000 -> 0 | CX54: =CX26*$EF54*1000 -> 0 | CY54: =CY26*$EF54*1000 -> 0 | CZ54: =CZ26*$EF54*1000 -> 0 | DA54: =DA26*$EF54*1000 -> 0 | DB54: =DB26*$EF54*1000 -> 0 | DC54: =DC26*$EF54*1000 -> 0 | ... DZ54: =DZ26*$EF54*1000 -> 0 | EF54: 0 | EM54: BPW
B55: =B28 -> Open Burning | C55: job | D55: =D27*$EF55*1000 -> 0 | E55: =E27*$EF55*1000 -> 0 | F55: =F27*$EF55*1000 -> 0 | G55: =G27*$EF55*1000 -> 0 | H55: =H27*$EF55*1000 -> 0 | I55: =I27*$EF55*1000 -> 0 | J55: =J27*$EF55*1000 -> 0 | K55: =K27*$EF55*1000 -> 0 | ... AH55: =AH27*$EF55*1000 -> 0 | AJ55: =AJ27*$EF55*1000 -> 0 | AK55: =AK27*$EF55*1000 -> 0 | AL55: =AL27*$EF55*1000 -> 0 | AM55: =AM27*$EF55*1000 -> 0 | AN55: =AN27*$EF55*1000 -> 0 | AO55: =AO27*$EF55*1000 -> 0 | AP55: =AP27*$EF55*1000 -> 0 | AQ55: =AQ27*$EF55*1000 -> 0 | ... BN55: =BN27*$EF55*1000 -> 0 | BP55: =BP27*$EF55*1000 -> 0 | BQ55: =BQ27*$EF55*1000 -> 0 | BR55: =BR27*$EF55*1000 -> 0 | BS55: =BS27*$EF55*1000 -> 0 | BT55: =BT27*$EF55*1000 -> 0 | BU55: =BU27*$EF55*1000 -> 0 | BV55: =BV27*$EF55*1000 -> 0 | BW55: =BW27*$EF55*1000 -> 0 | ... CT55: =CT27*$EF55*1000 -> 0 | CV55: =CV27*$EF55*1000 -> 0 | CW55: =CW27*$EF55*1000 -> 0 | CX55: =CX27*$EF55*1000 -> 0 | CY55: =CY27*$EF55*1000 -> 0 | CZ55: =CZ27*$EF55*1000 -> 0 | DA55: =DA27*$EF55*1000 -> 0 | DB55: =DB27*$EF55*1000 -> 0 | DC55: =DC27*$EF55*1000 -> 0 | ... DZ55: =DZ27*$EF55*1000 -> 0 | EF55: 0 | EM55: BPW
B56: =B29 -> Leakage Environment | C56: job | D56: =D28*$EF56*1000 -> 0 | E56: =E28*$EF56*1000 -> 0 | F56: =F28*$EF56*1000 -> 0 | G56: =G28*$EF56*1000 -> 0 | H56: =H28*$EF56*1000 -> 0 | I56: =I28*$EF56*1000 -> 0 | J56: =J28*$EF56*1000 -> 0 | K56: =K28*$EF56*1000 -> 0 | ... AH56: =AH28*$EF56*1000 -> 0 | AJ56: =AJ28*$EF56*1000 -> 0 | AK56: =AK28*$EF56*1000 -> 0 | AL56: =AL28*$EF56*1000 -> 0 | AM56: =AM28*$EF56*1000 -> 0 | AN56: =AN28*$EF56*1000 -> 0 | AO56: =AO28*$EF56*1000 -> 0 | AP56: =AP28*$EF56*1000 -> 0 | AQ56: =AQ28*$EF56*1000 -> 0 | ... BN56: =BN28*$EF56*1000 -> 0 | BP56: =BP28*$EF56*1000 -> 0 | BQ56: =BQ28*$EF56*1000 -> 0 | BR56: =BR28*$EF56*1000 -> 0 | BS56: =BS28*$EF56*1000 -> 0 | BT56: =BT28*$EF56*1000 -> 0 | BU56: =BU28*$EF56*1000 -> 0 | BV56: =BV28*$EF56*1000 -> 0 | BW56: =BW28*$EF56*1000 -> 0 | ... CT56: =CT28*$EF56*1000 -> 0 | CV56: =CV28*$EF56*1000 -> 0 | CW56: =CW28*$EF56*1000 -> 0 | CX56: =CX28*$EF56*1000 -> 0 | CY56: =CY28*$EF56*1000 -> 0 | CZ56: =CZ28*$EF56*1000 -> 0 | DA56: =DA28*$EF56*1000 -> 0 | DB56: =DB28*$EF56*1000 -> 0 | DC56: =DC28*$EF56*1000 -> 0 | ... DZ56: =DZ28*$EF56*1000 -> 0 | EF56: 0 | EM56: BPW
B57: =B30 -> Leakage Ocean | C57: job | D57: =D29*$EF57*1000 -> 0 | E57: =E29*$EF57*1000 -> 0 | F57: =F29*$EF57*1000 -> 0 | G57: =G29*$EF57*1000 -> 0 | H57: =H29*$EF57*1000 -> 0 | I57: =I29*$EF57*1000 -> 0 | J57: =J29*$EF57*1000 -> 0 | K57: =K29*$EF57*1000 -> 0 | ... AH57: =AH29*$EF57*1000 -> 0 | AJ57: =AJ29*$EF57*1000 -> 0 | AK57: =AK29*$EF57*1000 -> 0 | AL57: =AL29*$EF57*1000 -> 0 | AM57: =AM29*$EF57*1000 -> 0 | AN57: =AN29*$EF57*1000 -> 0 | AO57: =AO29*$EF57*1000 -> 0 | AP57: =AP29*$EF57*1000 -> 0 | AQ57: =AQ29*$EF57*1000 -> 0 | ... BN57: =BN29*$EF57*1000 -> 0 | BP57: =BP29*$EF57*1000 -> 0 | BQ57: =BQ29*$EF57*1000 -> 0 | BR57: =BR29*$EF57*1000 -> 0 | BS57: =BS29*$EF57*1000 -> 0 | BT57: =BT29*$EF57*1000 -> 0 | BU57: =BU29*$EF57*1000 -> 0 | BV57: =BV29*$EF57*1000 -> 0 | BW57: =BW29*$EF57*1000 -> 0 | ... CT57: =CT29*$EF57*1000 -> 0 | CV57: =CV29*$EF57*1000 -> 0 | CW57: =CW29*$EF57*1000 -> 0 | CX57: =CX29*$EF57*1000 -> 0 | CY57: =CY29*$EF57*1000 -> 0 | CZ57: =CZ29*$EF57*1000 -> 0 | DA57: =DA29*$EF57*1000 -> 0 | DB57: =DB29*$EF57*1000 -> 0 | DC57: =DC29*$EF57*1000 -> 0 | ... DZ57: =DZ29*$EF57*1000 -> 0 | EF57: 0 | EM57: BPW
A58: Additonal job creation from circular levers | C58: job | D58: =SUM(D35:D57) -> 1228898.3 | E58: =SUM(E35:E57) -> 1279224.7 | F58: =SUM(F35:F57) -> 1329906.2 | G58: =SUM(G35:G57) -> 1378877.4 | H58: =SUM(H35:H57) -> 1425814.5 | I58: =SUM(I35:I57) -> 1470402.4 | J58: =SUM(J35:J57) -> 1515603.6 | K58: =SUM(K35:K57) -> 1561411.8 | ... AH58: =SUM(AH35:AH57) -> 2929807.2 | AJ58: =SUM(AJ35:AJ57) -> 1228897.8 | AK58: =SUM(AK35:AK57) -> 1279223.7 | AL58: =SUM(AL35:AL57) -> 1329904 | AM58: =SUM(AM35:AM57) -> 1378872.8 | AN58: =SUM(AN35:AN57) -> 1425805 | AO58: =SUM(AO35:AO57) -> 1470382.7 | AP58: =SUM(AP35:AP57) -> 1515563.3 | AQ58: =SUM(AQ35:AQ57) -> 1561330.4 | ... BN58: =SUM(BN35:BN57) -> 2874305.2 | BP58: =SUM(BP35:BP57) -> 1228897.2 | BQ58: =SUM(BQ35:BQ57) -> 1262957.7 | BR58: =SUM(BR35:BR57) -> 1294884.1 | BS58: =SUM(BS35:BS57) -> 1324466.1 | BT58: =SUM(BT35:BT57) -> 1351507.9 | BU58: =SUM(BU35:BU57) -> 1375830.2 | BV58: =SUM(BV35:BV57) -> 1399984.2 | BW58: =SUM(BW35:BW57) -> 1423945.4 | ... CT58: =SUM(CT35:CT57) -> 1732073.9 | CV58: =SUM(CV35:CV57) -> 1228897.8 | CW58: =SUM(CW35:CW57) -> 1279223.7 | CX58: =SUM(CX35:CX57) -> 1329904 | CY58: =SUM(CY35:CY57) -> 1378872.8 | CZ58: =SUM(CZ35:CZ57) -> 1425805 | DA58: =SUM(DA35:DA57) -> 1470382.7 | DB58: =SUM(DB35:DB57) -> 1515563.3 | DC58: =SUM(DC35:DC57) -> 1561330.4 | ... DZ58: =SUM(DZ35:DZ57) -> 2869950.6
EF59: Emission factor | EG59: mT CO2 / mT of plastic
A60: CO2 | EF60: 2020 | EG60: 2050 | EM60: Source
B61: =B35 -> Fuel additive elimination | C61: mT CO2eq | D61: =D7*($EF61-$EG61)/30*(D$2-$D$2) -> 0 | E61: =E7*($EF61-$EG61)/30*(E$2-$D$2) -> 0 | F61: =F7*($EF61-$EG61)/30*(F$2-$D$2) -> 0 | G61: =G7*($EF61-$EG61)/30*(G$2-$D$2) -> 0 | H61: =H7*($EF61-$EG61)/30*(H$2-$D$2) -> 0 | I61: =I7*($EF61-$EG61)/30*(I$2-$D$2) -> 0 | J61: =J7*($EF61-$EG61)/30*(J$2-$D$2) -> 0 | K61: =K7*($EF61-$EG61)/30*(K$2-$D$2) -> 0 | ... AH61: =AH7*($EF61-$EG61)/30*(AH$2-$D$2) -> 0 | AJ61: =AJ7*($EF61-$EG61)/30*(AJ$2-$D$2) -> 0 | AK61: =AK7*($EF61-$EG61)/30*(AK$2-$D$2) -> 0 | AL61: =AL7*($EF61-$EG61)/30*(AL$2-$D$2) -> 0 | AM61: =AM7*($EF61-$EG61)/30*(AM$2-$D$2) -> 0 | AN61: =AN7*($EF61-$EG61)/30*(AN$2-$D$2) -> 0 | AO61: =AO7*($EF61-$EG61)/30*(AO$2-$D$2) -> 0 | AP61: =AP7*($EF61-$EG61)/30*(AP$2-$D$2) -> 0 | AQ61: =AQ7*($EF61-$EG61)/30*(AQ$2-$D$2) -> 0 | ... BN61: =BN7*($EF61-$EG61)/30*(BN$2-$D$2) -> 0 | BP61: =BP7*($EF61-$EG61)/30*(BP$2-$D$2) -> 0 | BQ61: =BQ7*($EF61-$EG61)/30*(BQ$2-$D$2) -> 0 | BR61: =BR7*($EF61-$EG61)/30*(BR$2-$D$2) -> 0 | BS61: =BS7*($EF61-$EG61)/30*(BS$2-$D$2) -> 0 | BT61: =BT7*($EF61-$EG61)/30*(BT$2-$D$2) -> 0 | BU61: =BU7*($EF61-$EG61)/30*(BU$2-$D$2) -> 0 | BV61: =BV7*($EF61-$EG61)/30*(BV$2-$D$2) -> 0 | BW61: =BW7*($EF61-$EG61)/30*(BW$2-$D$2) -> 0 | ... CT61: =CT7*($EF61-$EG61)/30*(CT$2-$D$2) -> 0 | CV61: =CV7*($EF61-$EG61)/30*(CV$2-$D$2) -> 0 | CW61: =CW7*($EF61-$EG61)/30*(CW$2-$D$2) -> 0 | CX61: =CX7*($EF61-$EG61)/30*(CX$2-$D$2) -> 0 | CY61: =CY7*($EF61-$EG61)/30*(CY$2-$D$2) -> 0 | CZ61: =CZ7*($EF61-$EG61)/30*(CZ$2-$D$2) -> 0 | DA61: =DA7*($EF61-$EG61)/30*(DA$2-$D$2) -> 0 | DB61: =DB7*($EF61-$EG61)/30*(DB$2-$D$2) -> 0 | DC61: =DC7*($EF61-$EG61)/30*(DC$2-$D$2) -> 0 | ... DZ61: =DZ7*($EF61-$EG61)/30*(DZ$2-$D$2) -> 0 | EF61: 0 | EG61: 0 | EM61: None
B62: =B36 -> Packaging reduction | C62: mT CO2eq | D62: =D8*($EF62-$EG62)/30*(D$2-$D$2) -> 0 | E62: =E8*($EF62-$EG62)/30*(E$2-$D$2) -> 0 | F62: =F8*($EF62-$EG62)/30*(F$2-$D$2) -> 0 | G62: =G8*($EF62-$EG62)/30*(G$2-$D$2) -> 0 | H62: =H8*($EF62-$EG62)/30*(H$2-$D$2) -> 0 | I62: =I8*($EF62-$EG62)/30*(I$2-$D$2) -> 0 | J62: =J8*($EF62-$EG62)/30*(J$2-$D$2) -> 0 | K62: =K8*($EF62-$EG62)/30*(K$2-$D$2) -> 0 | ... AH62: =AH8*($EF62-$EG62)/30*(AH$2-$D$2) -> 0 | AJ62: =AJ8*($EF62-$EG62)/30*(AJ$2-$D$2) -> 0 | AK62: =AK8*($EF62-$EG62)/30*(AK$2-$D$2) -> 0 | AL62: =AL8*($EF62-$EG62)/30*(AL$2-$D$2) -> 0 | AM62: =AM8*($EF62-$EG62)/30*(AM$2-$D$2) -> 0 | AN62: =AN8*($EF62-$EG62)/30*(AN$2-$D$2) -> 0 | AO62: =AO8*($EF62-$EG62)/30*(AO$2-$D$2) -> 0 | AP62: =AP8*($EF62-$EG62)/30*(AP$2-$D$2) -> 0 | AQ62: =AQ8*($EF62-$EG62)/30*(AQ$2-$D$2) -> 0 | ... BN62: =BN8*($EF62-$EG62)/30*(BN$2-$D$2) -> 0 | BP62: =BP8*($EF62-$EG62)/30*(BP$2-$D$2) -> 0 | BQ62: =BQ8*($EF62-$EG62)/30*(BQ$2-$D$2) -> 0 | BR62: =BR8*($EF62-$EG62)/30*(BR$2-$D$2) -> 0 | BS62: =BS8*($EF62-$EG62)/30*(BS$2-$D$2) -> 0 | BT62: =BT8*($EF62-$EG62)/30*(BT$2-$D$2) -> 0 | BU62: =BU8*($EF62-$EG62)/30*(BU$2-$D$2) -> 0 | BV62: =BV8*($EF62-$EG62)/30*(BV$2-$D$2) -> 0 | BW62: =BW8*($EF62-$EG62)/30*(BW$2-$D$2) -> 0 | ... CT62: =CT8*($EF62-$EG62)/30*(CT$2-$D$2) -> 0 | CV62: =CV8*($EF62-$EG62)/30*(CV$2-$D$2) -> 0 | CW62: =CW8*($EF62-$EG62)/30*(CW$2-$D$2) -> 0 | CX62: =CX8*($EF62-$EG62)/30*(CX$2-$D$2) -> 0 | CY62: =CY8*($EF62-$EG62)/30*(CY$2-$D$2) -> 0 | CZ62: =CZ8*($EF62-$EG62)/30*(CZ$2-$D$2) -> 0 | DA62: =DA8*($EF62-$EG62)/30*(DA$2-$D$2) -> 0 | DB62: =DB8*($EF62-$EG62)/30*(DB$2-$D$2) -> 0 | DC62: =DC8*($EF62-$EG62)/30*(DC$2-$D$2) -> 0 | ... DZ62: =DZ8*($EF62-$EG62)/30*(DZ$2-$D$2) -> 0 | EF62: 0 | EG62: 0 | EM62: BPW
B63: =B37 -> Packaging reuse | C63: mT CO2eq | D63: =D9*($EF63-$EG63)/30*(D$2-$D$2) -> 0 | E63: =E9*($EF63-$EG63)/30*(E$2-$D$2) -> 0 | F63: =F9*($EF63-$EG63)/30*(F$2-$D$2) -> 0 | G63: =G9*($EF63-$EG63)/30*(G$2-$D$2) -> 0 | H63: =H9*($EF63-$EG63)/30*(H$2-$D$2) -> 0 | I63: =I9*($EF63-$EG63)/30*(I$2-$D$2) -> 0 | J63: =J9*($EF63-$EG63)/30*(J$2-$D$2) -> 0 | K63: =K9*($EF63-$EG63)/30*(K$2-$D$2) -> 0 | ... AH63: =AH9*($EF63-$EG63)/30*(AH$2-$D$2) -> 0 | AJ63: =AJ9*($EF63-$EG63)/30*(AJ$2-$D$2) -> 0 | AK63: =AK9*($EF63-$EG63)/30*(AK$2-$D$2) -> 0 | AL63: =AL9*($EF63-$EG63)/30*(AL$2-$D$2) -> 0 | AM63: =AM9*($EF63-$EG63)/30*(AM$2-$D$2) -> 0 | AN63: =AN9*($EF63-$EG63)/30*(AN$2-$D$2) -> 0 | AO63: =AO9*($EF63-$EG63)/30*(AO$2-$D$2) -> 0 | AP63: =AP9*($EF63-$EG63)/30*(AP$2-$D$2) -> 0 | AQ63: =AQ9*($EF63-$EG63)/30*(AQ$2-$D$2) -> 0 | ... BN63: =BN9*($EF63-$EG63)/30*(BN$2-$D$2) -> 0 | BP63: =BP9*($EF63-$EG63)/30*(BP$2-$D$2) -> 0 | BQ63: =BQ9*($EF63-$EG63)/30*(BQ$2-$D$2) -> 0 | BR63: =BR9*($EF63-$EG63)/30*(BR$2-$D$2) -> 0 | BS63: =BS9*($EF63-$EG63)/30*(BS$2-$D$2) -> 0 | BT63: =BT9*($EF63-$EG63)/30*(BT$2-$D$2) -> 0 | BU63: =BU9*($EF63-$EG63)/30*(BU$2-$D$2) -> 0 | BV63: =BV9*($EF63-$EG63)/30*(BV$2-$D$2) -> 0 | BW63: =BW9*($EF63-$EG63)/30*(BW$2-$D$2) -> 0 | ... CT63: =CT9*($EF63-$EG63)/30*(CT$2-$D$2) -> 0 | CV63: =CV9*($EF63-$EG63)/30*(CV$2-$D$2) -> 0 | CW63: =CW9*($EF63-$EG63)/30*(CW$2-$D$2) -> 0 | CX63: =CX9*($EF63-$EG63)/30*(CX$2-$D$2) -> 0 | CY63: =CY9*($EF63-$EG63)/30*(CY$2-$D$2) -> 0 | CZ63: =CZ9*($EF63-$EG63)/30*(CZ$2-$D$2) -> 0 | DA63: =DA9*($EF63-$EG63)/30*(DA$2-$D$2) -> 0 | DB63: =DB9*($EF63-$EG63)/30*(DB$2-$D$2) -> 0 | DC63: =DC9*($EF63-$EG63)/30*(DC$2-$D$2) -> 0 | ... DZ63: =DZ9*($EF63-$EG63)/30*(DZ$2-$D$2) -> 0 | EF63: =AVERAGE(1.6,4.5) -> 3.05 | EG63: 0 | EM63: BPW
B64: =B38 -> Packaging substitution Paper | C64: mT CO2eq | D64: =D10*($EF64-$EG64)/30*(D$2-$D$2) -> 0 | E64: =E10*($EF64-$EG64)/30*(E$2-$D$2) -> 0 | F64: =F10*($EF64-$EG64)/30*(F$2-$D$2) -> 0 | G64: =G10*($EF64-$EG64)/30*(G$2-$D$2) -> 0 | H64: =H10*($EF64-$EG64)/30*(H$2-$D$2) -> 0 | I64: =I10*($EF64-$EG64)/30*(I$2-$D$2) -> 0 | J64: =J10*($EF64-$EG64)/30*(J$2-$D$2) -> 0 | K64: =K10*($EF64-$EG64)/30*(K$2-$D$2) -> 0 | ... AH64: =AH10*($EF64-$EG64)/30*(AH$2-$D$2) -> 0 | AJ64: =AJ10*($EF64-$EG64)/30*(AJ$2-$D$2) -> 0 | AK64: =AK10*($EF64-$EG64)/30*(AK$2-$D$2) -> 0 | AL64: =AL10*($EF64-$EG64)/30*(AL$2-$D$2) -> 0 | AM64: =AM10*($EF64-$EG64)/30*(AM$2-$D$2) -> 0 | AN64: =AN10*($EF64-$EG64)/30*(AN$2-$D$2) -> 0 | AO64: =AO10*($EF64-$EG64)/30*(AO$2-$D$2) -> 0 | AP64: =AP10*($EF64-$EG64)/30*(AP$2-$D$2) -> 0 | AQ64: =AQ10*($EF64-$EG64)/30*(AQ$2-$D$2) -> 0 | ... BN64: =BN10*($EF64-$EG64)/30*(BN$2-$D$2) -> 0 | BP64: =BP10*($EF64-$EG64)/30*(BP$2-$D$2) -> 0 | BQ64: =BQ10*($EF64-$EG64)/30*(BQ$2-$D$2) -> 0 | BR64: =BR10*($EF64-$EG64)/30*(BR$2-$D$2) -> 0 | BS64: =BS10*($EF64-$EG64)/30*(BS$2-$D$2) -> 0 | BT64: =BT10*($EF64-$EG64)/30*(BT$2-$D$2) -> 0 | BU64: =BU10*($EF64-$EG64)/30*(BU$2-$D$2) -> 0 | BV64: =BV10*($EF64-$EG64)/30*(BV$2-$D$2) -> 0 | BW64: =BW10*($EF64-$EG64)/30*(BW$2-$D$2) -> 0 | ... CT64: =CT10*($EF64-$EG64)/30*(CT$2-$D$2) -> 0 | CV64: =CV10*($EF64-$EG64)/30*(CV$2-$D$2) -> 0 | CW64: =CW10*($EF64-$EG64)/30*(CW$2-$D$2) -> 0 | CX64: =CX10*($EF64-$EG64)/30*(CX$2-$D$2) -> 0 | CY64: =CY10*($EF64-$EG64)/30*(CY$2-$D$2) -> 0 | CZ64: =CZ10*($EF64-$EG64)/30*(CZ$2-$D$2) -> 0 | DA64: =DA10*($EF64-$EG64)/30*(DA$2-$D$2) -> 0 | DB64: =DB10*($EF64-$EG64)/30*(DB$2-$D$2) -> 0 | DC64: =DC10*($EF64-$EG64)/30*(DC$2-$D$2) -> 0 | ... DZ64: =DZ10*($EF64-$EG64)/30*(DZ$2-$D$2) -> 0 | EF64: 2.5 | EG64: 0 | EM64: BPW
B65: =B39 -> Packaging Substitution Compostables | C65: mT CO2eq | D65: =D11*($EF65-$EG65)/30*(D$2-$D$2) -> 0 | E65: =E11*($EF65-$EG65)/30*(E$2-$D$2) -> 0 | F65: =F11*($EF65-$EG65)/30*(F$2-$D$2) -> 0 | G65: =G11*($EF65-$EG65)/30*(G$2-$D$2) -> 0 | H65: =H11*($EF65-$EG65)/30*(H$2-$D$2) -> 0 | I65: =I11*($EF65-$EG65)/30*(I$2-$D$2) -> 0 | J65: =J11*($EF65-$EG65)/30*(J$2-$D$2) -> 0 | K65: =K11*($EF65-$EG65)/30*(K$2-$D$2) -> 0 | ... AH65: =AH11*($EF65-$EG65)/30*(AH$2-$D$2) -> 0 | AJ65: =AJ11*($EF65-$EG65)/30*(AJ$2-$D$2) -> 0 | AK65: =AK11*($EF65-$EG65)/30*(AK$2-$D$2) -> 0 | AL65: =AL11*($EF65-$EG65)/30*(AL$2-$D$2) -> 0 | AM65: =AM11*($EF65-$EG65)/30*(AM$2-$D$2) -> 0 | AN65: =AN11*($EF65-$EG65)/30*(AN$2-$D$2) -> 0 | AO65: =AO11*($EF65-$EG65)/30*(AO$2-$D$2) -> 0 | AP65: =AP11*($EF65-$EG65)/30*(AP$2-$D$2) -> 0 | AQ65: =AQ11*($EF65-$EG65)/30*(AQ$2-$D$2) -> 0 | ... BN65: =BN11*($EF65-$EG65)/30*(BN$2-$D$2) -> 0 | BP65: =BP11*($EF65-$EG65)/30*(BP$2-$D$2) -> 0 | BQ65: =BQ11*($EF65-$EG65)/30*(BQ$2-$D$2) -> 0 | BR65: =BR11*($EF65-$EG65)/30*(BR$2-$D$2) -> 0 | BS65: =BS11*($EF65-$EG65)/30*(BS$2-$D$2) -> 0 | BT65: =BT11*($EF65-$EG65)/30*(BT$2-$D$2) -> 0 | BU65: =BU11*($EF65-$EG65)/30*(BU$2-$D$2) -> 0 | BV65: =BV11*($EF65-$EG65)/30*(BV$2-$D$2) -> 0 | BW65: =BW11*($EF65-$EG65)/30*(BW$2-$D$2) -> 0 | ... CT65: =CT11*($EF65-$EG65)/30*(CT$2-$D$2) -> 0 | CV65: =CV11*($EF65-$EG65)/30*(CV$2-$D$2) -> 0 | CW65: =CW11*($EF65-$EG65)/30*(CW$2-$D$2) -> 0 | CX65: =CX11*($EF65-$EG65)/30*(CX$2-$D$2) -> 0 | CY65: =CY11*($EF65-$EG65)/30*(CY$2-$D$2) -> 0 | CZ65: =CZ11*($EF65-$EG65)/30*(CZ$2-$D$2) -> 0 | DA65: =DA11*($EF65-$EG65)/30*(DA$2-$D$2) -> 0 | DB65: =DB11*($EF65-$EG65)/30*(DB$2-$D$2) -> 0 | DC65: =DC11*($EF65-$EG65)/30*(DC$2-$D$2) -> 0 | ... DZ65: =DZ11*($EF65-$EG65)/30*(DZ$2-$D$2) -> 0 | EF65: 5.2 | EG65: 0 | EM65: BPW
B66: =B40 -> MaaS | C66: mT CO2eq | D66: =D12*($EF66-$EG66)/30*(D$2-$D$2) -> 0 | E66: =E12*($EF66-$EG66)/30*(E$2-$D$2) -> 0 | F66: =F12*($EF66-$EG66)/30*(F$2-$D$2) -> 0 | G66: =G12*($EF66-$EG66)/30*(G$2-$D$2) -> 0 | H66: =H12*($EF66-$EG66)/30*(H$2-$D$2) -> 0 | I66: =I12*($EF66-$EG66)/30*(I$2-$D$2) -> 0 | J66: =J12*($EF66-$EG66)/30*(J$2-$D$2) -> 0 | K66: =K12*($EF66-$EG66)/30*(K$2-$D$2) -> 0 | ... AH66: =AH12*($EF66-$EG66)/30*(AH$2-$D$2) -> 0 | AJ66: =AJ12*($EF66-$EG66)/30*(AJ$2-$D$2) -> 0 | AK66: =AK12*($EF66-$EG66)/30*(AK$2-$D$2) -> 0 | AL66: =AL12*($EF66-$EG66)/30*(AL$2-$D$2) -> 0 | AM66: =AM12*($EF66-$EG66)/30*(AM$2-$D$2) -> 0 | AN66: =AN12*($EF66-$EG66)/30*(AN$2-$D$2) -> 0 | AO66: =AO12*($EF66-$EG66)/30*(AO$2-$D$2) -> 0 | AP66: =AP12*($EF66-$EG66)/30*(AP$2-$D$2) -> 0 | AQ66: =AQ12*($EF66-$EG66)/30*(AQ$2-$D$2) -> 0 | ... BN66: =BN12*($EF66-$EG66)/30*(BN$2-$D$2) -> 0 | BP66: =BP12*($EF66-$EG66)/30*(BP$2-$D$2) -> 0 | BQ66: =BQ12*($EF66-$EG66)/30*(BQ$2-$D$2) -> 0 | BR66: =BR12*($EF66-$EG66)/30*(BR$2-$D$2) -> 0 | BS66: =BS12*($EF66-$EG66)/30*(BS$2-$D$2) -> 0 | BT66: =BT12*($EF66-$EG66)/30*(BT$2-$D$2) -> 0 | BU66: =BU12*($EF66-$EG66)/30*(BU$2-$D$2) -> 0 | BV66: =BV12*($EF66-$EG66)/30*(BV$2-$D$2) -> 0 | BW66: =BW12*($EF66-$EG66)/30*(BW$2-$D$2) -> 0 | ... CT66: =CT12*($EF66-$EG66)/30*(CT$2-$D$2) -> 0 | CV66: =CV12*($EF66-$EG66)/30*(CV$2-$D$2) -> 0 | CW66: =CW12*($EF66-$EG66)/30*(CW$2-$D$2) -> 0 | CX66: =CX12*($EF66-$EG66)/30*(CX$2-$D$2) -> 0 | CY66: =CY12*($EF66-$EG66)/30*(CY$2-$D$2) -> 0 | CZ66: =CZ12*($EF66-$EG66)/30*(CZ$2-$D$2) -> 0 | DA66: =DA12*($EF66-$EG66)/30*(DA$2-$D$2) -> 0 | DB66: =DB12*($EF66-$EG66)/30*(DB$2-$D$2) -> 0 | DC66: =DC12*($EF66-$EG66)/30*(DC$2-$D$2) -> 0 | ... DZ66: =DZ12*($EF66-$EG66)/30*(DZ$2-$D$2) -> 0 | EF66: 1 | EG66: 0
B67: =B41 -> Vehicle life extension | C67: mT CO2eq | D67: =D13*($EF67-$EG67)/30*(D$2-$D$2) -> 0 | E67: =E13*($EF67-$EG67)/30*(E$2-$D$2) -> 0 | F67: =F13*($EF67-$EG67)/30*(F$2-$D$2) -> 0 | G67: =G13*($EF67-$EG67)/30*(G$2-$D$2) -> 0 | H67: =H13*($EF67-$EG67)/30*(H$2-$D$2) -> 0 | I67: =I13*($EF67-$EG67)/30*(I$2-$D$2) -> 0 | J67: =J13*($EF67-$EG67)/30*(J$2-$D$2) -> 0 | K67: =K13*($EF67-$EG67)/30*(K$2-$D$2) -> 0 | ... AH67: =AH13*($EF67-$EG67)/30*(AH$2-$D$2) -> 0 | AJ67: =AJ13*($EF67-$EG67)/30*(AJ$2-$D$2) -> 0 | AK67: =AK13*($EF67-$EG67)/30*(AK$2-$D$2) -> 0 | AL67: =AL13*($EF67-$EG67)/30*(AL$2-$D$2) -> 0 | AM67: =AM13*($EF67-$EG67)/30*(AM$2-$D$2) -> 0 | AN67: =AN13*($EF67-$EG67)/30*(AN$2-$D$2) -> 0 | AO67: =AO13*($EF67-$EG67)/30*(AO$2-$D$2) -> 0 | AP67: =AP13*($EF67-$EG67)/30*(AP$2-$D$2) -> 0 | AQ67: =AQ13*($EF67-$EG67)/30*(AQ$2-$D$2) -> 0 | ... BN67: =BN13*($EF67-$EG67)/30*(BN$2-$D$2) -> 0 | BP67: =BP13*($EF67-$EG67)/30*(BP$2-$D$2) -> 0 | BQ67: =BQ13*($EF67-$EG67)/30*(BQ$2-$D$2) -> 0 | BR67: =BR13*($EF67-$EG67)/30*(BR$2-$D$2) -> 0 | BS67: =BS13*($EF67-$EG67)/30*(BS$2-$D$2) -> 0 | BT67: =BT13*($EF67-$EG67)/30*(BT$2-$D$2) -> 0 | BU67: =BU13*($EF67-$EG67)/30*(BU$2-$D$2) -> 0 | BV67: =BV13*($EF67-$EG67)/30*(BV$2-$D$2) -> 0 | BW67: =BW13*($EF67-$EG67)/30*(BW$2-$D$2) -> 0 | ... CT67: =CT13*($EF67-$EG67)/30*(CT$2-$D$2) -> 0 | CV67: =CV13*($EF67-$EG67)/30*(CV$2-$D$2) -> 0 | CW67: =CW13*($EF67-$EG67)/30*(CW$2-$D$2) -> 0 | CX67: =CX13*($EF67-$EG67)/30*(CX$2-$D$2) -> 0 | CY67: =CY13*($EF67-$EG67)/30*(CY$2-$D$2) -> 0 | CZ67: =CZ13*($EF67-$EG67)/30*(CZ$2-$D$2) -> 0 | DA67: =DA13*($EF67-$EG67)/30*(DA$2-$D$2) -> 0 | DB67: =DB13*($EF67-$EG67)/30*(DB$2-$D$2) -> 0 | DC67: =DC13*($EF67-$EG67)/30*(DC$2-$D$2) -> 0 | ... DZ67: =DZ13*($EF67-$EG67)/30*(DZ$2-$D$2) -> 0 | EF67: 1 | EG67: 0
B68: =B42 -> Building reduction | C68: mT CO2eq | D68: =D14*($EF68-$EG68)/30*(D$2-$D$2) -> 0 | E68: =E14*($EF68-$EG68)/30*(E$2-$D$2) -> 0 | F68: =F14*($EF68-$EG68)/30*(F$2-$D$2) -> 0 | G68: =G14*($EF68-$EG68)/30*(G$2-$D$2) -> 0 | H68: =H14*($EF68-$EG68)/30*(H$2-$D$2) -> 0 | I68: =I14*($EF68-$EG68)/30*(I$2-$D$2) -> 0 | J68: =J14*($EF68-$EG68)/30*(J$2-$D$2) -> 0 | K68: =K14*($EF68-$EG68)/30*(K$2-$D$2) -> 0 | ... AH68: =AH14*($EF68-$EG68)/30*(AH$2-$D$2) -> 0 | AJ68: =AJ14*($EF68-$EG68)/30*(AJ$2-$D$2) -> 0 | AK68: =AK14*($EF68-$EG68)/30*(AK$2-$D$2) -> 0 | AL68: =AL14*($EF68-$EG68)/30*(AL$2-$D$2) -> 0 | AM68: =AM14*($EF68-$EG68)/30*(AM$2-$D$2) -> 0 | AN68: =AN14*($EF68-$EG68)/30*(AN$2-$D$2) -> 0 | AO68: =AO14*($EF68-$EG68)/30*(AO$2-$D$2) -> 0 | AP68: =AP14*($EF68-$EG68)/30*(AP$2-$D$2) -> 0 | AQ68: =AQ14*($EF68-$EG68)/30*(AQ$2-$D$2) -> 0 | ... BN68: =BN14*($EF68-$EG68)/30*(BN$2-$D$2) -> 0 | BP68: =BP14*($EF68-$EG68)/30*(BP$2-$D$2) -> 0 | BQ68: =BQ14*($EF68-$EG68)/30*(BQ$2-$D$2) -> 0 | BR68: =BR14*($EF68-$EG68)/30*(BR$2-$D$2) -> 0 | BS68: =BS14*($EF68-$EG68)/30*(BS$2-$D$2) -> 0 | BT68: =BT14*($EF68-$EG68)/30*(BT$2-$D$2) -> 0 | BU68: =BU14*($EF68-$EG68)/30*(BU$2-$D$2) -> 0 | BV68: =BV14*($EF68-$EG68)/30*(BV$2-$D$2) -> 0 | BW68: =BW14*($EF68-$EG68)/30*(BW$2-$D$2) -> 0 | ... CT68: =CT14*($EF68-$EG68)/30*(CT$2-$D$2) -> 0 | CV68: =CV14*($EF68-$EG68)/30*(CV$2-$D$2) -> 0 | CW68: =CW14*($EF68-$EG68)/30*(CW$2-$D$2) -> 0 | CX68: =CX14*($EF68-$EG68)/30*(CX$2-$D$2) -> 0 | CY68: =CY14*($EF68-$EG68)/30*(CY$2-$D$2) -> 0 | CZ68: =CZ14*($EF68-$EG68)/30*(CZ$2-$D$2) -> 0 | DA68: =DA14*($EF68-$EG68)/30*(DA$2-$D$2) -> 0 | DB68: =DB14*($EF68-$EG68)/30*(DB$2-$D$2) -> 0 | DC68: =DC14*($EF68-$EG68)/30*(DC$2-$D$2) -> 0 | ... DZ68: =DZ14*($EF68-$EG68)/30*(DZ$2-$D$2) -> 0 | EF68: 0 | EG68: 0 | EM68: BPW
B69: =B43 -> Building substitution | C69: mT CO2eq | D69: =D15*($EF69-$EG69)/30*(D$2-$D$2) -> 0 | E69: =E15*($EF69-$EG69)/30*(E$2-$D$2) -> 0 | F69: =F15*($EF69-$EG69)/30*(F$2-$D$2) -> 0 | G69: =G15*($EF69-$EG69)/30*(G$2-$D$2) -> 0 | H69: =H15*($EF69-$EG69)/30*(H$2-$D$2) -> 0 | I69: =I15*($EF69-$EG69)/30*(I$2-$D$2) -> 0 | J69: =J15*($EF69-$EG69)/30*(J$2-$D$2) -> 0 | K69: =K15*($EF69-$EG69)/30*(K$2-$D$2) -> 0 | ... AH69: =AH15*($EF69-$EG69)/30*(AH$2-$D$2) -> 0 | AJ69: =AJ15*($EF69-$EG69)/30*(AJ$2-$D$2) -> 0 | AK69: =AK15*($EF69-$EG69)/30*(AK$2-$D$2) -> 0 | AL69: =AL15*($EF69-$EG69)/30*(AL$2-$D$2) -> 0 | AM69: =AM15*($EF69-$EG69)/30*(AM$2-$D$2) -> 0 | AN69: =AN15*($EF69-$EG69)/30*(AN$2-$D$2) -> 0 | AO69: =AO15*($EF69-$EG69)/30*(AO$2-$D$2) -> 0 | AP69: =AP15*($EF69-$EG69)/30*(AP$2-$D$2) -> 0 | AQ69: =AQ15*($EF69-$EG69)/30*(AQ$2-$D$2) -> 0 | ... BN69: =BN15*($EF69-$EG69)/30*(BN$2-$D$2) -> 0 | BP69: =BP15*($EF69-$EG69)/30*(BP$2-$D$2) -> 0 | BQ69: =BQ15*($EF69-$EG69)/30*(BQ$2-$D$2) -> 0 | BR69: =BR15*($EF69-$EG69)/30*(BR$2-$D$2) -> 0 | BS69: =BS15*($EF69-$EG69)/30*(BS$2-$D$2) -> 0 | BT69: =BT15*($EF69-$EG69)/30*(BT$2-$D$2) -> 0 | BU69: =BU15*($EF69-$EG69)/30*(BU$2-$D$2) -> 0 | BV69: =BV15*($EF69-$EG69)/30*(BV$2-$D$2) -> 0 | BW69: =BW15*($EF69-$EG69)/30*(BW$2-$D$2) -> 0 | ... CT69: =CT15*($EF69-$EG69)/30*(CT$2-$D$2) -> 0 | CV69: =CV15*($EF69-$EG69)/30*(CV$2-$D$2) -> 0 | CW69: =CW15*($EF69-$EG69)/30*(CW$2-$D$2) -> 0 | CX69: =CX15*($EF69-$EG69)/30*(CX$2-$D$2) -> 0 | CY69: =CY15*($EF69-$EG69)/30*(CY$2-$D$2) -> 0 | CZ69: =CZ15*($EF69-$EG69)/30*(CZ$2-$D$2) -> 0 | DA69: =DA15*($EF69-$EG69)/30*(DA$2-$D$2) -> 0 | DB69: =DB15*($EF69-$EG69)/30*(DB$2-$D$2) -> 0 | DC69: =DC15*($EF69-$EG69)/30*(DC$2-$D$2) -> 0 | ... DZ69: =DZ15*($EF69-$EG69)/30*(DZ$2-$D$2) -> 0 | EF69: 2.5 | EG69: 0 | EM69: BPW
B70: =B44 -> Apparel - waste reduction | C70: mT CO2eq | D70: =D16*($EF70-$EG70)/30*(D$2-$D$2) -> 0 | E70: =E16*($EF70-$EG70)/30*(E$2-$D$2) -> 0 | F70: =F16*($EF70-$EG70)/30*(F$2-$D$2) -> 0 | G70: =G16*($EF70-$EG70)/30*(G$2-$D$2) -> 0 | H70: =H16*($EF70-$EG70)/30*(H$2-$D$2) -> 0 | I70: =I16*($EF70-$EG70)/30*(I$2-$D$2) -> 0 | J70: =J16*($EF70-$EG70)/30*(J$2-$D$2) -> 0 | K70: =K16*($EF70-$EG70)/30*(K$2-$D$2) -> 0 | ... AH70: =AH16*($EF70-$EG70)/30*(AH$2-$D$2) -> 0 | AJ70: =AJ16*($EF70-$EG70)/30*(AJ$2-$D$2) -> 0 | AK70: =AK16*($EF70-$EG70)/30*(AK$2-$D$2) -> 0 | AL70: =AL16*($EF70-$EG70)/30*(AL$2-$D$2) -> 0 | AM70: =AM16*($EF70-$EG70)/30*(AM$2-$D$2) -> 0 | AN70: =AN16*($EF70-$EG70)/30*(AN$2-$D$2) -> 0 | AO70: =AO16*($EF70-$EG70)/30*(AO$2-$D$2) -> 0 | AP70: =AP16*($EF70-$EG70)/30*(AP$2-$D$2) -> 0 | AQ70: =AQ16*($EF70-$EG70)/30*(AQ$2-$D$2) -> 0 | ... BN70: =BN16*($EF70-$EG70)/30*(BN$2-$D$2) -> 0 | BP70: =BP16*($EF70-$EG70)/30*(BP$2-$D$2) -> 0 | BQ70: =BQ16*($EF70-$EG70)/30*(BQ$2-$D$2) -> 0 | BR70: =BR16*($EF70-$EG70)/30*(BR$2-$D$2) -> 0 | BS70: =BS16*($EF70-$EG70)/30*(BS$2-$D$2) -> 0 | BT70: =BT16*($EF70-$EG70)/30*(BT$2-$D$2) -> 0 | BU70: =BU16*($EF70-$EG70)/30*(BU$2-$D$2) -> 0 | BV70: =BV16*($EF70-$EG70)/30*(BV$2-$D$2) -> 0 | BW70: =BW16*($EF70-$EG70)/30*(BW$2-$D$2) -> 0 | ... CT70: =CT16*($EF70-$EG70)/30*(CT$2-$D$2) -> 0 | CV70: =CV16*($EF70-$EG70)/30*(CV$2-$D$2) -> 0 | CW70: =CW16*($EF70-$EG70)/30*(CW$2-$D$2) -> 0 | CX70: =CX16*($EF70-$EG70)/30*(CX$2-$D$2) -> 0 | CY70: =CY16*($EF70-$EG70)/30*(CY$2-$D$2) -> 0 | CZ70: =CZ16*($EF70-$EG70)/30*(CZ$2-$D$2) -> 0 | DA70: =DA16*($EF70-$EG70)/30*(DA$2-$D$2) -> 0 | DB70: =DB16*($EF70-$EG70)/30*(DB$2-$D$2) -> 0 | DC70: =DC16*($EF70-$EG70)/30*(DC$2-$D$2) -> 0 | ... DZ70: =DZ16*($EF70-$EG70)/30*(DZ$2-$D$2) -> 0 | EF70: 0 | EG70: 0 | EM70: BPW
B71: =B45 -> Apparel - NBM | C71: mT CO2eq | D71: =D17*($EF71-$EG71)/30*(D$2-$D$2) -> 0 | E71: =E17*($EF71-$EG71)/30*(E$2-$D$2) -> 0 | F71: =F17*($EF71-$EG71)/30*(F$2-$D$2) -> 0 | G71: =G17*($EF71-$EG71)/30*(G$2-$D$2) -> 0 | H71: =H17*($EF71-$EG71)/30*(H$2-$D$2) -> 0 | I71: =I17*($EF71-$EG71)/30*(I$2-$D$2) -> 0 | J71: =J17*($EF71-$EG71)/30*(J$2-$D$2) -> 0 | K71: =K17*($EF71-$EG71)/30*(K$2-$D$2) -> 0 | ... AH71: =AH17*($EF71-$EG71)/30*(AH$2-$D$2) -> 0 | AJ71: =AJ17*($EF71-$EG71)/30*(AJ$2-$D$2) -> 0 | AK71: =AK17*($EF71-$EG71)/30*(AK$2-$D$2) -> 0 | AL71: =AL17*($EF71-$EG71)/30*(AL$2-$D$2) -> 0 | AM71: =AM17*($EF71-$EG71)/30*(AM$2-$D$2) -> 0 | AN71: =AN17*($EF71-$EG71)/30*(AN$2-$D$2) -> 0 | AO71: =AO17*($EF71-$EG71)/30*(AO$2-$D$2) -> 0 | AP71: =AP17*($EF71-$EG71)/30*(AP$2-$D$2) -> 0 | AQ71: =AQ17*($EF71-$EG71)/30*(AQ$2-$D$2) -> 0 | ... BN71: =BN17*($EF71-$EG71)/30*(BN$2-$D$2) -> 0 | BP71: =BP17*($EF71-$EG71)/30*(BP$2-$D$2) -> 0 | BQ71: =BQ17*($EF71-$EG71)/30*(BQ$2-$D$2) -> 0 | BR71: =BR17*($EF71-$EG71)/30*(BR$2-$D$2) -> 0 | BS71: =BS17*($EF71-$EG71)/30*(BS$2-$D$2) -> 0 | BT71: =BT17*($EF71-$EG71)/30*(BT$2-$D$2) -> 0 | BU71: =BU17*($EF71-$EG71)/30*(BU$2-$D$2) -> 0 | BV71: =BV17*($EF71-$EG71)/30*(BV$2-$D$2) -> 0 | BW71: =BW17*($EF71-$EG71)/30*(BW$2-$D$2) -> 0 | ... CT71: =CT17*($EF71-$EG71)/30*(CT$2-$D$2) -> 0 | CV71: =CV17*($EF71-$EG71)/30*(CV$2-$D$2) -> 0 | CW71: =CW17*($EF71-$EG71)/30*(CW$2-$D$2) -> 0 | CX71: =CX17*($EF71-$EG71)/30*(CX$2-$D$2) -> 0 | CY71: =CY17*($EF71-$EG71)/30*(CY$2-$D$2) -> 0 | CZ71: =CZ17*($EF71-$EG71)/30*(CZ$2-$D$2) -> 0 | DA71: =DA17*($EF71-$EG71)/30*(DA$2-$D$2) -> 0 | DB71: =DB17*($EF71-$EG71)/30*(DB$2-$D$2) -> 0 | DC71: =DC17*($EF71-$EG71)/30*(DC$2-$D$2) -> 0 | ... DZ71: =DZ17*($EF71-$EG71)/30*(DZ$2-$D$2) -> 0 | EF71: =EF63 -> 3.05 | EG71: 0 | EM71: BPW
B72: =B46 -> Apparel - substitution | C72: mT CO2eq | D72: =D18*($EF72-$EG72)/30*(D$2-$D$2) -> 0 | E72: =E18*($EF72-$EG72)/30*(E$2-$D$2) -> 0 | F72: =F18*($EF72-$EG72)/30*(F$2-$D$2) -> 0 | G72: =G18*($EF72-$EG72)/30*(G$2-$D$2) -> 0 | H72: =H18*($EF72-$EG72)/30*(H$2-$D$2) -> 0 | I72: =I18*($EF72-$EG72)/30*(I$2-$D$2) -> 0 | J72: =J18*($EF72-$EG72)/30*(J$2-$D$2) -> 0 | K72: =K18*($EF72-$EG72)/30*(K$2-$D$2) -> 0 | ... AH72: =AH18*($EF72-$EG72)/30*(AH$2-$D$2) -> 0 | AJ72: =AJ18*($EF72-$EG72)/30*(AJ$2-$D$2) -> 0 | AK72: =AK18*($EF72-$EG72)/30*(AK$2-$D$2) -> 0 | AL72: =AL18*($EF72-$EG72)/30*(AL$2-$D$2) -> 0 | AM72: =AM18*($EF72-$EG72)/30*(AM$2-$D$2) -> 0 | AN72: =AN18*($EF72-$EG72)/30*(AN$2-$D$2) -> 0 | AO72: =AO18*($EF72-$EG72)/30*(AO$2-$D$2) -> 0 | AP72: =AP18*($EF72-$EG72)/30*(AP$2-$D$2) -> 0 | AQ72: =AQ18*($EF72-$EG72)/30*(AQ$2-$D$2) -> 0 | ... BN72: =BN18*($EF72-$EG72)/30*(BN$2-$D$2) -> 0 | BP72: =BP18*($EF72-$EG72)/30*(BP$2-$D$2) -> 0 | BQ72: =BQ18*($EF72-$EG72)/30*(BQ$2-$D$2) -> 0 | BR72: =BR18*($EF72-$EG72)/30*(BR$2-$D$2) -> 0 | BS72: =BS18*($EF72-$EG72)/30*(BS$2-$D$2) -> 0 | BT72: =BT18*($EF72-$EG72)/30*(BT$2-$D$2) -> 0 | BU72: =BU18*($EF72-$EG72)/30*(BU$2-$D$2) -> 0 | BV72: =BV18*($EF72-$EG72)/30*(BV$2-$D$2) -> 0 | BW72: =BW18*($EF72-$EG72)/30*(BW$2-$D$2) -> 0 | ... CT72: =CT18*($EF72-$EG72)/30*(CT$2-$D$2) -> 0 | CV72: =CV18*($EF72-$EG72)/30*(CV$2-$D$2) -> 0 | CW72: =CW18*($EF72-$EG72)/30*(CW$2-$D$2) -> 0 | CX72: =CX18*($EF72-$EG72)/30*(CX$2-$D$2) -> 0 | CY72: =CY18*($EF72-$EG72)/30*(CY$2-$D$2) -> 0 | CZ72: =CZ18*($EF72-$EG72)/30*(CZ$2-$D$2) -> 0 | DA72: =DA18*($EF72-$EG72)/30*(DA$2-$D$2) -> 0 | DB72: =DB18*($EF72-$EG72)/30*(DB$2-$D$2) -> 0 | DC72: =DC18*($EF72-$EG72)/30*(DC$2-$D$2) -> 0 | ... DZ72: =DZ18*($EF72-$EG72)/30*(DZ$2-$D$2) -> 0 | EF72: =EF65 -> 5.2 | EG72: 0 | EM72: BPW
B73: =B47 -> Others Reduction | C73: mT CO2eq | D73: =D19*($EF73-$EG73)/30*(D$2-$D$2) -> 0 | E73: =E19*($EF73-$EG73)/30*(E$2-$D$2) -> 0 | F73: =F19*($EF73-$EG73)/30*(F$2-$D$2) -> 0 | G73: =G19*($EF73-$EG73)/30*(G$2-$D$2) -> 0 | H73: =H19*($EF73-$EG73)/30*(H$2-$D$2) -> 0 | I73: =I19*($EF73-$EG73)/30*(I$2-$D$2) -> 0 | J73: =J19*($EF73-$EG73)/30*(J$2-$D$2) -> 0 | K73: =K19*($EF73-$EG73)/30*(K$2-$D$2) -> 0 | ... AH73: =AH19*($EF73-$EG73)/30*(AH$2-$D$2) -> 0 | AJ73: =AJ19*($EF73-$EG73)/30*(AJ$2-$D$2) -> 0 | AK73: =AK19*($EF73-$EG73)/30*(AK$2-$D$2) -> 0 | AL73: =AL19*($EF73-$EG73)/30*(AL$2-$D$2) -> 0 | AM73: =AM19*($EF73-$EG73)/30*(AM$2-$D$2) -> 0 | AN73: =AN19*($EF73-$EG73)/30*(AN$2-$D$2) -> 0 | AO73: =AO19*($EF73-$EG73)/30*(AO$2-$D$2) -> 0 | AP73: =AP19*($EF73-$EG73)/30*(AP$2-$D$2) -> 0 | AQ73: =AQ19*($EF73-$EG73)/30*(AQ$2-$D$2) -> 0 | ... BN73: =BN19*($EF73-$EG73)/30*(BN$2-$D$2) -> 0 | BP73: =BP19*($EF73-$EG73)/30*(BP$2-$D$2) -> 0 | BQ73: =BQ19*($EF73-$EG73)/30*(BQ$2-$D$2) -> 0 | BR73: =BR19*($EF73-$EG73)/30*(BR$2-$D$2) -> 0 | BS73: =BS19*($EF73-$EG73)/30*(BS$2-$D$2) -> 0 | BT73: =BT19*($EF73-$EG73)/30*(BT$2-$D$2) -> 0 | BU73: =BU19*($EF73-$EG73)/30*(BU$2-$D$2) -> 0 | BV73: =BV19*($EF73-$EG73)/30*(BV$2-$D$2) -> 0 | BW73: =BW19*($EF73-$EG73)/30*(BW$2-$D$2) -> 0 | ... CT73: =CT19*($EF73-$EG73)/30*(CT$2-$D$2) -> 0 | CV73: =CV19*($EF73-$EG73)/30*(CV$2-$D$2) -> 0 | CW73: =CW19*($EF73-$EG73)/30*(CW$2-$D$2) -> 0 | CX73: =CX19*($EF73-$EG73)/30*(CX$2-$D$2) -> 0 | CY73: =CY19*($EF73-$EG73)/30*(CY$2-$D$2) -> 0 | CZ73: =CZ19*($EF73-$EG73)/30*(CZ$2-$D$2) -> 0 | DA73: =DA19*($EF73-$EG73)/30*(DA$2-$D$2) -> 0 | DB73: =DB19*($EF73-$EG73)/30*(DB$2-$D$2) -> 0 | DC73: =DC19*($EF73-$EG73)/30*(DC$2-$D$2) -> 0 | ... DZ73: =DZ19*($EF73-$EG73)/30*(DZ$2-$D$2) -> 0 | EF73: 0 | EG73: 0 | EM73: BPW
B74: =B48 -> Others Substitution | C74: mT CO2eq | D74: =D20*($EF74-$EG74)/30*(D$2-$D$2) -> 0 | E74: =E20*($EF74-$EG74)/30*(E$2-$D$2) -> 0 | F74: =F20*($EF74-$EG74)/30*(F$2-$D$2) -> 0 | G74: =G20*($EF74-$EG74)/30*(G$2-$D$2) -> 0 | H74: =H20*($EF74-$EG74)/30*(H$2-$D$2) -> 0 | I74: =I20*($EF74-$EG74)/30*(I$2-$D$2) -> 0 | J74: =J20*($EF74-$EG74)/30*(J$2-$D$2) -> 0 | K74: =K20*($EF74-$EG74)/30*(K$2-$D$2) -> 0 | ... AH74: =AH20*($EF74-$EG74)/30*(AH$2-$D$2) -> 0 | AJ74: =AJ20*($EF74-$EG74)/30*(AJ$2-$D$2) -> 0 | AK74: =AK20*($EF74-$EG74)/30*(AK$2-$D$2) -> 0 | AL74: =AL20*($EF74-$EG74)/30*(AL$2-$D$2) -> 0 | AM74: =AM20*($EF74-$EG74)/30*(AM$2-$D$2) -> 0 | AN74: =AN20*($EF74-$EG74)/30*(AN$2-$D$2) -> 0 | AO74: =AO20*($EF74-$EG74)/30*(AO$2-$D$2) -> 0 | AP74: =AP20*($EF74-$EG74)/30*(AP$2-$D$2) -> 0 | AQ74: =AQ20*($EF74-$EG74)/30*(AQ$2-$D$2) -> 0 | ... BN74: =BN20*($EF74-$EG74)/30*(BN$2-$D$2) -> 0 | BP74: =BP20*($EF74-$EG74)/30*(BP$2-$D$2) -> 0 | BQ74: =BQ20*($EF74-$EG74)/30*(BQ$2-$D$2) -> 0 | BR74: =BR20*($EF74-$EG74)/30*(BR$2-$D$2) -> 0 | BS74: =BS20*($EF74-$EG74)/30*(BS$2-$D$2) -> 0 | BT74: =BT20*($EF74-$EG74)/30*(BT$2-$D$2) -> 0 | BU74: =BU20*($EF74-$EG74)/30*(BU$2-$D$2) -> 0 | BV74: =BV20*($EF74-$EG74)/30*(BV$2-$D$2) -> 0 | BW74: =BW20*($EF74-$EG74)/30*(BW$2-$D$2) -> 0 | ... CT74: =CT20*($EF74-$EG74)/30*(CT$2-$D$2) -> 0 | CV74: =CV20*($EF74-$EG74)/30*(CV$2-$D$2) -> 0 | CW74: =CW20*($EF74-$EG74)/30*(CW$2-$D$2) -> 0 | CX74: =CX20*($EF74-$EG74)/30*(CX$2-$D$2) -> 0 | CY74: =CY20*($EF74-$EG74)/30*(CY$2-$D$2) -> 0 | CZ74: =CZ20*($EF74-$EG74)/30*(CZ$2-$D$2) -> 0 | DA74: =DA20*($EF74-$EG74)/30*(DA$2-$D$2) -> 0 | DB74: =DB20*($EF74-$EG74)/30*(DB$2-$D$2) -> 0 | DC74: =DC20*($EF74-$EG74)/30*(DC$2-$D$2) -> 0 | ... DZ74: =DZ20*($EF74-$EG74)/30*(DZ$2-$D$2) -> 0 | EF74: =AVERAGE(EF64:EF65) -> 3.85 | EG74: 0 | EM74: BPW
A75: Additonal CO2 emissions from circular levers | C75: mT CO2eq | D75: =SUM(D61:D74) -> 0 | E75: =SUM(E61:E74) -> 0 | F75: =SUM(F61:F74) -> 0 | G75: =SUM(G61:G74) -> 0 | H75: =SUM(H61:H74) -> 0 | I75: =SUM(I61:I74) -> 0 | J75: =SUM(J61:J74) -> 0 | K75: =SUM(K61:K74) -> 0 | ... AH75: =SUM(AH61:AH74) -> 0 | AJ75: =SUM(AJ61:AJ74) -> 0 | AK75: =SUM(AK61:AK74) -> 0 | AL75: =SUM(AL61:AL74) -> 0 | AM75: =SUM(AM61:AM74) -> 0 | AN75: =SUM(AN61:AN74) -> 0 | AO75: =SUM(AO61:AO74) -> 0 | AP75: =SUM(AP61:AP74) -> 0 | AQ75: =SUM(AQ61:AQ74) -> 0 | ... BN75: =SUM(BN61:BN74) -> 0 | BP75: =SUM(BP61:BP74) -> 0 | BQ75: =SUM(BQ61:BQ74) -> 0 | BR75: =SUM(BR61:BR74) -> 0 | BS75: =SUM(BS61:BS74) -> 0 | BT75: =SUM(BT61:BT74) -> 0 | BU75: =SUM(BU61:BU74) -> 0 | BV75: =SUM(BV61:BV74) -> 0 | BW75: =SUM(BW61:BW74) -> 0 | ... CT75: =SUM(CT61:CT74) -> 0 | CV75: =SUM(CV61:CV74) -> 0 | CW75: =SUM(CW61:CW74) -> 0 | CX75: =SUM(CX61:CX74) -> 0 | CY75: =SUM(CY61:CY74) -> 0 | CZ75: =SUM(CZ61:CZ74) -> 0 | DA75: =SUM(DA61:DA74) -> 0 | DB75: =SUM(DB61:DB74) -> 0 | DC75: =SUM(DC61:DC74) -> 0 | ... DZ75: =SUM(DZ61:DZ74) -> 0
A77: Annualized CAPEX | EF77: 2020 | EK77: $/T | EM77: Source
B78: =B7 -> Fuel additive elimination | C78: m$ | D78: =D7*$EF78 -> 0 | E78: =E7*$EF78 -> 0 | F78: =F7*$EF78 -> 0 | G78: =G7*$EF78 -> 0 | H78: =H7*$EF78 -> 0 | I78: =I7*$EF78 -> 0 | J78: =J7*$EF78 -> 0 | K78: =K7*$EF78 -> 0 | ... AH78: =AH7*$EF78 -> 0 | AJ78: =AJ7*$EF78 -> 0 | AK78: =AK7*$EF78 -> 0 | AL78: =AL7*$EF78 -> 0 | AM78: =AM7*$EF78 -> 0 | AN78: =AN7*$EF78 -> 0 | AO78: =AO7*$EF78 -> 0 | AP78: =AP7*$EF78 -> 0 | AQ78: =AQ7*$EF78 -> 0 | ... BN78: =BN7*$EF78 -> 0 | BP78: =BP7*$EF78 -> 0 | BQ78: =BQ7*$EF78 -> 0 | BR78: =BR7*$EF78 -> 0 | BS78: =BS7*$EF78 -> 0 | BT78: =BT7*$EF78 -> 0 | BU78: =BU7*$EF78 -> 0 | BV78: =BV7*$EF78 -> 0 | BW78: =BW7*$EF78 -> 0 | ... CT78: =CT7*$EF78 -> 0 | CV78: =CV7*$EF78 -> 0 | CW78: =CW7*$EF78 -> 0 | CX78: =CX7*$EF78 -> 0 | CY78: =CY7*$EF78 -> 0 | CZ78: =CZ7*$EF78 -> 0 | DA78: =DA7*$EF78 -> 0 | DB78: =DB7*$EF78 -> 0 | DC78: =DC7*$EF78 -> 0 | ... DZ78: =DZ7*$EF78 -> 0 | EF78: 0 | EM78: None
B79: =B8 -> Packaging reduction | C79: m$ | D79: =D8*$EF79 -> 0 | E79: =E8*$EF79 -> 0 | F79: =F8*$EF79 -> 0 | G79: =G8*$EF79 -> 0 | H79: =H8*$EF79 -> 0 | I79: =I8*$EF79 -> 0 | J79: =J8*$EF79 -> 0 | K79: =K8*$EF79 -> 0 | ... AH79: =AH8*$EF79 -> 0 | AJ79: =AJ8*$EF79 -> 0 | AK79: =AK8*$EF79 -> 0 | AL79: =AL8*$EF79 -> 0 | AM79: =AM8*$EF79 -> 0 | AN79: =AN8*$EF79 -> 0 | AO79: =AO8*$EF79 -> 0 | AP79: =AP8*$EF79 -> 0 | AQ79: =AQ8*$EF79 -> 0 | ... BN79: =BN8*$EF79 -> 0 | BP79: =BP8*$EF79 -> 0 | BQ79: =BQ8*$EF79 -> 0 | BR79: =BR8*$EF79 -> 0 | BS79: =BS8*$EF79 -> 0 | BT79: =BT8*$EF79 -> 0 | BU79: =BU8*$EF79 -> 0 | BV79: =BV8*$EF79 -> 0 | BW79: =BW8*$EF79 -> 0 | ... CT79: =CT8*$EF79 -> 0 | CV79: =CV8*$EF79 -> 0 | CW79: =CW8*$EF79 -> 0 | CX79: =CX8*$EF79 -> 0 | CY79: =CY8*$EF79 -> 0 | CZ79: =CZ8*$EF79 -> 0 | DA79: =DA8*$EF79 -> 0 | DB79: =DB8*$EF79 -> 0 | DC79: =DC8*$EF79 -> 0 | ... DZ79: =DZ8*$EF79 -> 0 | EF79: 0 | EM79: BPW
B80: =B9 -> Packaging reuse | C80: m$ | D80: =D9*$EF80 -> 0 | E80: =E9*$EF80 -> 0 | F80: =F9*$EF80 -> 0 | G80: =G9*$EF80 -> 0 | H80: =H9*$EF80 -> 0 | I80: =I9*$EF80 -> 0 | J80: =J9*$EF80 -> 0 | K80: =K9*$EF80 -> 0 | ... AH80: =AH9*$EF80 -> 0 | AJ80: =AJ9*$EF80 -> 0 | AK80: =AK9*$EF80 -> 0 | AL80: =AL9*$EF80 -> 0 | AM80: =AM9*$EF80 -> 0 | AN80: =AN9*$EF80 -> 0 | AO80: =AO9*$EF80 -> 0 | AP80: =AP9*$EF80 -> 0 | AQ80: =AQ9*$EF80 -> 0 | ... BN80: =BN9*$EF80 -> 0 | BP80: =BP9*$EF80 -> 0 | BQ80: =BQ9*$EF80 -> 0 | BR80: =BR9*$EF80 -> 0 | BS80: =BS9*$EF80 -> 0 | BT80: =BT9*$EF80 -> 0 | BU80: =BU9*$EF80 -> 0 | BV80: =BV9*$EF80 -> 0 | BW80: =BW9*$EF80 -> 0 | ... CT80: =CT9*$EF80 -> 0 | CV80: =CV9*$EF80 -> 0 | CW80: =CW9*$EF80 -> 0 | CX80: =CX9*$EF80 -> 0 | CY80: =CY9*$EF80 -> 0 | CZ80: =CZ9*$EF80 -> 0 | DA80: =DA9*$EF80 -> 0 | DB80: =DB9*$EF80 -> 0 | DC80: =DC9*$EF80 -> 0 | ... DZ80: =DZ9*$EF80 -> 0 | EF80: =AVERAGE(196,322) -> 259 | EM80: BPW
B81: =B10 -> Packaging substitution Paper | C81: m$ | D81: =D10*$EF81 -> 0 | E81: =E10*$EF81 -> 0 | F81: =F10*$EF81 -> 0 | G81: =G10*$EF81 -> 0 | H81: =H10*$EF81 -> 0 | I81: =I10*$EF81 -> 0 | J81: =J10*$EF81 -> 0 | K81: =K10*$EF81 -> 0 | ... AH81: =AH10*$EF81 -> 0 | AJ81: =AJ10*$EF81 -> 0 | AK81: =AK10*$EF81 -> 0 | AL81: =AL10*$EF81 -> 0 | AM81: =AM10*$EF81 -> 0 | AN81: =AN10*$EF81 -> 0 | AO81: =AO10*$EF81 -> 0 | AP81: =AP10*$EF81 -> 0 | AQ81: =AQ10*$EF81 -> 0 | ... BN81: =BN10*$EF81 -> 0 | BP81: =BP10*$EF81 -> 0 | BQ81: =BQ10*$EF81 -> 0 | BR81: =BR10*$EF81 -> 0 | BS81: =BS10*$EF81 -> 0 | BT81: =BT10*$EF81 -> 0 | BU81: =BU10*$EF81 -> 0 | BV81: =BV10*$EF81 -> 0 | BW81: =BW10*$EF81 -> 0 | ... CT81: =CT10*$EF81 -> 0 | CV81: =CV10*$EF81 -> 0 | CW81: =CW10*$EF81 -> 0 | CX81: =CX10*$EF81 -> 0 | CY81: =CY10*$EF81 -> 0 | CZ81: =CZ10*$EF81 -> 0 | DA81: =DA10*$EF81 -> 0 | DB81: =DB10*$EF81 -> 0 | DC81: =DC10*$EF81 -> 0 | ... DZ81: =DZ10*$EF81 -> 0 | EF81: 300 | EM81: BPW
B82: =B11 -> Packaging Substitution Compostables | C82: m$ | D82: =D11*$EF82 -> 0 | E82: =E11*$EF82 -> 0 | F82: =F11*$EF82 -> 0 | G82: =G11*$EF82 -> 0 | H82: =H11*$EF82 -> 0 | I82: =I11*$EF82 -> 0 | J82: =J11*$EF82 -> 0 | K82: =K11*$EF82 -> 0 | ... AH82: =AH11*$EF82 -> 0 | AJ82: =AJ11*$EF82 -> 0 | AK82: =AK11*$EF82 -> 0 | AL82: =AL11*$EF82 -> 0 | AM82: =AM11*$EF82 -> 0 | AN82: =AN11*$EF82 -> 0 | AO82: =AO11*$EF82 -> 0 | AP82: =AP11*$EF82 -> 0 | AQ82: =AQ11*$EF82 -> 0 | ... BN82: =BN11*$EF82 -> 0 | BP82: =BP11*$EF82 -> 0 | BQ82: =BQ11*$EF82 -> 0 | BR82: =BR11*$EF82 -> 0 | BS82: =BS11*$EF82 -> 0 | BT82: =BT11*$EF82 -> 0 | BU82: =BU11*$EF82 -> 0 | BV82: =BV11*$EF82 -> 0 | BW82: =BW11*$EF82 -> 0 | ... CT82: =CT11*$EF82 -> 0 | CV82: =CV11*$EF82 -> 0 | CW82: =CW11*$EF82 -> 0 | CX82: =CX11*$EF82 -> 0 | CY82: =CY11*$EF82 -> 0 | CZ82: =CZ11*$EF82 -> 0 | DA82: =DA11*$EF82 -> 0 | DB82: =DB11*$EF82 -> 0 | DC82: =DC11*$EF82 -> 0 | ... DZ82: =DZ11*$EF82 -> 0 | EF82: 727 | EM82: BPW
B83: =B12 -> MaaS | C83: m$ | D83: =D12*$EF83 -> 0 | E83: =E12*$EF83 -> 0 | F83: =F12*$EF83 -> 0 | G83: =G12*$EF83 -> 0 | H83: =H12*$EF83 -> 0 | I83: =I12*$EF83 -> 0 | J83: =J12*$EF83 -> 0 | K83: =K12*$EF83 -> 0 | ... AH83: =AH12*$EF83 -> 0 | AJ83: =AJ12*$EF83 -> 0 | AK83: =AK12*$EF83 -> 0 | AL83: =AL12*$EF83 -> 0 | AM83: =AM12*$EF83 -> 0 | AN83: =AN12*$EF83 -> 0 | AO83: =AO12*$EF83 -> 0 | AP83: =AP12*$EF83 -> 0 | AQ83: =AQ12*$EF83 -> 0 | ... BN83: =BN12*$EF83 -> 0 | BP83: =BP12*$EF83 -> 0 | BQ83: =BQ12*$EF83 -> 0 | BR83: =BR12*$EF83 -> 0 | BS83: =BS12*$EF83 -> 0 | BT83: =BT12*$EF83 -> 0 | BU83: =BU12*$EF83 -> 0 | BV83: =BV12*$EF83 -> 0 | BW83: =BW12*$EF83 -> 0 | ... CT83: =CT12*$EF83 -> 0 | CV83: =CV12*$EF83 -> 0 | CW83: =CW12*$EF83 -> 0 | CX83: =CX12*$EF83 -> 0 | CY83: =CY12*$EF83 -> 0 | CZ83: =CZ12*$EF83 -> 0 | DA83: =DA12*$EF83 -> 0 | DB83: =DB12*$EF83 -> 0 | DC83: =DC12*$EF83 -> 0 | ... DZ83: =DZ12*$EF83 -> 0 | EF83: 100
B84: =B13 -> Vehicle life extension | C84: m$ | D84: =D13*$EF84 -> 0 | E84: =E13*$EF84 -> 0 | F84: =F13*$EF84 -> 0 | G84: =G13*$EF84 -> 0 | H84: =H13*$EF84 -> 0 | I84: =I13*$EF84 -> 0 | J84: =J13*$EF84 -> 0 | K84: =K13*$EF84 -> 0 | ... AH84: =AH13*$EF84 -> 0 | AJ84: =AJ13*$EF84 -> 0 | AK84: =AK13*$EF84 -> 0 | AL84: =AL13*$EF84 -> 0 | AM84: =AM13*$EF84 -> 0 | AN84: =AN13*$EF84 -> 0 | AO84: =AO13*$EF84 -> 0 | AP84: =AP13*$EF84 -> 0 | AQ84: =AQ13*$EF84 -> 0 | ... BN84: =BN13*$EF84 -> 0 | BP84: =BP13*$EF84 -> 0 | BQ84: =BQ13*$EF84 -> 0 | BR84: =BR13*$EF84 -> 0 | BS84: =BS13*$EF84 -> 0 | BT84: =BT13*$EF84 -> 0 | BU84: =BU13*$EF84 -> 0 | BV84: =BV13*$EF84 -> 0 | BW84: =BW13*$EF84 -> 0 | ... CT84: =CT13*$EF84 -> 0 | CV84: =CV13*$EF84 -> 0 | CW84: =CW13*$EF84 -> 0 | CX84: =CX13*$EF84 -> 0 | CY84: =CY13*$EF84 -> 0 | CZ84: =CZ13*$EF84 -> 0 | DA84: =DA13*$EF84 -> 0 | DB84: =DB13*$EF84 -> 0 | DC84: =DC13*$EF84 -> 0 | ... DZ84: =DZ13*$EF84 -> 0 | EF84: 100
B85: =B14 -> Building reduction | C85: m$ | D85: =D14*$EF85 -> 0 | E85: =E14*$EF85 -> 0 | F85: =F14*$EF85 -> 0 | G85: =G14*$EF85 -> 0 | H85: =H14*$EF85 -> 0 | I85: =I14*$EF85 -> 0 | J85: =J14*$EF85 -> 0 | K85: =K14*$EF85 -> 0 | ... AH85: =AH14*$EF85 -> 0 | AJ85: =AJ14*$EF85 -> 0 | AK85: =AK14*$EF85 -> 0 | AL85: =AL14*$EF85 -> 0 | AM85: =AM14*$EF85 -> 0 | AN85: =AN14*$EF85 -> 0 | AO85: =AO14*$EF85 -> 0 | AP85: =AP14*$EF85 -> 0 | AQ85: =AQ14*$EF85 -> 0 | ... BN85: =BN14*$EF85 -> 0 | BP85: =BP14*$EF85 -> 0 | BQ85: =BQ14*$EF85 -> 0 | BR85: =BR14*$EF85 -> 0 | BS85: =BS14*$EF85 -> 0 | BT85: =BT14*$EF85 -> 0 | BU85: =BU14*$EF85 -> 0 | BV85: =BV14*$EF85 -> 0 | BW85: =BW14*$EF85 -> 0 | ... CT85: =CT14*$EF85 -> 0 | CV85: =CV14*$EF85 -> 0 | CW85: =CW14*$EF85 -> 0 | CX85: =CX14*$EF85 -> 0 | CY85: =CY14*$EF85 -> 0 | CZ85: =CZ14*$EF85 -> 0 | DA85: =DA14*$EF85 -> 0 | DB85: =DB14*$EF85 -> 0 | DC85: =DC14*$EF85 -> 0 | ... DZ85: =DZ14*$EF85 -> 0 | EF85: 0 | EM85: BPW
B86: =B15 -> Building substitution | C86: m$ | D86: =D15*$EF86 -> 0 | E86: =E15*$EF86 -> 0 | F86: =F15*$EF86 -> 0 | G86: =G15*$EF86 -> 0 | H86: =H15*$EF86 -> 0 | I86: =I15*$EF86 -> 0 | J86: =J15*$EF86 -> 0 | K86: =K15*$EF86 -> 0 | ... AH86: =AH15*$EF86 -> 0 | AJ86: =AJ15*$EF86 -> 0 | AK86: =AK15*$EF86 -> 0 | AL86: =AL15*$EF86 -> 0 | AM86: =AM15*$EF86 -> 0 | AN86: =AN15*$EF86 -> 0 | AO86: =AO15*$EF86 -> 0 | AP86: =AP15*$EF86 -> 0 | AQ86: =AQ15*$EF86 -> 0 | ... BN86: =BN15*$EF86 -> 0 | BP86: =BP15*$EF86 -> 0 | BQ86: =BQ15*$EF86 -> 0 | BR86: =BR15*$EF86 -> 0 | BS86: =BS15*$EF86 -> 0 | BT86: =BT15*$EF86 -> 0 | BU86: =BU15*$EF86 -> 0 | BV86: =BV15*$EF86 -> 0 | BW86: =BW15*$EF86 -> 0 | ... CT86: =CT15*$EF86 -> 0 | CV86: =CV15*$EF86 -> 0 | CW86: =CW15*$EF86 -> 0 | CX86: =CX15*$EF86 -> 0 | CY86: =CY15*$EF86 -> 0 | CZ86: =CZ15*$EF86 -> 0 | DA86: =DA15*$EF86 -> 0 | DB86: =DB15*$EF86 -> 0 | DC86: =DC15*$EF86 -> 0 | ... DZ86: =DZ15*$EF86 -> 0 | EF86: 100 | EM86: BPW
B87: =B16 -> Apparel - waste reduction | C87: m$ | D87: =D16*$EF87 -> 0 | E87: =E16*$EF87 -> 0 | F87: =F16*$EF87 -> 0 | G87: =G16*$EF87 -> 0 | H87: =H16*$EF87 -> 0 | I87: =I16*$EF87 -> 0 | J87: =J16*$EF87 -> 0 | K87: =K16*$EF87 -> 0 | ... AH87: =AH16*$EF87 -> 0 | AJ87: =AJ16*$EF87 -> 0 | AK87: =AK16*$EF87 -> 0 | AL87: =AL16*$EF87 -> 0 | AM87: =AM16*$EF87 -> 0 | AN87: =AN16*$EF87 -> 0 | AO87: =AO16*$EF87 -> 0 | AP87: =AP16*$EF87 -> 0 | AQ87: =AQ16*$EF87 -> 0 | ... BN87: =BN16*$EF87 -> 0 | BP87: =BP16*$EF87 -> 0 | BQ87: =BQ16*$EF87 -> 0 | BR87: =BR16*$EF87 -> 0 | BS87: =BS16*$EF87 -> 0 | BT87: =BT16*$EF87 -> 0 | BU87: =BU16*$EF87 -> 0 | BV87: =BV16*$EF87 -> 0 | BW87: =BW16*$EF87 -> 0 | ... CT87: =CT16*$EF87 -> 0 | CV87: =CV16*$EF87 -> 0 | CW87: =CW16*$EF87 -> 0 | CX87: =CX16*$EF87 -> 0 | CY87: =CY16*$EF87 -> 0 | CZ87: =CZ16*$EF87 -> 0 | DA87: =DA16*$EF87 -> 0 | DB87: =DB16*$EF87 -> 0 | DC87: =DC16*$EF87 -> 0 | ... DZ87: =DZ16*$EF87 -> 0 | EF87: 0 | EM87: BPW
B88: =B17 -> Apparel - NBM | C88: m$ | D88: =D17*$EF88 -> 0 | E88: =E17*$EF88 -> 0 | F88: =F17*$EF88 -> 0 | G88: =G17*$EF88 -> 0 | H88: =H17*$EF88 -> 0 | I88: =I17*$EF88 -> 0 | J88: =J17*$EF88 -> 0 | K88: =K17*$EF88 -> 0 | ... AH88: =AH17*$EF88 -> 0 | AJ88: =AJ17*$EF88 -> 0 | AK88: =AK17*$EF88 -> 0 | AL88: =AL17*$EF88 -> 0 | AM88: =AM17*$EF88 -> 0 | AN88: =AN17*$EF88 -> 0 | AO88: =AO17*$EF88 -> 0 | AP88: =AP17*$EF88 -> 0 | AQ88: =AQ17*$EF88 -> 0 | ... BN88: =BN17*$EF88 -> 0 | BP88: =BP17*$EF88 -> 0 | BQ88: =BQ17*$EF88 -> 0 | BR88: =BR17*$EF88 -> 0 | BS88: =BS17*$EF88 -> 0 | BT88: =BT17*$EF88 -> 0 | BU88: =BU17*$EF88 -> 0 | BV88: =BV17*$EF88 -> 0 | BW88: =BW17*$EF88 -> 0 | ... CT88: =CT17*$EF88 -> 0 | CV88: =CV17*$EF88 -> 0 | CW88: =CW17*$EF88 -> 0 | CX88: =CX17*$EF88 -> 0 | CY88: =CY17*$EF88 -> 0 | CZ88: =CZ17*$EF88 -> 0 | DA88: =DA17*$EF88 -> 0 | DB88: =DB17*$EF88 -> 0 | DC88: =DC17*$EF88 -> 0 | ... DZ88: =DZ17*$EF88 -> 0 | EF88: 100 | EM88: BPW
B89: =B18 -> Apparel - substitution | C89: m$ | D89: =D18*$EF89 -> 0 | E89: =E18*$EF89 -> 0 | F89: =F18*$EF89 -> 0 | G89: =G18*$EF89 -> 0 | H89: =H18*$EF89 -> 0 | I89: =I18*$EF89 -> 0 | J89: =J18*$EF89 -> 0 | K89: =K18*$EF89 -> 0 | ... AH89: =AH18*$EF89 -> 0 | AJ89: =AJ18*$EF89 -> 0 | AK89: =AK18*$EF89 -> 0 | AL89: =AL18*$EF89 -> 0 | AM89: =AM18*$EF89 -> 0 | AN89: =AN18*$EF89 -> 0 | AO89: =AO18*$EF89 -> 0 | AP89: =AP18*$EF89 -> 0 | AQ89: =AQ18*$EF89 -> 0 | ... BN89: =BN18*$EF89 -> 0 | BP89: =BP18*$EF89 -> 0 | BQ89: =BQ18*$EF89 -> 0 | BR89: =BR18*$EF89 -> 0 | BS89: =BS18*$EF89 -> 0 | BT89: =BT18*$EF89 -> 0 | BU89: =BU18*$EF89 -> 0 | BV89: =BV18*$EF89 -> 0 | BW89: =BW18*$EF89 -> 0 | ... CT89: =CT18*$EF89 -> 0 | CV89: =CV18*$EF89 -> 0 | CW89: =CW18*$EF89 -> 0 | CX89: =CX18*$EF89 -> 0 | CY89: =CY18*$EF89 -> 0 | CZ89: =CZ18*$EF89 -> 0 | DA89: =DA18*$EF89 -> 0 | DB89: =DB18*$EF89 -> 0 | DC89: =DC18*$EF89 -> 0 | ... DZ89: =DZ18*$EF89 -> 0 | EF89: 100 | EM89: BPW
B90: =B19 -> Others Reduction | C90: m$ | D90: =D19*$EF90 -> 0 | E90: =E19*$EF90 -> 0 | F90: =F19*$EF90 -> 0 | G90: =G19*$EF90 -> 0 | H90: =H19*$EF90 -> 0 | I90: =I19*$EF90 -> 0 | J90: =J19*$EF90 -> 0 | K90: =K19*$EF90 -> 0 | ... AH90: =AH19*$EF90 -> 0 | AJ90: =AJ19*$EF90 -> 0 | AK90: =AK19*$EF90 -> 0 | AL90: =AL19*$EF90 -> 0 | AM90: =AM19*$EF90 -> 0 | AN90: =AN19*$EF90 -> 0 | AO90: =AO19*$EF90 -> 0 | AP90: =AP19*$EF90 -> 0 | AQ90: =AQ19*$EF90 -> 0 | ... BN90: =BN19*$EF90 -> 0 | BP90: =BP19*$EF90 -> 0 | BQ90: =BQ19*$EF90 -> 0 | BR90: =BR19*$EF90 -> 0 | BS90: =BS19*$EF90 -> 0 | BT90: =BT19*$EF90 -> 0 | BU90: =BU19*$EF90 -> 0 | BV90: =BV19*$EF90 -> 0 | BW90: =BW19*$EF90 -> 0 | ... CT90: =CT19*$EF90 -> 0 | CV90: =CV19*$EF90 -> 0 | CW90: =CW19*$EF90 -> 0 | CX90: =CX19*$EF90 -> 0 | CY90: =CY19*$EF90 -> 0 | CZ90: =CZ19*$EF90 -> 0 | DA90: =DA19*$EF90 -> 0 | DB90: =DB19*$EF90 -> 0 | DC90: =DC19*$EF90 -> 0 | ... DZ90: =DZ19*$EF90 -> 0 | EF90: 0 | EM90: BPW
B91: =B20 -> Others Substitution | C91: m$ | D91: =D20*$EF91 -> 0 | E91: =E20*$EF91 -> 0 | F91: =F20*$EF91 -> 0 | G91: =G20*$EF91 -> 0 | H91: =H20*$EF91 -> 0 | I91: =I20*$EF91 -> 0 | J91: =J20*$EF91 -> 0 | K91: =K20*$EF91 -> 0 | ... AH91: =AH20*$EF91 -> 0 | AJ91: =AJ20*$EF91 -> 0 | AK91: =AK20*$EF91 -> 0 | AL91: =AL20*$EF91 -> 0 | AM91: =AM20*$EF91 -> 0 | AN91: =AN20*$EF91 -> 0 | AO91: =AO20*$EF91 -> 0 | AP91: =AP20*$EF91 -> 0 | AQ91: =AQ20*$EF91 -> 0 | ... BN91: =BN20*$EF91 -> 0 | BP91: =BP20*$EF91 -> 0 | BQ91: =BQ20*$EF91 -> 0 | BR91: =BR20*$EF91 -> 0 | BS91: =BS20*$EF91 -> 0 | BT91: =BT20*$EF91 -> 0 | BU91: =BU20*$EF91 -> 0 | BV91: =BV20*$EF91 -> 0 | BW91: =BW20*$EF91 -> 0 | ... CT91: =CT20*$EF91 -> 0 | CV91: =CV20*$EF91 -> 0 | CW91: =CW20*$EF91 -> 0 | CX91: =CX20*$EF91 -> 0 | CY91: =CY20*$EF91 -> 0 | CZ91: =CZ20*$EF91 -> 0 | DA91: =DA20*$EF91 -> 0 | DB91: =DB20*$EF91 -> 0 | DC91: =DC20*$EF91 -> 0 | ... DZ91: =DZ20*$EF91 -> 0 | EF91: 100 | EM91: BPW
B92: =B22 -> Mecahnical Recycling | C92: m$ | D92: =D22*$EF92 -> 4244.1701 | E92: =E22*$EF92 -> 4559.4269 | F92: =F22*$EF92 -> 4942.8201 | G92: =G22*$EF92 -> 5332.8521 | H92: =H22*$EF92 -> 5727.2858 | I92: =I22*$EF92 -> 6123.7375 | J92: =J22*$EF92 -> 6533.7669 | K92: =K22*$EF92 -> 6957.3934 | ... AH92: =AH22*$EF92 -> 31591.803 | AJ92: =AJ22*$EF92 -> 4244.1701 | AK92: =AK22*$EF92 -> 4559.4269 | AL92: =AL22*$EF92 -> 4942.8201 | AM92: =AM22*$EF92 -> 5332.8521 | AN92: =AN22*$EF92 -> 5727.2858 | AO92: =AO22*$EF92 -> 6123.7375 | AP92: =AP22*$EF92 -> 6533.7669 | AQ92: =AQ22*$EF92 -> 6957.3934 | ... BN92: =BN22*$EF92 -> 31591.803 | BP92: =BP22*$EF92 -> 4244.1701 | BQ92: =BQ22*$EF92 -> 4315.0477 | BR92: =BR22*$EF92 -> 4387.109 | BS92: =BS22*$EF92 -> 4460.3737 | BT92: =BT22*$EF92 -> 4534.862 | BU92: =BU22*$EF92 -> 4610.5942 | BV92: =BV22*$EF92 -> 4687.5911 | BW92: =BW22*$EF92 -> 4765.8739 | ... CT92: =CT22*$EF92 -> 6975.5344 | CV92: =CV22*$EF92 -> 4244.1701 | CW92: =CW22*$EF92 -> 4559.4269 | CX92: =CX22*$EF92 -> 4942.8201 | CY92: =CY22*$EF92 -> 5332.8521 | CZ92: =CZ22*$EF92 -> 5727.2858 | DA92: =DA22*$EF92 -> 6123.7375 | DB92: =DB22*$EF92 -> 6533.7669 | DC92: =DC22*$EF92 -> 6957.3934 | ... DZ92: =DZ22*$EF92 -> 31591.803 | EF92: =AVERAGE(160,120) -> 140
B93: =B23 -> Chemical Recycling | C93: m$ | D93: =D23*$EF93 -> 0.021962799 | E93: =E23*$EF93 -> 0.048323375 | F93: =F23*$EF93 -> 0.10216992 | G93: =G23*$EF93 -> 0.2145778 | H93: =H23*$EF93 -> 0.44724902 | I93: =I23*$EF93 -> 0.92396257 | J93: =J23*$EF93 -> 1.8925481 | K93: =K23*$EF93 -> 3.8339031 | ... AH93: =AH23*$EF93 -> 2677.2589 | AJ93: =AJ23*$EF93 -> 0.012135484 | AK93: =AK23*$EF93 -> 0.026840285 | AL93: =AL23*$EF93 -> 0.056734877 | AM93: =AM23*$EF93 -> 0.11913389 | AN93: =AN23*$EF93 -> 0.24828327 | AO93: =AO23*$EF93 -> 0.51288757 | AP93: =AP23*$EF93 -> 1.0505214 | AQ93: =AQ23*$EF93 -> 2.1281796 | ... BN93: =BN23*$EF93 -> 1492.4649 | BP93: =BP23*$EF93 -> 0 | BQ93: =BQ23*$EF93 -> 0 | BR93: =BR23*$EF93 -> 0 | BS93: =BS23*$EF93 -> 0 | BT93: =BT23*$EF93 -> 0 | BU93: =BU23*$EF93 -> 0 | BV93: =BV23*$EF93 -> 0 | BW93: =BW23*$EF93 -> 0 | ... CT93: =CT23*$EF93 -> 0 | CV93: =CV23*$EF93 -> 0.012135484 | CW93: =CW23*$EF93 -> 0.026840285 | CX93: =CX23*$EF93 -> 0.056734877 | CY93: =CY23*$EF93 -> 0.11913389 | CZ93: =CZ23*$EF93 -> 0.24828327 | DA93: =DA23*$EF93 -> 0.51288757 | DB93: =DB23*$EF93 -> 1.0505214 | DC93: =DC23*$EF93 -> 2.1281796 | ... DZ93: =DZ23*$EF93 -> 1492.4649 | EF93: 153
B94: =B24 -> Waste management (collection + MRF) | C94: m$ | D94: =D24*$EF94 -> 28932.049 | E94: =E24*$EF94 -> 30037.941 | F94: =F24*$EF94 -> 31116.448 | G94: =G24*$EF94 -> 32147.802 | H94: =H24*$EF94 -> 33124.939 | I94: =I24*$EF94 -> 34041.027 | J94: =J24*$EF94 -> 34964.829 | K94: =K24*$EF94 -> 35895.685 | ... AH94: =AH24*$EF94 -> 54706.419 | AJ94: =AJ24*$EF94 -> 28932.047 | AK94: =AK24*$EF94 -> 30037.937 | AL94: =AL24*$EF94 -> 31116.44 | AM94: =AM24*$EF94 -> 32147.785 | AN94: =AN24*$EF94 -> 33124.902 | AO94: =AO24*$EF94 -> 34040.952 | AP94: =AP24*$EF94 -> 34964.677 | AQ94: =AQ24*$EF94 -> 35895.381 | ... BN94: =BN24*$EF94 -> 54519.2 | BP94: =BP24*$EF94 -> 28932.045 | BQ94: =BQ24*$EF94 -> 29760.84 | BR94: =BR24*$EF94 -> 30534.983 | BS94: =BS24*$EF94 -> 31249.117 | BT94: =BT24*$EF94 -> 31898.247 | BU94: =BU24*$EF94 -> 32477.796 | BV94: =BV24*$EF94 -> 33052.508 | BW94: =BW24*$EF94 -> 33621.751 | ... CT94: =CT24*$EF94 -> 40346.769 | CV94: =CV24*$EF94 -> 28932.047 | CW94: =CW24*$EF94 -> 30037.937 | CX94: =CX24*$EF94 -> 31116.44 | CY94: =CY24*$EF94 -> 32147.785 | CZ94: =CZ24*$EF94 -> 33124.902 | DA94: =DA24*$EF94 -> 34040.952 | DB94: =DB24*$EF94 -> 34964.677 | DC94: =DC24*$EF94 -> 35895.381 | ... DZ94: =DZ24*$EF94 -> 54409.129 | EF94: =52+64 -> 116
B95: =B25 -> Incineration | C95: m$ | D95: =D25*$EF95 -> 1270.4776 | E95: =E25*$EF95 -> 1351.3183 | F95: =F25*$EF95 -> 1429.9045 | G95: =G25*$EF95 -> 1507.5414 | H95: =H25*$EF95 -> 1583.6869 | I95: =I25*$EF95 -> 1657.79 | J95: =J25*$EF95 -> 1733.0262 | K95: =K25*$EF95 -> 1809.3013 | ... AH95: =AH25*$EF95 -> 2378.1122 | AJ95: =AJ25*$EF95 -> 1270.4779 | AK95: =AK25*$EF95 -> 1351.3189 | AL95: =AL25*$EF95 -> 1429.9058 | AM95: =AM25*$EF95 -> 1507.5444 | AN95: =AN25*$EF95 -> 1583.6933 | AO95: =AO25*$EF95 -> 1657.8036 | AP95: =AP25*$EF95 -> 1733.0548 | AQ95: =AQ25*$EF95 -> 1809.3607 | ... BN95: =BN25*$EF95 -> 2441.9211 | BP95: =BP25*$EF95 -> 1270.4782 | BQ95: =BQ25*$EF95 -> 1332.2585 | BR95: =BR25*$EF95 -> 1392.7595 | BS95: =BS25*$EF95 -> 1451.5705 | BT95: =BT25*$EF95 -> 1508.2774 | BU95: =BU25*$EF95 -> 1562.4679 | BV95: =BV25*$EF95 -> 1617.5534 | BW95: =BW25*$EF95 -> 1673.4988 | ... CT95: =CT25*$EF95 -> 2799.6276 | CV95: =CV25*$EF95 -> 1270.4779 | CW95: =CW25*$EF95 -> 1351.3189 | CX95: =CX25*$EF95 -> 1429.9058 | CY95: =CY25*$EF95 -> 1507.5444 | CZ95: =CZ25*$EF95 -> 1583.6933 | DA95: =DA25*$EF95 -> 1657.8036 | DB95: =DB25*$EF95 -> 1733.0548 | DC95: =DC25*$EF95 -> 1809.3607 | ... DZ95: =DZ25*$EF95 -> 2432.0435 | EF95: 27
B96: CSS | C96: m$ | D96: =D25*$EF96*('Scope 3 Yearly'!D20/SUM('Scope 3 Yearly'!D19:D20)) -> 0.1453021 | E96: =E25*$EF96*('Scope 3 Yearly'!E20/SUM('Scope 3 Yearly'!E19:E20)) -> 0.29927139 | F96: =F25*$EF96*('Scope 3 Yearly'!F20/SUM('Scope 3 Yearly'!F19:F20)) -> 0.61216484 | G96: =G25*$EF96*('Scope 3 Yearly'!G20/SUM('Scope 3 Yearly'!G19:G20)) -> 1.2445961 | H96: =H25*$EF96*('Scope 3 Yearly'!H20/SUM('Scope 3 Yearly'!H19:H20)) -> 2.5127037 | I96: =I25*$EF96*('Scope 3 Yearly'!I20/SUM('Scope 3 Yearly'!I19:I20)) -> 5.0307579 | J96: =J25*$EF96*('Scope 3 Yearly'!J20/SUM('Scope 3 Yearly'!J19:J20)) -> 9.9917259 | K96: =K25*$EF96*('Scope 3 Yearly'!K20/SUM('Scope 3 Yearly'!K19:K20)) -> 19.636487 | ... AH96: =AH25*$EF96*('Scope 3 Yearly'!AH20/SUM('Scope 3 Yearly'!AH19:AH20)) -> 5842.8489 | AJ96: =AJ25*$EF96*('Scope 3 Yearly'!AJ20/SUM('Scope 3 Yearly'!AJ19:AJ20)) -> 0.14530213 | AK96: =AK25*$EF96*('Scope 3 Yearly'!AK20/SUM('Scope 3 Yearly'!AK19:AK20)) -> 0.29927153 | AL96: =AL25*$EF96*('Scope 3 Yearly'!AL20/SUM('Scope 3 Yearly'!AL19:AL20)) -> 0.61216543 | AM96: =AM25*$EF96*('Scope 3 Yearly'!AM20/SUM('Scope 3 Yearly'!AM19:AM20)) -> 1.2445986 | AN96: =AN25*$EF96*('Scope 3 Yearly'!AN20/SUM('Scope 3 Yearly'!AN19:AN20)) -> 2.5127138 | AO96: =AO25*$EF96*('Scope 3 Yearly'!AO20/SUM('Scope 3 Yearly'!AO19:AO20)) -> 5.030799 | AP96: =AP25*$EF96*('Scope 3 Yearly'!AP20/SUM('Scope 3 Yearly'!AP19:AP20)) -> 9.9918904 | AQ96: =AQ25*$EF96*('Scope 3 Yearly'!AQ20/SUM('Scope 3 Yearly'!AQ19:AQ20)) -> 19.637131 | ... BN96: =BN25*$EF96*('Scope 3 Yearly'!BN20/SUM('Scope 3 Yearly'!BN19:BN20)) -> 5999.6227 | BP96: =BP25*$EF96*('Scope 3 Yearly'!BP20/SUM('Scope 3 Yearly'!BP19:BP20)) -> 0 | BQ96: =BQ25*$EF96*('Scope 3 Yearly'!BQ20/SUM('Scope 3 Yearly'!BQ19:BQ20)) -> 0 | BR96: =BR25*$EF96*('Scope 3 Yearly'!BR20/SUM('Scope 3 Yearly'!BR19:BR20)) -> 0 | BS96: =BS25*$EF96*('Scope 3 Yearly'!BS20/SUM('Scope 3 Yearly'!BS19:BS20)) -> 0 | BT96: =BT25*$EF96*('Scope 3 Yearly'!BT20/SUM('Scope 3 Yearly'!BT19:BT20)) -> 0 | BU96: =BU25*$EF96*('Scope 3 Yearly'!BU20/SUM('Scope 3 Yearly'!BU19:BU20)) -> 0 | BV96: =BV25*$EF96*('Scope 3 Yearly'!BV20/SUM('Scope 3 Yearly'!BV19:BV20)) -> 0 | BW96: =BW25*$EF96*('Scope 3 Yearly'!BW20/SUM('Scope 3 Yearly'!BW19:BW20)) -> 0 | ... CT96: =CT25*$EF96*('Scope 3 Yearly'!CT20/SUM('Scope 3 Yearly'!CT19:CT20)) -> 0 | CV96: =CV25*$EF96*('Scope 3 Yearly'!CV20/SUM('Scope 3 Yearly'!CV19:CV20)) -> 0.14530213 | CW96: =CW25*$EF96*('Scope 3 Yearly'!CW20/SUM('Scope 3 Yearly'!CW19:CW20)) -> 0.29927153 | CX96: =CX25*$EF96*('Scope 3 Yearly'!CX20/SUM('Scope 3 Yearly'!CX19:CX20)) -> 0.61216543 | CY96: =CY25*$EF96*('Scope 3 Yearly'!CY20/SUM('Scope 3 Yearly'!CY19:CY20)) -> 1.2445986 | CZ96: =CZ25*$EF96*('Scope 3 Yearly'!CZ20/SUM('Scope 3 Yearly'!CZ19:CZ20)) -> 2.5127138 | DA96: =DA25*$EF96*('Scope 3 Yearly'!DA20/SUM('Scope 3 Yearly'!DA19:DA20)) -> 5.030799 | DB96: =DB25*$EF96*('Scope 3 Yearly'!DB20/SUM('Scope 3 Yearly'!DB19:DB20)) -> 9.9918904 | DC96: =DC25*$EF96*('Scope 3 Yearly'!DC20/SUM('Scope 3 Yearly'!DC19:DC20)) -> 19.637131 | ... DZ96: =DZ25*$EF96*('Scope 3 Yearly'!DZ20/SUM('Scope 3 Yearly'!DZ19:DZ20)) -> 5975.3542 | EF96: 67
B97: =B26 -> Landfill | C97: m$ | D97: =D26*$EF97 -> 2502.7233 | E97: =E26*$EF97 -> 2587.7059 | F97: =F26*$EF97 -> 2664.521 | G97: =G26*$EF97 -> 2736.2257 | H97: =H26*$EF97 -> 2802.2891 | I97: =I26*$EF97 -> 2862.2096 | J97: =J26*$EF97 -> 2921.8073 | K97: =K26*$EF97 -> 2980.9778 | ... AH97: =AH26*$EF97 -> 2658.8615 | AJ97: =AJ26*$EF97 -> 2502.7238 | AK97: =AK26*$EF97 -> 2587.7071 | AL97: =AL26*$EF97 -> 2664.5236 | AM97: =AM26*$EF97 -> 2736.2311 | AN97: =AN26*$EF97 -> 2802.3004 | AO97: =AO26*$EF97 -> 2862.233 | AP97: =AP26*$EF97 -> 2921.8554 | AQ97: =AQ26*$EF97 -> 2981.0757 | ... BN97: =BN26*$EF97 -> 2730.2034 | BP97: =BP26*$EF97 -> 2502.7245 | BQ97: =BQ26*$EF97 -> 2539.8403 | BR97: =BR26*$EF97 -> 2568.9807 | BS97: =BS26*$EF97 -> 2589.8535 | BT97: =BT26*$EF97 -> 2602.2367 | BU97: =BU26*$EF97 -> 2605.9818 | BV97: =BV26*$EF97 -> 2607.1703 | BW97: =BW26*$EF97 -> 2605.7427 | ... CT97: =CT26*$EF97 -> 1622.1399 | CV97: =CV26*$EF97 -> 2502.7238 | CW97: =CW26*$EF97 -> 2587.7071 | CX97: =CX26*$EF97 -> 2664.5236 | CY97: =CY26*$EF97 -> 2736.2311 | CZ97: =CZ26*$EF97 -> 2802.3004 | DA97: =DA26*$EF97 -> 2862.233 | DB97: =DB26*$EF97 -> 2921.8554 | DC97: =DC26*$EF97 -> 2981.0757 | ... DZ97: =DZ26*$EF97 -> 2719.1597 | EF97: 23
B98: =B27 -> Dumpsite | C98: m$ | D98: =D27*$EF98 -> 0 | E98: =E27*$EF98 -> 0 | F98: =F27*$EF98 -> 0 | G98: =G27*$EF98 -> 0 | H98: =H27*$EF98 -> 0 | I98: =I27*$EF98 -> 0 | J98: =J27*$EF98 -> 0 | K98: =K27*$EF98 -> 0 | ... AH98: =AH27*$EF98 -> 0 | AJ98: =AJ27*$EF98 -> 0 | AK98: =AK27*$EF98 -> 0 | AL98: =AL27*$EF98 -> 0 | AM98: =AM27*$EF98 -> 0 | AN98: =AN27*$EF98 -> 0 | AO98: =AO27*$EF98 -> 0 | AP98: =AP27*$EF98 -> 0 | AQ98: =AQ27*$EF98 -> 0 | ... BN98: =BN27*$EF98 -> 0 | BP98: =BP27*$EF98 -> 0 | BQ98: =BQ27*$EF98 -> 0 | BR98: =BR27*$EF98 -> 0 | BS98: =BS27*$EF98 -> 0 | BT98: =BT27*$EF98 -> 0 | BU98: =BU27*$EF98 -> 0 | BV98: =BV27*$EF98 -> 0 | BW98: =BW27*$EF98 -> 0 | ... CT98: =CT27*$EF98 -> 0 | CV98: =CV27*$EF98 -> 0 | CW98: =CW27*$EF98 -> 0 | CX98: =CX27*$EF98 -> 0 | CY98: =CY27*$EF98 -> 0 | CZ98: =CZ27*$EF98 -> 0 | DA98: =DA27*$EF98 -> 0 | DB98: =DB27*$EF98 -> 0 | DC98: =DC27*$EF98 -> 0 | ... DZ98: =DZ27*$EF98 -> 0 | EF98: 0
B99: =B28 -> Open Burning | C99: m$ | D99: =D28*$EF99 -> 0 | E99: =E28*$EF99 -> 0 | F99: =F28*$EF99 -> 0 | G99: =G28*$EF99 -> 0 | H99: =H28*$EF99 -> 0 | I99: =I28*$EF99 -> 0 | J99: =J28*$EF99 -> 0 | K99: =K28*$EF99 -> 0 | ... AH99: =AH28*$EF99 -> 0 | AJ99: =AJ28*$EF99 -> 0 | AK99: =AK28*$EF99 -> 0 | AL99: =AL28*$EF99 -> 0 | AM99: =AM28*$EF99 -> 0 | AN99: =AN28*$EF99 -> 0 | AO99: =AO28*$EF99 -> 0 | AP99: =AP28*$EF99 -> 0 | AQ99: =AQ28*$EF99 -> 0 | ... BN99: =BN28*$EF99 -> 0 | BP99: =BP28*$EF99 -> 0 | BQ99: =BQ28*$EF99 -> 0 | BR99: =BR28*$EF99 -> 0 | BS99: =BS28*$EF99 -> 0 | BT99: =BT28*$EF99 -> 0 | BU99: =BU28*$EF99 -> 0 | BV99: =BV28*$EF99 -> 0 | BW99: =BW28*$EF99 -> 0 | ... CT99: =CT28*$EF99 -> 0 | CV99: =CV28*$EF99 -> 0 | CW99: =CW28*$EF99 -> 0 | CX99: =CX28*$EF99 -> 0 | CY99: =CY28*$EF99 -> 0 | CZ99: =CZ28*$EF99 -> 0 | DA99: =DA28*$EF99 -> 0 | DB99: =DB28*$EF99 -> 0 | DC99: =DC28*$EF99 -> 0 | ... DZ99: =DZ28*$EF99 -> 0 | EF99: 0
B100: =B29 -> Leakage Environment | C100: m$ | D100: =D29*$EF100 -> 0 | E100: =E29*$EF100 -> 0 | F100: =F29*$EF100 -> 0 | G100: =G29*$EF100 -> 0 | H100: =H29*$EF100 -> 0 | I100: =I29*$EF100 -> 0 | J100: =J29*$EF100 -> 0 | K100: =K29*$EF100 -> 0 | ... AH100: =AH29*$EF100 -> 0 | AJ100: =AJ29*$EF100 -> 0 | AK100: =AK29*$EF100 -> 0 | AL100: =AL29*$EF100 -> 0 | AM100: =AM29*$EF100 -> 0 | AN100: =AN29*$EF100 -> 0 | AO100: =AO29*$EF100 -> 0 | AP100: =AP29*$EF100 -> 0 | AQ100: =AQ29*$EF100 -> 0 | ... BN100: =BN29*$EF100 -> 0 | BP100: =BP29*$EF100 -> 0 | BQ100: =BQ29*$EF100 -> 0 | BR100: =BR29*$EF100 -> 0 | BS100: =BS29*$EF100 -> 0 | BT100: =BT29*$EF100 -> 0 | BU100: =BU29*$EF100 -> 0 | BV100: =BV29*$EF100 -> 0 | BW100: =BW29*$EF100 -> 0 | ... CT100: =CT29*$EF100 -> 0 | CV100: =CV29*$EF100 -> 0 | CW100: =CW29*$EF100 -> 0 | CX100: =CX29*$EF100 -> 0 | CY100: =CY29*$EF100 -> 0 | CZ100: =CZ29*$EF100 -> 0 | DA100: =DA29*$EF100 -> 0 | DB100: =DB29*$EF100 -> 0 | DC100: =DC29*$EF100 -> 0 | ... DZ100: =DZ29*$EF100 -> 0 | EF100: 0
B101: =B30 -> Leakage Ocean | C101: m$ | D101: =D30*$EF101 -> 0 | E101: =E30*$EF101 -> 0 | F101: =F30*$EF101 -> 0 | G101: =G30*$EF101 -> 0 | H101: =H30*$EF101 -> 0 | I101: =I30*$EF101 -> 0 | J101: =J30*$EF101 -> 0 | K101: =K30*$EF101 -> 0 | ... AH101: =AH30*$EF101 -> 0 | AJ101: =AJ30*$EF101 -> 0 | AK101: =AK30*$EF101 -> 0 | AL101: =AL30*$EF101 -> 0 | AM101: =AM30*$EF101 -> 0 | AN101: =AN30*$EF101 -> 0 | AO101: =AO30*$EF101 -> 0 | AP101: =AP30*$EF101 -> 0 | AQ101: =AQ30*$EF101 -> 0 | ... BN101: =BN30*$EF101 -> 0 | BP101: =BP30*$EF101 -> 0 | BQ101: =BQ30*$EF101 -> 0 | BR101: =BR30*$EF101 -> 0 | BS101: =BS30*$EF101 -> 0 | BT101: =BT30*$EF101 -> 0 | BU101: =BU30*$EF101 -> 0 | BV101: =BV30*$EF101 -> 0 | BW101: =BW30*$EF101 -> 0 | ... CT101: =CT30*$EF101 -> 0 | CV101: =CV30*$EF101 -> 0 | CW101: =CW30*$EF101 -> 0 | CX101: =CX30*$EF101 -> 0 | CY101: =CY30*$EF101 -> 0 | CZ101: =CZ30*$EF101 -> 0 | DA101: =DA30*$EF101 -> 0 | DB101: =DB30*$EF101 -> 0 | DC101: =DC30*$EF101 -> 0 | ... DZ101: =DZ30*$EF101 -> 0 | EF101: 0
...

Sheet Yearly Summary
D1: HIGH CIRCULARITY | AJ1: LOW CIRCULARITY | BP1: BAU Most Economic
D2: 2020 | E2: =D2+1 -> 2021 | F2: =E2+1 -> 2022 | G2: =F2+1 -> 2023 | H2: =G2+1 -> 2024 | I2: =H2+1 -> 2025 | J2: =I2+1 -> 2026 | K2: =J2+1 -> 2027 | L2: =K2+1 -> 2028 | ... AH2: =AG2+1 -> 2050 | AJ2: 2020 | AK2: =AJ2+1 -> 2021 | AL2: =AK2+1 -> 2022 | AM2: =AL2+1 -> 2023 | AN2: =AM2+1 -> 2024 | AO2: =AN2+1 -> 2025 | AP2: =AO2+1 -> 2026 | AQ2: =AP2+1 -> 2027 | AR2: =AQ2+1 -> 2028 | ... BN2: =BM2+1 -> 2050 | BP2: 2020 | BQ2: =BP2+1 -> 2021 | BR2: =BQ2+1 -> 2022 | BS2: =BR2+1 -> 2023 | BT2: =BS2+1 -> 2024 | BU2: =BT2+1 -> 2025 | BV2: =BU2+1 -> 2026 | BW2: =BV2+1 -> 2027 | BX2: =BW2+1 -> 2028 | ... CT2: =CS2+1 -> 2050
A3: Total - inlcuding derivatives total weight
A4: Production BAU | C4: ='Yearly HC Ethylene'!C146 -> m Tons | D4: =D17+D57+D27+D32+D37+D42+D47+D52+D20+D23 -> 777.71929 | E4: =E17+E57+E27+E32+E37+E42+E47+E52+E20+E23 -> 799.39932 | F4: =F17+F57+F27+F32+F37+F42+F47+F52+F20+F23 -> 820.18946 | G4: =G17+G57+G27+G32+G37+G42+G47+G52+G20+G23 -> 841.28771 | H4: =H17+H57+H27+H32+H37+H42+H47+H52+H20+H23 -> 862.70204 | I4: =I17+I57+I27+I32+I37+I42+I47+I52+I20+I23 -> 884.44081 | J4: =J17+J57+J27+J32+J37+J42+J47+J52+J20+J23 -> 906.92663 | K4: =K17+K57+K27+K32+K37+K42+K47+K52+K20+K23 -> 929.65173 | ... AH4: =AH17+AH57+AH27+AH32+AH37+AH42+AH47+AH52+AH20+AH23 -> 1507.7993 | AJ4: =D4 -> 777.71929 | AK4: =E4 -> 799.39932 | AL4: =F4 -> 820.18946 | AM4: =G4 -> 841.28771 | AN4: =H4 -> 862.70204 | AO4: =I4 -> 884.44081 | AP4: =J4 -> 906.92663 | AQ4: =K4 -> 929.65173 | ... BN4: =AH4 -> 1507.7993 | BP4: =AJ4 -> 777.71929 | BQ4: =AK4 -> 799.39932 | BR4: =AL4 -> 820.18946 | BS4: =AM4 -> 841.28771 | BT4: =AN4 -> 862.70204 | BU4: =AO4 -> 884.44081 | BV4: =AP4 -> 906.92663 | BW4: =AQ4 -> 929.65173 | ... CT4: =BN4 -> 1507.7993 | CW4: =AH4-AH10 -> 590.53677 | CX4: =(BN4/AJ4)^(1/30)-1 -> 0.022313327
A5: Production Sceanrio | C5: ='Yearly HC Ethylene'!C147 -> m Tons | D5: =D18+D58+D28+D33+D38+D43+D48+D53+D21+D24 -> 777.71915 | E5: =E18+E58+E28+E33+E38+E43+E48+E53+E21+E24 -> 795.89075 | F5: =F18+F58+F28+F33+F38+F43+F48+F53+F21+F24 -> 812.87545 | G5: =G18+G58+G28+G33+G38+G43+G48+G53+G21+G24 -> 830.09236 | H5: =H18+H58+H28+H33+H38+H43+H48+H53+H21+H24 -> 847.56402 | I5: =I18+I58+I28+I33+I38+I43+I48+I53+I21+I24 -> 865.32706 | J5: =J18+J58+J28+J33+J38+J43+J48+J53+J21+J24 -> 883.47591 | K5: =K18+K58+K28+K33+K38+K43+K48+K53+K21+K24 -> 901.71879 | ... AH5: =AH18+AH58+AH28+AH33+AH38+AH43+AH48+AH53+AH21+AH24 -> 1147.2384 | AJ5: =AJ18+AJ58+AJ28+AJ33+AJ38+AJ43+AJ48+AJ53+AJ21+AJ24 -> 777.71921 | AK5: =AK18+AK58+AK28+AK33+AK38+AK43+AK48+AK53+AK21+AK24 -> 795.86298 | AL5: =AL18+AL58+AL28+AL33+AL38+AL43+AL48+AL53+AL21+AL24 -> 812.81909 | AM5: =AM18+AM58+AM28+AM33+AM38+AM43+AM48+AM53+AM21+AM24 -> 830.00674 | AN5: =AN18+AN58+AN28+AN33+AN38+AN43+AN48+AN53+AN21+AN24 -> 847.44862 | AO5: =AO18+AO58+AO28+AO33+AO38+AO43+AO48+AO53+AO21+AO24 -> 865.18171 | AP5: =AP18+AP58+AP28+AP33+AP38+AP43+AP48+AP53+AP21+AP24 -> 883.30113 | AQ5: =AQ18+AQ58+AQ28+AQ33+AQ38+AQ43+AQ48+AQ53+AQ21+AQ24 -> 901.51646 | ... BN5: =BN18+BN58+BN28+BN33+BN38+BN43+BN48+BN53+BN21+BN24 -> 1155.0078 | BP5: =BP18+BP58+BP28+BP33+BP38+BP43+BP48+BP53+BP21+BP24 -> 762.77192 | BQ5: =BQ18+BQ58+BQ28+BQ33+BQ38+BQ43+BQ48+BQ53+BQ21+BQ24 -> 783.70264 | BR5: =BR18+BR58+BR28+BR33+BR38+BR43+BR48+BR53+BR21+BR24 -> 803.73359 | BS5: =BS18+BS58+BS28+BS33+BS38+BS43+BS48+BS53+BS21+BS24 -> 824.06251 | BT5: =BT18+BT58+BT28+BT33+BT38+BT43+BT48+BT53+BT21+BT24 -> 844.69712 | BU5: =BU18+BU58+BU28+BU33+BU38+BU43+BU48+BU53+BU21+BU24 -> 865.64551 | BV5: =BV18+BV58+BV28+BV33+BV38+BV43+BV48+BV53+BV21+BV24 -> 887.12967 | BW5: =BW18+BW58+BW28+BW33+BW38+BW43+BW48+BW53+BW21+BW24 -> 908.83215 | ... CT5: =CT18+CT58+CT28+CT33+CT38+CT43+CT48+CT53+CT21+CT24 -> 1419.8784 | CW5: =70/CW4 -> 0.11853623
A6: Waste availability (pyrolysis only) | C6: ='Yearly HC Ethylene'!C154 -> m Tons | D6: =D29+D34+D39+D44+D49+D54+D59 -> 36.640987 | E6: =E29+E34+E39+E44+E49+E54+E59 -> 39.371849 | F6: =F29+F34+F39+F44+F49+F54+F59 -> 41.683724 | G6: =G29+G34+G39+G44+G49+G54+G59 -> 43.98677 | H6: =H29+H34+H39+H44+H49+H54+H59 -> 46.265876 | I6: =I29+I34+I39+I44+I49+I54+I59 -> 48.505086 | J6: =J29+J34+J39+J44+J49+J54+J59 -> 50.796752 | K6: =K29+K34+K39+K44+K49+K54+K59 -> 53.13657 | ... AH6: =AH29+AH34+AH39+AH44+AH49+AH54+AH59 -> 57.419773 | AJ6: =AJ29+AJ34+AJ39+AJ44+AJ49+AJ54+AJ59 -> 36.641051 | AK6: =AK29+AK34+AK39+AK44+AK49+AK54+AK59 -> 39.035494 | AL6: =AL29+AL34+AL39+AL44+AL49+AL54+AL59 -> 41.340677 | AM6: =AM29+AM34+AM39+AM44+AM49+AM54+AM59 -> 43.639013 | AN6: =AN29+AN34+AN39+AN44+AN49+AN54+AN59 -> 45.915705 | AO6: =AO29+AO34+AO39+AO44+AO49+AO54+AO59 -> 48.155274 | AP6: =AP29+AP34+AP39+AP44+AP49+AP54+AP59 -> 50.450132 | AQ6: =AQ29+AQ34+AQ39+AQ44+AQ49+AQ54+AQ59 -> 52.797467 | ... BN6: =BN29+BN34+BN39+BN44+BN49+BN54+BN59 -> 65.113621 | BP6: =BP29+BP34+BP39+BP44+BP49+BP54+BP59 -> 0 | BQ6: =BQ29+BQ34+BQ39+BQ44+BQ49+BQ54+BQ59 -> 0 | BR6: =BR29+BR34+BR39+BR44+BR49+BR54+BR59 -> 0 | BS6: =BS29+BS34+BS39+BS44+BS49+BS54+BS59 -> 0 | BT6: =BT29+BT34+BT39+BT44+BT49+BT54+BT59 -> 0 | BU6: =BU29+BU34+BU39+BU44+BU49+BU54+BU59 -> 0 | BV6: =BV29+BV34+BV39+BV44+BV49+BV54+BV59 -> 0 | BW6: =BW29+BW34+BW39+BW44+BW49+BW54+BW59 -> 0 | ... CT6: =CT29+CT34+CT39+CT44+CT49+CT54+CT59 -> 0
CV7: =BN6/(BN5-BN10)*0.8 -> 0.22650594
A8: Total - per ton of basic chemical
A9: Production BAU | C9: =C27 -> m Tons | D9: =D14+D27+D32+D37+D42+D47+D52+D57 -> 661.63221 | E9: =E14+E27+E32+E37+E42+E47+E52+E57 -> 681.06308 | F9: =F14+F27+F32+F37+F42+F47+F52+F57 -> 700.1174 | G9: =G14+G27+G32+G37+G42+G47+G52+G57 -> 719.45436 | H9: =H14+H27+H32+H37+H42+H47+H52+H57 -> 739.08157 | I9: =I14+I27+I32+I37+I42+I47+I52+I57 -> 759.00701 | J9: =J14+J27+J32+J37+J42+J47+J52+J57 -> 777.34663 | K9: =K14+K27+K32+K37+K42+K47+K52+K57 -> 795.89948 | ... AH9: =AH14+AH27+AH32+AH37+AH42+AH47+AH52+AH57 -> 1299.6618 | AJ9: =AJ14+AJ27+AJ32+AJ37+AJ42+AJ47+AJ52+AJ57 -> 661.63221 | AK9: =AK14+AK27+AK32+AK37+AK42+AK47+AK52+AK57 -> 681.06308 | AL9: =AL14+AL27+AL32+AL37+AL42+AL47+AL52+AL57 -> 700.1174 | AM9: =AM14+AM27+AM32+AM37+AM42+AM47+AM52+AM57 -> 719.45436 | AN9: =AN14+AN27+AN32+AN37+AN42+AN47+AN52+AN57 -> 739.08157 | AO9: =AO14+AO27+AO32+AO37+AO42+AO47+AO52+AO57 -> 759.00701 | AP9: =AP14+AP27+AP32+AP37+AP42+AP47+AP52+AP57 -> 777.34663 | AQ9: =AQ14+AQ27+AQ32+AQ37+AQ42+AQ47+AQ52+AQ57 -> 795.89948 | ... BN9: =BN14+BN27+BN32+BN37+BN42+BN47+BN52+BN57 -> 1299.6618 | BP9: =BP14+BP27+BP32+BP37+BP42+BP47+BP52+BP57 -> 646.68484 | BQ9: =BQ14+BQ27+BQ32+BQ37+BQ42+BQ47+BQ52+BQ57 -> 665.73167 | BR9: =BR14+BR27+BR32+BR37+BR42+BR47+BR52+BR57 -> 684.39209 | BS9: =BS14+BS27+BS32+BS37+BS42+BS47+BS52+BS57 -> 703.32502 | BT9: =BT14+BT27+BT32+BT37+BT42+BT47+BT52+BT57 -> 722.53783 | BU9: =BU14+BU27+BU32+BU37+BU42+BU47+BU52+BU57 -> 742.03821 | BV9: =BV14+BV27+BV32+BV37+BV42+BV47+BV52+BV57 -> 759.96497 | BW9: =BW14+BW27+BW32+BW37+BW42+BW47+BW52+BW57 -> 778.09489 | ... CT9: =CT14+CT27+CT32+CT37+CT42+CT47+CT52+CT57 -> 1297.1642 | CW9: =AH9-AH15 -> 881.94478 | CX9: =(BN9/AJ9)^(1/30)-1 -> 0.022760133
A10: Production Circular | C10: ='Yearly HC Ethylene'!C152 -> m Tons | D10: =D15+D28+D33+D38+D43+D48+D53+D58 -> 661.63206 | E10: =E15+E28+E33+E38+E43+E48+E53+E58 -> 677.55451 | F10: =F15+F28+F33+F38+F43+F48+F53+F58 -> 692.80339 | G10: =G15+G28+G33+G38+G43+G48+G53+G58 -> 708.25901 | H10: =H15+H28+H33+H38+H43+H48+H53+H58 -> 723.94355 | I10: =I15+I28+I33+I38+I43+I48+I53+I58 -> 739.89326 | J10: =J15+J28+J33+J38+J43+J48+J53+J58 -> 751.88015 | K10: =K15+K28+K33+K38+K43+K48+K53+K58 -> 763.95053 | ... AH10: =AH15+AH28+AH33+AH38+AH43+AH48+AH53+AH58 -> 917.26255 | AJ10: =AJ15+AJ28+AJ33+AJ38+AJ43+AJ48+AJ53+AJ58 -> 661.63213 | AK10: =AK15+AK28+AK33+AK38+AK43+AK48+AK53+AK58 -> 677.52674 | AL10: =AL15+AL28+AL33+AL38+AL43+AL48+AL53+AL58 -> 692.74703 | AM10: =AM15+AM28+AM33+AM38+AM43+AM48+AM53+AM58 -> 708.17339 | AN10: =AN15+AN28+AN33+AN38+AN43+AN48+AN53+AN58 -> 723.82815 | AO10: =AO15+AO28+AO33+AO38+AO43+AO48+AO53+AO58 -> 739.74791 | AP10: =AP15+AP28+AP33+AP38+AP43+AP48+AP53+AP58 -> 751.70537 | AQ10: =AQ15+AQ28+AQ33+AQ38+AQ43+AQ48+AQ53+AQ58 -> 763.7482 | ... BN10: =BN15+BN28+BN33+BN38+BN43+BN48+BN53+BN58 -> 925.03192 | BP10: =BP15+BP28+BP33+BP38+BP43+BP48+BP53+BP58 -> 646.68484 | BQ10: =BQ15+BQ28+BQ33+BQ38+BQ43+BQ48+BQ53+BQ58 -> 665.3664 | BR10: =BR15+BR28+BR33+BR38+BR43+BR48+BR53+BR58 -> 683.66153 | BS10: =BS15+BS28+BS33+BS38+BS43+BS48+BS53+BS58 -> 702.22916 | BT10: =BT15+BT28+BT33+BT38+BT43+BT48+BT53+BT58 -> 721.07666 | BU10: =BU15+BU28+BU33+BU38+BU43+BU48+BU53+BU58 -> 740.21171 | BV10: =BV15+BV28+BV33+BV38+BV43+BV48+BV53+BV58 -> 755.53392 | BW10: =BW15+BW28+BW33+BW38+BW43+BW48+BW53+BW58 -> 771.06389 | ... CT10: =CT15+CT28+CT33+CT38+CT43+CT48+CT53+CT58 -> 1189.9026 | CW10: =70/CW9 -> 0.079370049
A11: Waste availability (pyrolysis only) | C11: ='Yearly HC Ethylene'!C159 -> m Tons | D11: =D29+D34+D39+D44+D49+D54+D59 -> 36.640987 | E11: =E29+E34+E39+E44+E49+E54+E59 -> 39.371849 | F11: =F29+F34+F39+F44+F49+F54+F59 -> 41.683724 | G11: =G29+G34+G39+G44+G49+G54+G59 -> 43.98677 | H11: =H29+H34+H39+H44+H49+H54+H59 -> 46.265876 | I11: =I29+I34+I39+I44+I49+I54+I59 -> 48.505086 | J11: =J29+J34+J39+J44+J49+J54+J59 -> 50.796752 | K11: =K29+K34+K39+K44+K49+K54+K59 -> 53.13657 | ... AH11: =AH29+AH34+AH39+AH44+AH49+AH54+AH59 -> 57.419773 | AJ11: =AJ29+AJ34+AJ39+AJ44+AJ49+AJ54+AJ59 -> 36.641051 | AK11: =AK29+AK34+AK39+AK44+AK49+AK54+AK59 -> 39.035494 | AL11: =AL29+AL34+AL39+AL44+AL49+AL54+AL59 -> 41.340677 | AM11: =AM29+AM34+AM39+AM44+AM49+AM54+AM59 -> 43.639013 | AN11: =AN29+AN34+AN39+AN44+AN49+AN54+AN59 -> 45.915705 | AO11: =AO29+AO34+AO39+AO44+AO49+AO54+AO59 -> 48.155274 | AP11: =AP29+AP34+AP39+AP44+AP49+AP54+AP59 -> 50.450132 | AQ11: =AQ29+AQ34+AQ39+AQ44+AQ49+AQ54+AQ59 -> 52.797467 | ... BN11: =BN29+BN34+BN39+BN44+BN49+BN54+BN59 -> 65.113621 | BP11: =BP29+BP34+BP39+BP44+BP49+BP54+BP59 -> 0 | BQ11: =BQ29+BQ34+BQ39+BQ44+BQ49+BQ54+BQ59 -> 0 | BR11: =BR29+BR34+BR39+BR44+BR49+BR54+BR59 -> 0 | BS11: =BS29+BS34+BS39+BS44+BS49+BS54+BS59 -> 0 | BT11: =BT29+BT34+BT39+BT44+BT49+BT54+BT59 -> 0 | BU11: =BU29+BU34+BU39+BU44+BU49+BU54+BU59 -> 0 | BV11: =BV29+BV34+BV39+BV44+BV49+BV54+BV59 -> 0 | BW11: =BW29+BW34+BW39+BW44+BW49+BW54+BW59 -> 0 | ... CT11: =CT29+CT34+CT39+CT44+CT49+CT54+CT59 -> 0
CV12: =BN11/(BN10-BN15)*0.8 -> 0.10267962
A13: Ammonia
A14: Ammonia Production BAU | C14: m Tons of NH3 | D14: =Ammonia!D3 -> 185 | E14: =Ammonia!E3 -> 189.74298 | F14: =Ammonia!F3 -> 194.52584 | G14: =Ammonia!G3 -> 199.34916 | H14: =Ammonia!H3 -> 204.21354 | I14: =Ammonia!I3 -> 209.11958 | J14: =Ammonia!J3 -> 213.99116 | K14: =Ammonia!K3 -> 218.88005 | ... AH14: =Ammonia!AH3 -> 524.97872 | AJ14: =D14 -> 185 | AK14: =E14 -> 189.74298 | AL14: =F14 -> 194.52584 | AM14: =G14 -> 199.34916 | AN14: =H14 -> 204.21354 | AO14: =I14 -> 209.11958 | AP14: =J14 -> 213.99116 | AQ14: =K14 -> 218.88005 | ... BN14: =AH14 -> 524.97872 | BP14: =AJ14 -> 185 | BQ14: =AK14 -> 189.74298 | BR14: =AL14 -> 194.52584 | BS14: =AM14 -> 199.34916 | BT14: =AN14 -> 204.21354 | BU14: =AO14 -> 209.11958 | BV14: =AP14 -> 213.99116 | BW14: =AQ14 -> 218.88005 | ... CT14: =BN14 -> 524.97872 | CX14: =(BN14/AJ14)^(1/30)-1 -> 0.035378158
A15: Ammonia Production Circular | C15: m Tons of NH3 | D15: =Ammonia!D4 -> 185 | E15: =Ammonia!E4 -> 189.3777 | F15: =Ammonia!F4 -> 193.79528 | G15: =Ammonia!G4 -> 198.2533 | H15: =Ammonia!H4 -> 202.75237 | I15: =Ammonia!I4 -> 207.29308 | J15: =Ammonia!J4 -> 209.56011 | K15: =Ammonia!K4 -> 211.84904 | ... AH15: =Ammonia!AH4 -> 417.71705 | AJ15: =D15 -> 185 | AK15: =E15 -> 189.3777 | AL15: =F15 -> 193.79528 | AM15: =G15 -> 198.2533 | AN15: =H15 -> 202.75237 | AO15: =I15 -> 207.29308 | AP15: =J15 -> 209.56011 | AQ15: =K15 -> 211.84904 | ... BN15: =AH15 -> 417.71705 | BP15: =AJ15 -> 185 | BQ15: =AK15 -> 189.3777 | BR15: =AL15 -> 193.79528 | BS15: =AM15 -> 198.2533 | BT15: =AN15 -> 202.75237 | BU15: =AO15 -> 207.29308 | BV15: =AP15 -> 209.56011 | BW15: =AQ15 -> 211.84904 | ... CT15: =BN15 -> 417.71705
CY16: Ammonia | CZ16: Ethylene | DA16: Propylene | DB16: Methanol | DC16: Benzene | DD16: Toluene | DE16: Xylene | DF16: Butadiene
A17: Ammonia Production BAU (minus deritavies) | C17: m Tons of NH3 | D17: =Ammonia!D6 -> 73.487083 | E17: =Ammonia!E6 -> 76.195627 | F17: =Ammonia!F6 -> 79.312909 | G17: =Ammonia!G6 -> 82.446225 | H17: =Ammonia!H6 -> 85.595808 | I17: =Ammonia!I6 -> 88.761896 | J17: =Ammonia!J6 -> 94.174267 | K17: =Ammonia!K6 -> 99.577121 | ... AH17: =Ammonia!AH6 -> 434.87859 | AJ17: =D17 -> 73.487083 | AK17: =E17 -> 76.195627 | AL17: =F17 -> 79.312909 | AM17: =G17 -> 82.446225 | AN17: =H17 -> 85.595808 | AO17: =I17 -> 88.761896 | AP17: =J17 -> 94.174267 | AQ17: =K17 -> 99.577121 | ... BN17: =AH17 -> 434.87859 | BP17: =AJ17 -> 73.487083 | BQ17: =AK17 -> 76.195627 | BR17: =AL17 -> 79.312909 | BS17: =AM17 -> 82.446225 | BT17: =AN17 -> 85.595808 | BU17: =AO17 -> 88.761896 | BV17: =AP17 -> 94.174267 | BW17: =AQ17 -> 99.577121 | ... CT17: =BN17 -> 434.87859
A18: Ammonia Production Circular (minus derivatives) | C18: m Tons of NH3 | D18: =Ammonia!D7 -> 73.487083 | E18: =Ammonia!E7 -> 75.830355 | F18: =Ammonia!F7 -> 78.58235 | G18: =Ammonia!G7 -> 81.350366 | H18: =Ammonia!H7 -> 84.134635 | I18: =Ammonia!I7 -> 86.935396 | J18: =Ammonia!J7 -> 89.743218 | K18: =Ammonia!K7 -> 92.546113 | ... AH18: =Ammonia!AH7 -> 327.61692 | AJ18: =D18 -> 73.487083 | AK18: =E18 -> 75.830355 | AL18: =F18 -> 78.58235 | AM18: =G18 -> 81.350366 | AN18: =H18 -> 84.134635 | AO18: =I18 -> 86.935396 | AP18: =J18 -> 89.743218 | AQ18: =K18 -> 92.546113 | ... BN18: =AH18 -> 327.61692 | BP18: =AJ18 -> 73.487083 | BQ18: =AK18 -> 75.830355 | BR18: =AL18 -> 78.58235 | BS18: =AM18 -> 81.350366 | BT18: =AN18 -> 84.134635 | BU18: =AO18 -> 86.935396 | BV18: =AP18 -> 89.743218 | BW18: =AQ18 -> 92.546113 | ... CT18: =BN18 -> 327.61692 | CX18: 2020 | CY18: =D14 -> 185 | CZ18: =D27 -> 162.69231 | DA18: =AJ32 -> 111.92308 | DB18: =AJ37 -> 70.960267 | DC18: =AJ42 -> 51.832301 | DD18: =AJ47 -> 14.015261 | DE18: =AJ52 -> 50.261625 | DF18: =AJ57 -> 14.947368
CX19: 2050 BAU | CY19: =AH14 -> 524.97872 | CZ19: =AH27 -> 280.10459 | DA19: =BN32 -> 162.9241 | DB19: =BN37 -> 145.59946 | DC19: =BN42 -> 71.872008 | DD19: =BN47 -> 19.433923 | DE19: =BN52 -> 69.694069 | DF19: =BN57 -> 25.054959
A20: Urea Production BAU | C20: m Tons of UREA | D20: =Ammonia!D9 -> 178.3 | E20: =Ammonia!E9 -> 181.47413 | F20: =Ammonia!F9 -> 184.13609 | G20: =Ammonia!G9 -> 186.8371 | H20: =Ammonia!H9 -> 189.57773 | I20: =Ammonia!I9 -> 192.35857 | J20: =Ammonia!J9 -> 195.18019 | K20: =Ammonia!K9 -> 198.0432 | ... AH20: =Ammonia!AH9 -> 233.53851 | AJ20: =D20 -> 178.3 | AK20: =E20 -> 181.47413 | AL20: =F20 -> 184.13609 | AM20: =G20 -> 186.8371 | AN20: =H20 -> 189.57773 | AO20: =I20 -> 192.35857 | AP20: =J20 -> 195.18019 | AQ20: =K20 -> 198.0432 | ... BN20: =AH20 -> 233.53851 | BP20: =AJ20 -> 178.3 | BQ20: =AK20 -> 181.47413 | BR20: =AL20 -> 184.13609 | BS20: =AM20 -> 186.8371 | BT20: =AN20 -> 189.57773 | BU20: =AO20 -> 192.35857 | BV20: =AP20 -> 195.18019 | BW20: =AQ20 -> 198.0432 | ... CT20: =BN20 -> 233.53851 | CX20: 2050 Most Economic | CY20: =BN15 -> 417.71705 | CZ20: =BN28 -> 179.24238 | DA20: =BN33 -> 113.37364 | DB20: =BN38+'Final Exhibits'!E22 -> 375.20259 | DC20: =BN43 -> 47.492425 | DD20: =BN48 -> 12.841775 | DE20: =BN53 -> 46.053261 | DF20: =BN58 -> 23.108795
